Workbook

Sheet Scorecard
A1: Outliers | B1: 46023 | C1: 46054 | D1: 46082 | E1: 46113 | F1: 46143 | G1: 46174 | H1: 46204 | I1: 46235 | J1: 46266 | K1: 46296 | L1: 46327 | M1: 46357 | S1: 46023 | T1: 46054 | U1: 46082 | V1: 46113 | W1: 46143 | X1: 46174 | Y1: 46204 | Z1: 46235 | AA1: 46266 | AB1: 46296 | AC1: 46327 | AD1: 46357 | AE1: 46023 | AF1: 46023 | AG1: 46023 | AH1: 46054 | AI1: 46082 | AJ1: 46113 | AK1: 46143 | AL1: 46174 | AM1: 46204 | AN1: 46235 | AO1: 46266 | AP1: 46296 | AQ1: 46327 | AR1: 46357 | AS1: 46023 | AT1: 46023 | AU1: 46023 | AV1: 46054 | AW1: 46082 | AX1: 46113 | AY1: 46143 | AZ1: 46174 | BA1: 46204 | BB1: 46235 | BC1: 46266 | BD1: 46296 | BE1: 46327 | BF1: 46357 | BG1: 46023 | BH1: 46023 | BI1: 46023 | BJ1: 46054 | BK1: 46082 | BL1: 46113 | BM1: 46143 | BN1: 46174 | BO1: 46204 | BP1: 46235 | BQ1: 46266 | BR1: 46296 | BS1: 46327 | BT1: 46357 | BU1: 46023 | BV1: 46023 | BW1: 46023 | BX1: 46113 | BY1: 46204 | BZ1: 46296 | CC1: 46023
A2: {=_xlfn.QUARTILE.INC(IF(Base!$V:$V>0,Base!$V:$V),3)+(1.5*(_xlfn.QUARTILE.INC(IF(Base!$V:$V>0,Base!$V:$V),3)-_xlfn.QUARTILE.INC(IF(Base!$V:$V>0,Base!$V:$V),1)))} -> 17 | B2: 46053 | C2: 46081 | D2: 46112 | E2: 46142 | F2: 46173 | G2: 46203 | H2: 46234 | I2: 46265 | J2: 46295 | K2: 46326 | L2: 46356 | M2: 46387 | S2: 46053 | T2: 46081 | U2: 46112 | V2: 46142 | W2: 46173 | X2: 46203 | Y2: 46234 | Z2: 46265 | AA2: 46295 | AB2: 46326 | AC2: 46356 | AD2: 46387 | AE2: 46112 | AF2: 46112 | AG2: 46053 | AH2: 46081 | AI2: 46112 | AJ2: 46142 | AK2: 46173 | AL2: 46203 | AM2: 46234 | AN2: 46265 | AO2: 46295 | AP2: 46326 | AQ2: 46356 | AR2: 46387 | AS2: 46112 | AT2: 46112 | AU2: 46053 | AV2: 46081 | AW2: 46112 | AX2: 46142 | AY2: 46173 | AZ2: 46203 | BA2: 46234 | BB2: 46265 | BC2: 46295 | BD2: 46326 | BE2: 46356 | BF2: 46387 | BG2: 46112 | BH2: 46112 | BI2: 46053 | BJ2: 46081 | BK2: 46112 | BL2: 46142 | BM2: 46173 | BN2: 46203 | BO2: 46234 | BP2: 46265 | BQ2: 46295 | BR2: 46326 | BS2: 46356 | BT2: 46387 | BU2: 46112 | BV2: 46112 | BW2: 46112 | BX2: 46203 | BY2: 46295 | BZ2: 41274 | CC2: 46112
AE4: Growth Levers (80%) | BW4: SP Satisfaction (20%)
A5: OM | B5: Jan | C5: Fev | D5: Mar | E5: Apr | F5: May | G5: Jun | H5: Jul | I5: Aug | J5: Sep | K5: Oct | L5: Nov | M5: Dec | N5: Managed SPs | O5: #survey Q1 | P5: # survey Q2 | Q5: # survey Q3 | R5: # survey Q4 | S5: Jan | T5: Fev | U5: Mar | V5: Apr | W5: May | X5: Jun | Y5: Jul | Z5: Aug | AA5: Sep | AB5: Oct | AC5: Nov | AD5: Dec | AE5: Adoption Real | AF5: Nota Adoption | AG5: Jan | AH5: Fev | AI5: Mar | AJ5: Apr | AK5: May | AL5: Jun | AM5: Jul | AN5: Aug | AO5: Sep | AP5: Oct | AQ5: Nov | AR5: Dec | AS5: TTR Real | AT5: Nota TTR | AU5: Jan | AV5: Fev | AW5: Mar | AX5: Apr | AY5: May | AZ5: Jun | BA5: Jul | BB5: Aug | BC5: Sep | BD5: Oct | BE5: Nov | BF5: Dec | BG5: Issue % real | BH5: Nota Issue % | BI5: Jan | BJ5: Fev | BK5: Mar | BL5: Apr | BM5: May | BN5: Jun | BO5: Jul | BP5: Aug | BQ5: Sep | BR5: Oct | BS5: Nov | BT5: Dec | BU5: Strikes | BV5: Nota strikes | BW5: Q1 | BX5: Q2 | BY5: Q3 | BZ5: Q4 | CA5: Survey real | CB5: Nota Survey | CC5: Final Score
A6: fpereluc | B6: =COUNTIFS('Sellers Pro'!$F:$F,Scorecard!$A6,'Sellers Pro'!$Q:$Q,"<"&Scorecard!B$2,'Sellers Pro'!$O:$O,"1") -> 46 | C6: =COUNTIFS('Sellers Pro'!$F:$F,Scorecard!$A6,'Sellers Pro'!$Q:$Q,"<"&Scorecard!C$2,'Sellers Pro'!$O:$O,"1") -> 48 | D6: =COUNTIFS('Sellers Pro'!$F:$F,Scorecard!$A6,'Sellers Pro'!$Q:$Q,"<"&Scorecard!D$2,'Sellers Pro'!$O:$O,"1") -> 48 | E6: =COUNTIFS('Sellers Pro'!$F:$F,Scorecard!$A6,'Sellers Pro'!$Q:$Q,"<"&Scorecard!E$2,'Sellers Pro'!$O:$O,"1") -> 48 | F6: =COUNTIFS('Sellers Pro'!$F:$F,Scorecard!$A6,'Sellers Pro'!$Q:$Q,"<"&Scorecard!F$2,'Sellers Pro'!$O:$O,"1") -> 48 | G6: =COUNTIFS('Sellers Pro'!$F:$F,Scorecard!$A6,'Sellers Pro'!$Q:$Q,"<"&Scorecard!G$2,'Sellers Pro'!$O:$O,"1") -> 48 | H6: =COUNTIFS('Sellers Pro'!$F:$F,Scorecard!$A6,'Sellers Pro'!$Q:$Q,"<"&Scorecard!H$2,'Sellers Pro'!$O:$O,"1") -> 48 | I6: =COUNTIFS('Sellers Pro'!$F:$F,Scorecard!$A6,'Sellers Pro'!$Q:$Q,"<"&Scorecard!I$2,'Sellers Pro'!$O:$O,"1") -> 48 | ... M6: =COUNTIFS('Sellers Pro'!$F:$F,Scorecard!$A6,'Sellers Pro'!$Q:$Q,"<"&Scorecard!M$2,'Sellers Pro'!$O:$O,"1") -> 48 | N6: =IFERROR(AVERAGEIF(B6:M6,">0",B6:M6),"-") -> 47.833333 | O6: =COUNTIFS('Survey Q1'!$G:$G,"="&1,'Survey Q1'!$C:$C,Scorecard!$A6) -> 10 | P6: =COUNTIFS('Survey Q2'!$G:$G,"="&1,'Survey Q1'!$C:$C,Scorecard!$A6) -> 0 | Q6: =COUNTIFS('Survey Q3'!$G:$G,"="&1,'Survey Q1'!$C:$C,Scorecard!$A6) -> 0 | R6: =COUNTIFS('Survey Q4'!$G:$G,"="&1,'Survey Q1'!$C:$C,Scorecard!$A6) -> 0 | S6: =IFERROR(COUNTIFS(Base!$J:$J,Scorecard!$A6,Base!$E:$E,">"&S$1,Base!$E:$E,"<"&S$2,Base!$AH:$AH,"1",Base!$A:$A,"2026")/$N6,"0") -> 0.48083624 | T6: =IFERROR(COUNTIFS(Base!$J:$J,Scorecard!$A6,Base!$E:$E,">"&T$1,Base!$E:$E,"<"&T$2,Base!$AH:$AH,"1",Base!$A:$A,"2026")/$N6,"0") -> 0.68989547 | U6: =IFERROR(COUNTIFS(Base!$J:$J,Scorecard!$A6,Base!$E:$E,">"&U$1,Base!$E:$E,"<"&U$2,Base!$AH:$AH,"1",Base!$A:$A,"2026")/$N6,"0") -> 0.58536585 | V6: =IFERROR(COUNTIFS(Base!$J:$J,Scorecard!$A6,Base!$E:$E,">"&V$1,Base!$E:$E,"<"&V$2,Base!$AH:$AH,"1",Base!$A:$A,"2026")/$N6,"0") -> 0 | W6: =IFERROR(COUNTIFS(Base!$J:$J,Scorecard!$A6,Base!$E:$E,">"&W$1,Base!$E:$E,"<"&W$2,Base!$AH:$AH,"1",Base!$A:$A,"2026")/$N6,"0") -> 0 | X6: =IFERROR(COUNTIFS(Base!$J:$J,Scorecard!$A6,Base!$E:$E,">"&X$1,Base!$E:$E,"<"&X$2,Base!$AH:$AH,"1",Base!$A:$A,"2026")/$N6,"0") -> 0 | Y6: =IFERROR(COUNTIFS(Base!$J:$J,Scorecard!$A6,Base!$E:$E,">"&Y$1,Base!$E:$E,"<"&Y$2,Base!$AH:$AH,"1",Base!$A:$A,"2026")/$N6,"0") -> 0 | Z6: =IFERROR(COUNTIFS(Base!$J:$J,Scorecard!$A6,Base!$E:$E,">"&Z$1,Base!$E:$E,"<"&Z$2,Base!$AH:$AH,"1",Base!$A:$A,"2026")/$N6,"0") -> 0 | ... AD6: =IFERROR(COUNTIFS(Base!$J:$J,Scorecard!$A6,Base!$E:$E,">"&AD$1,Base!$E:$E,"<"&AD$2,Base!$AH:$AH,"1",Base!$A:$A,"2026")/$N6,"0") -> 0 | AE6: =IFERROR(AVERAGEIF(S6:AD6,">0",S6:AD6),"-") -> 0.58536585 | AF6: =IF(AE6="-",0,IF(AE6<Goals!$K$6,Goals!$L$7,IF(AE6<Goals!$K$5,Goals!$L$6,IF(AE6<Goals!$K$4,Goals!$L$5,IF(AE6<Goals!$K$3,Goals!$L$4,IF(AE6<Goals!$K$2,Goals!$L$3,Goals!$L$2)))))) -> 0.5 | AG6: =IFERROR(AVERAGEIFS(Base!$V:$V,Base!$J:$J,Scorecard!$A6,Base!$E:$E,">"&AG$1,Base!$G:$G,"<"&AG$2,Base!$V:$V,"<"&$A$2,Base!$V:$V,">"&0,Base!$A:$A,"2026"),"0") -> 3.25 | AH6: =IFERROR(AVERAGEIFS(Base!$V:$V,Base!$J:$J,Scorecard!$A6,Base!$E:$E,">"&AH$1,Base!$G:$G,"<"&AH$2,Base!$V:$V,"<"&$A$2,Base!$V:$V,">"&0,Base!$A:$A,"2026"),"0") -> 4.859375 | AI6: =IFERROR(AVERAGEIFS(Base!$V:$V,Base!$J:$J,Scorecard!$A6,Base!$E:$E,">"&AI$1,Base!$G:$G,"<"&AI$2,Base!$V:$V,"<"&$A$2,Base!$V:$V,">"&0,Base!$A:$A,"2026"),"0") -> 3.2678571 | AJ6: =IFERROR(AVERAGEIFS(Base!$V:$V,Base!$J:$J,Scorecard!$A6,Base!$E:$E,">"&AJ$1,Base!$G:$G,"<"&AJ$2,Base!$V:$V,"<"&$A$2,Base!$V:$V,">"&0,Base!$A:$A,"2026"),"0") -> 0 | AK6: =IFERROR(AVERAGEIFS(Base!$V:$V,Base!$J:$J,Scorecard!$A6,Base!$E:$E,">"&AK$1,Base!$G:$G,"<"&AK$2,Base!$V:$V,"<"&$A$2,Base!$V:$V,">"&0,Base!$A:$A,"2026"),"0") -> 0 | AL6: =IFERROR(AVERAGEIFS(Base!$V:$V,Base!$J:$J,Scorecard!$A6,Base!$E:$E,">"&AL$1,Base!$G:$G,"<"&AL$2,Base!$V:$V,"<"&$A$2,Base!$V:$V,">"&0,Base!$A:$A,"2026"),"0") -> 0 | AM6: =IFERROR(AVERAGEIFS(Base!$V:$V,Base!$J:$J,Scorecard!$A6,Base!$E:$E,">"&AM$1,Base!$G:$G,"<"&AM$2,Base!$V:$V,"<"&$A$2,Base!$V:$V,">"&0,Base!$A:$A,"2026"),"0") -> 0 | AN6: =IFERROR(AVERAGEIFS(Base!$V:$V,Base!$J:$J,Scorecard!$A6,Base!$E:$E,">"&AN$1,Base!$G:$G,"<"&AN$2,Base!$V:$V,"<"&$A$2,Base!$V:$V,">"&0,Base!$A:$A,"2026"),"0") -> 0 | ... AR6: =IFERROR(AVERAGEIFS(Base!$V:$V,Base!$J:$J,Scorecard!$A6,Base!$E:$E,">"&AR$1,Base!$G:$G,"<"&AR$2,Base!$V:$V,"<"&$A$2,Base!$V:$V,">"&0,Base!$A:$A,"2026"),"0") -> 0 | AS6: =IFERROR(AVERAGEIF(AG6:AR6,">0",AG6:AR6),"-") -> 3.7924107 | AT6: =IF(AS6="-",0,IF(AS6>Goals!$N$6,Goals!$O$7,IF(AS6>Goals!$N$5,Goals!$O$6,IF(AS6>Goals!$N$4,Goals!$O$5,IF(AS6>Goals!$N$3,Goals!$O$4,IF(AS6>Goals!$N$2,Goals!$O$3,Goals!$O$2)))))) -> 0.8 | AU6: =IFERROR(COUNTIFS(Base!$E:$E,">"&AU$1,Base!$G:$G,"<"&AU$2,Base!$J:$J,Scorecard!$A6,Base!$T:$T,"COMPLETED")/COUNTIFS(Base!$E:$E,">"&AU$1,Base!$E:$E,"<"&AU$2,Base!$J:$J,Scorecard!$A6),"0") -> 0.7 | AV6: =IFERROR(COUNTIFS(Base!$E:$E,">"&AV$1,Base!$G:$G,"<"&AV$2,Base!$J:$J,Scorecard!$A6,Base!$T:$T,"COMPLETED")/COUNTIFS(Base!$E:$E,">"&AV$1,Base!$E:$E,"<"&AV$2,Base!$J:$J,Scorecard!$A6),"0") -> 0.71875 | AW6: =IFERROR(COUNTIFS(Base!$E:$E,">"&AW$1,Base!$G:$G,"<"&AW$2,Base!$J:$J,Scorecard!$A6,Base!$T:$T,"COMPLETED")/COUNTIFS(Base!$E:$E,">"&AW$1,Base!$E:$E,"<"&AW$2,Base!$J:$J,Scorecard!$A6),"0") -> 0.68181818 | AX6: =IFERROR(COUNTIFS(Base!$E:$E,">"&AX$1,Base!$G:$G,"<"&AX$2,Base!$J:$J,Scorecard!$A6,Base!$T:$T,"COMPLETED")/COUNTIFS(Base!$E:$E,">"&AX$1,Base!$E:$E,"<"&AX$2,Base!$J:$J,Scorecard!$A6),"0") -> 0 | AY6: =IFERROR(COUNTIFS(Base!$E:$E,">"&AY$1,Base!$G:$G,"<"&AY$2,Base!$J:$J,Scorecard!$A6,Base!$T:$T,"COMPLETED")/COUNTIFS(Base!$E:$E,">"&AY$1,Base!$E:$E,"<"&AY$2,Base!$J:$J,Scorecard!$A6),"0") -> 0 | AZ6: =IFERROR(COUNTIFS(Base!$E:$E,">"&AZ$1,Base!$G:$G,"<"&AZ$2,Base!$J:$J,Scorecard!$A6,Base!$T:$T,"COMPLETED")/COUNTIFS(Base!$E:$E,">"&AZ$1,Base!$E:$E,"<"&AZ$2,Base!$J:$J,Scorecard!$A6),"0") -> 0 | BA6: =IFERROR(COUNTIFS(Base!$E:$E,">"&BA$1,Base!$G:$G,"<"&BA$2,Base!$J:$J,Scorecard!$A6,Base!$T:$T,"COMPLETED")/COUNTIFS(Base!$E:$E,">"&BA$1,Base!$E:$E,"<"&BA$2,Base!$J:$J,Scorecard!$A6),"0") -> 0 | BB6: =IFERROR(COUNTIFS(Base!$E:$E,">"&BB$1,Base!$G:$G,"<"&BB$2,Base!$J:$J,Scorecard!$A6,Base!$T:$T,"COMPLETED")/COUNTIFS(Base!$E:$E,">"&BB$1,Base!$E:$E,"<"&BB$2,Base!$J:$J,Scorecard!$A6),"0") -> 0 | ... BF6: =IFERROR(COUNTIFS(Base!$E:$E,">"&BF$1,Base!$G:$G,"<"&BF$2,Base!$J:$J,Scorecard!$A6,Base!$T:$T,"COMPLETED")/COUNTIFS(Base!$E:$E,">"&BF$1,Base!$E:$E,"<"&BF$2,Base!$J:$J,Scorecard!$A6),"0") -> 0 | BG6: =IFERROR(AVERAGEIF(AU6:BF6,">0",AU6:BF6),"-") -> 0.70018939 | BH6: =IF(BG6="-",0,IF(BG6<Goals!$Q$6,Goals!$R$7,IF(BG6<Goals!$Q$5,Goals!$R$6,IF(BG6<Goals!$Q$4,Goals!$R$5,IF(BG6<Goals!$Q$3,Goals!$R$4,IF(BG6<Goals!$Q$2,Goals!$R$3,Goals!$R$2)))))) -> 0.5 | BI6: =COUNTIFS(Strikes!$A:$A,Scorecard!$A6,Strikes!$C:$C,">"&Scorecard!BI$1,Strikes!$C:$C,"<"&Scorecard!BI$2) -> 0 | BJ6: =COUNTIFS(Strikes!$A:$A,Scorecard!$A6,Strikes!$C:$C,">"&Scorecard!BJ$1,Strikes!$C:$C,"<"&Scorecard!BJ$2) -> 0 | BK6: =COUNTIFS(Strikes!$A:$A,Scorecard!$A6,Strikes!$C:$C,">"&Scorecard!BK$1,Strikes!$C:$C,"<"&Scorecard!BK$2) -> 0 | BL6: =COUNTIFS(Strikes!$A:$A,Scorecard!$A6,Strikes!$C:$C,">"&Scorecard!BL$1,Strikes!$C:$C,"<"&Scorecard!BL$2) -> 0 | BM6: =COUNTIFS(Strikes!$A:$A,Scorecard!$A6,Strikes!$C:$C,">"&Scorecard!BM$1,Strikes!$C:$C,"<"&Scorecard!BM$2) -> 0 | BN6: =COUNTIFS(Strikes!$A:$A,Scorecard!$A6,Strikes!$C:$C,">"&Scorecard!BN$1,Strikes!$C:$C,"<"&Scorecard!BN$2) -> 0 | BO6: =COUNTIFS(Strikes!$A:$A,Scorecard!$A6,Strikes!$C:$C,">"&Scorecard!BO$1,Strikes!$C:$C,"<"&Scorecard!BO$2) -> 0 | BP6: =COUNTIFS(Strikes!$A:$A,Scorecard!$A6,Strikes!$C:$C,">"&Scorecard!BP$1,Strikes!$C:$C,"<"&Scorecard!BP$2) -> 0 | ... BT6: =COUNTIFS(Strikes!$A:$A,Scorecard!$A6,Strikes!$C:$C,">"&Scorecard!BT$1,Strikes!$C:$C,"<"&Scorecard!BT$2) -> 0 | BU6: =IFERROR(AVERAGEIF(BI6:BT6,">0",BI6:BT6),"0") -> 0 | BV6: =IF(BU6="-",0,IF(BU6=Goals!$H$7,Goals!$I$7,IF(BU6=Goals!$H$6,Goals!$I$6,IF(BU6=Goals!$H$5,Goals!$I$5,IF(BU6=Goals!$H$4,Goals!$I$4,IF(BU6=Goals!$H$3,Goals!$I$3,Goals!$I$2)))))) -> 1.2 | BW6: =IFERROR(COUNTIFS('Survey Q1'!$C:$C,Scorecard!$A6,'Survey Q1'!$F:$F,"1")/O6,"0") -> 0.7 | BX6: =IFERROR(COUNTIFS('Survey Q2'!$C:$C,Scorecard!$A6,'Survey Q1'!$F:$F,"1")/P6,"0") -> 0 | BY6: =IFERROR(COUNTIFS('Survey Q3'!$C:$C,Scorecard!$A6,'Survey Q1'!$F:$F,"1")/Q6,"0") -> 0 | BZ6: =IFERROR(COUNTIFS('Survey Q4'!$C:$C,Scorecard!$A6,'Survey Q1'!$F:$F,"1")/R6,"0") -> 0 | CA6: =IFERROR(AVERAGEIF(BW6:BZ6,">0",BW6:BZ6),"-") -> 0.7 | CB6: =IF(CA6="-",0,IF(CA6<Goals!$T$6,Goals!$U$7,IF(CA6<Goals!$T$5,Goals!$U$6,IF(CA6<Goals!$T$4,Goals!$U$5,IF(CA6<Goals!$T$3,Goals!$U$4,IF(CA6<Goals!$T$2,Goals!$U$3,Goals!$U$2)))))) -> 0 | CC6: =Scorecard!AF6*Goals!$C$3+Scorecard!AT6*Goals!$D$3+Scorecard!BH6*Goals!$E$3+Scorecard!CB6*Goals!$B$3+BV6*Goals!$F$3 -> 0.51
A7: gomrodrd | B7: =COUNTIFS('Sellers Pro'!$F:$F,Scorecard!$A7,'Sellers Pro'!$Q:$Q,"<"&Scorecard!B$2,'Sellers Pro'!$O:$O,"1") -> 39 | C7: =COUNTIFS('Sellers Pro'!$F:$F,Scorecard!$A7,'Sellers Pro'!$Q:$Q,"<"&Scorecard!C$2,'Sellers Pro'!$O:$O,"1") -> 39 | D7: =COUNTIFS('Sellers Pro'!$F:$F,Scorecard!$A7,'Sellers Pro'!$Q:$Q,"<"&Scorecard!D$2,'Sellers Pro'!$O:$O,"1") -> 39 | E7: =COUNTIFS('Sellers Pro'!$F:$F,Scorecard!$A7,'Sellers Pro'!$Q:$Q,"<"&Scorecard!E$2,'Sellers Pro'!$O:$O,"1") -> 39 | F7: =COUNTIFS('Sellers Pro'!$F:$F,Scorecard!$A7,'Sellers Pro'!$Q:$Q,"<"&Scorecard!F$2,'Sellers Pro'!$O:$O,"1") -> 39 | G7: =COUNTIFS('Sellers Pro'!$F:$F,Scorecard!$A7,'Sellers Pro'!$Q:$Q,"<"&Scorecard!G$2,'Sellers Pro'!$O:$O,"1") -> 39 | H7: =COUNTIFS('Sellers Pro'!$F:$F,Scorecard!$A7,'Sellers Pro'!$Q:$Q,"<"&Scorecard!H$2,'Sellers Pro'!$O:$O,"1") -> 39 | I7: =COUNTIFS('Sellers Pro'!$F:$F,Scorecard!$A7,'Sellers Pro'!$Q:$Q,"<"&Scorecard!I$2,'Sellers Pro'!$O:$O,"1") -> 39 | ... M7: =COUNTIFS('Sellers Pro'!$F:$F,Scorecard!$A7,'Sellers Pro'!$Q:$Q,"<"&Scorecard!M$2,'Sellers Pro'!$O:$O,"1") -> 39 | N7: =IFERROR(AVERAGEIF(B7:M7,">0",B7:M7),"-") -> 39 | O7: =COUNTIFS('Survey Q1'!$G:$G,"="&1,'Survey Q1'!$C:$C,Scorecard!$A7) -> 19 | P7: =COUNTIFS('Survey Q2'!$G:$G,"="&1,'Survey Q1'!$C:$C,Scorecard!$A7) -> 0 | Q7: =COUNTIFS('Survey Q3'!$G:$G,"="&1,'Survey Q1'!$C:$C,Scorecard!$A7) -> 0 | R7: =COUNTIFS('Survey Q4'!$G:$G,"="&1,'Survey Q1'!$C:$C,Scorecard!$A7) -> 0 | S7: =IFERROR(COUNTIFS(Base!$J:$J,Scorecard!$A7,Base!$E:$E,">"&S$1,Base!$E:$E,"<"&S$2,Base!$AH:$AH,"1",Base!$A:$A,"2026")/$N7,"0") -> 0.64102564 | T7: =IFERROR(COUNTIFS(Base!$J:$J,Scorecard!$A7,Base!$E:$E,">"&T$1,Base!$E:$E,"<"&T$2,Base!$AH:$AH,"1",Base!$A:$A,"2026")/$N7,"0") -> 0.53846154 | U7: =IFERROR(COUNTIFS(Base!$J:$J,Scorecard!$A7,Base!$E:$E,">"&U$1,Base!$E:$E,"<"&U$2,Base!$AH:$AH,"1",Base!$A:$A,"2026")/$N7,"0") -> 0.66666667 | V7: =IFERROR(COUNTIFS(Base!$J:$J,Scorecard!$A7,Base!$E:$E,">"&V$1,Base!$E:$E,"<"&V$2,Base!$AH:$AH,"1",Base!$A:$A,"2026")/$N7,"0") -> 0 | W7: =IFERROR(COUNTIFS(Base!$J:$J,Scorecard!$A7,Base!$E:$E,">"&W$1,Base!$E:$E,"<"&W$2,Base!$AH:$AH,"1",Base!$A:$A,"2026")/$N7,"0") -> 0 | X7: =IFERROR(COUNTIFS(Base!$J:$J,Scorecard!$A7,Base!$E:$E,">"&X$1,Base!$E:$E,"<"&X$2,Base!$AH:$AH,"1",Base!$A:$A,"2026")/$N7,"0") -> 0 | Y7: =IFERROR(COUNTIFS(Base!$J:$J,Scorecard!$A7,Base!$E:$E,">"&Y$1,Base!$E:$E,"<"&Y$2,Base!$AH:$AH,"1",Base!$A:$A,"2026")/$N7,"0") -> 0 | Z7: =IFERROR(COUNTIFS(Base!$J:$J,Scorecard!$A7,Base!$E:$E,">"&Z$1,Base!$E:$E,"<"&Z$2,Base!$AH:$AH,"1",Base!$A:$A,"2026")/$N7,"0") -> 0 | ... AD7: =IFERROR(COUNTIFS(Base!$J:$J,Scorecard!$A7,Base!$E:$E,">"&AD$1,Base!$E:$E,"<"&AD$2,Base!$AH:$AH,"1",Base!$A:$A,"2026")/$N7,"0") -> 0 | AE7: =IFERROR(AVERAGEIF(S7:AD7,">0",S7:AD7),"-") -> 0.61538462 | AF7: =IF(AE7="-",0,IF(AE7<Goals!$K$6,Goals!$L$7,IF(AE7<Goals!$K$5,Goals!$L$6,IF(AE7<Goals!$K$4,Goals!$L$5,IF(AE7<Goals!$K$3,Goals!$L$4,IF(AE7<Goals!$K$2,Goals!$L$3,Goals!$L$2)))))) -> 0.5 | AG7: =IFERROR(AVERAGEIFS(Base!$V:$V,Base!$J:$J,Scorecard!$A7,Base!$E:$E,">"&AG$1,Base!$G:$G,"<"&AG$2,Base!$V:$V,"<"&$A$2,Base!$V:$V,">"&0,Base!$A:$A,"2026"),"0") -> 3.6944444 | AH7: =IFERROR(AVERAGEIFS(Base!$V:$V,Base!$J:$J,Scorecard!$A7,Base!$E:$E,">"&AH$1,Base!$G:$G,"<"&AH$2,Base!$V:$V,"<"&$A$2,Base!$V:$V,">"&0,Base!$A:$A,"2026"),"0") -> 3.2142857 | AI7: =IFERROR(AVERAGEIFS(Base!$V:$V,Base!$J:$J,Scorecard!$A7,Base!$E:$E,">"&AI$1,Base!$G:$G,"<"&AI$2,Base!$V:$V,"<"&$A$2,Base!$V:$V,">"&0,Base!$A:$A,"2026"),"0") -> 3.075 | AJ7: =IFERROR(AVERAGEIFS(Base!$V:$V,Base!$J:$J,Scorecard!$A7,Base!$E:$E,">"&AJ$1,Base!$G:$G,"<"&AJ$2,Base!$V:$V,"<"&$A$2,Base!$V:$V,">"&0,Base!$A:$A,"2026"),"0") -> 0 | AK7: =IFERROR(AVERAGEIFS(Base!$V:$V,Base!$J:$J,Scorecard!$A7,Base!$E:$E,">"&AK$1,Base!$G:$G,"<"&AK$2,Base!$V:$V,"<"&$A$2,Base!$V:$V,">"&0,Base!$A:$A,"2026"),"0") -> 0 | AL7: =IFERROR(AVERAGEIFS(Base!$V:$V,Base!$J:$J,Scorecard!$A7,Base!$E:$E,">"&AL$1,Base!$G:$G,"<"&AL$2,Base!$V:$V,"<"&$A$2,Base!$V:$V,">"&0,Base!$A:$A,"2026"),"0") -> 0 | AM7: =IFERROR(AVERAGEIFS(Base!$V:$V,Base!$J:$J,Scorecard!$A7,Base!$E:$E,">"&AM$1,Base!$G:$G,"<"&AM$2,Base!$V:$V,"<"&$A$2,Base!$V:$V,">"&0,Base!$A:$A,"2026"),"0") -> 0 | AN7: =IFERROR(AVERAGEIFS(Base!$V:$V,Base!$J:$J,Scorecard!$A7,Base!$E:$E,">"&AN$1,Base!$G:$G,"<"&AN$2,Base!$V:$V,"<"&$A$2,Base!$V:$V,">"&0,Base!$A:$A,"2026"),"0") -> 0 | ... AR7: =IFERROR(AVERAGEIFS(Base!$V:$V,Base!$J:$J,Scorecard!$A7,Base!$E:$E,">"&AR$1,Base!$G:$G,"<"&AR$2,Base!$V:$V,"<"&$A$2,Base!$V:$V,">"&0,Base!$A:$A,"2026"),"0") -> 0 | AS7: =IFERROR(AVERAGEIF(AG7:AR7,">0",AG7:AR7),"-") -> 3.3279101 | AT7: =IF(AS7="-",0,IF(AS7>Goals!$N$6,Goals!$O$7,IF(AS7>Goals!$N$5,Goals!$O$6,IF(AS7>Goals!$N$4,Goals!$O$5,IF(AS7>Goals!$N$3,Goals!$O$4,IF(AS7>Goals!$N$2,Goals!$O$3,Goals!$O$2)))))) -> 0.8 | AU7: =IFERROR(COUNTIFS(Base!$E:$E,">"&AU$1,Base!$G:$G,"<"&AU$2,Base!$J:$J,Scorecard!$A7,Base!$T:$T,"COMPLETED")/COUNTIFS(Base!$E:$E,">"&AU$1,Base!$E:$E,"<"&AU$2,Base!$J:$J,Scorecard!$A7),"0") -> 0.75 | AV7: =IFERROR(COUNTIFS(Base!$E:$E,">"&AV$1,Base!$G:$G,"<"&AV$2,Base!$J:$J,Scorecard!$A7,Base!$T:$T,"COMPLETED")/COUNTIFS(Base!$E:$E,">"&AV$1,Base!$E:$E,"<"&AV$2,Base!$J:$J,Scorecard!$A7),"0") -> 0.72580645 | AW7: =IFERROR(COUNTIFS(Base!$E:$E,">"&AW$1,Base!$G:$G,"<"&AW$2,Base!$J:$J,Scorecard!$A7,Base!$T:$T,"COMPLETED")/COUNTIFS(Base!$E:$E,">"&AW$1,Base!$E:$E,"<"&AW$2,Base!$J:$J,Scorecard!$A7),"0") -> 0.65909091 | AX7: =IFERROR(COUNTIFS(Base!$E:$E,">"&AX$1,Base!$G:$G,"<"&AX$2,Base!$J:$J,Scorecard!$A7,Base!$T:$T,"COMPLETED")/COUNTIFS(Base!$E:$E,">"&AX$1,Base!$E:$E,"<"&AX$2,Base!$J:$J,Scorecard!$A7),"0") -> 0 | AY7: =IFERROR(COUNTIFS(Base!$E:$E,">"&AY$1,Base!$G:$G,"<"&AY$2,Base!$J:$J,Scorecard!$A7,Base!$T:$T,"COMPLETED")/COUNTIFS(Base!$E:$E,">"&AY$1,Base!$E:$E,"<"&AY$2,Base!$J:$J,Scorecard!$A7),"0") -> 0 | AZ7: =IFERROR(COUNTIFS(Base!$E:$E,">"&AZ$1,Base!$G:$G,"<"&AZ$2,Base!$J:$J,Scorecard!$A7,Base!$T:$T,"COMPLETED")/COUNTIFS(Base!$E:$E,">"&AZ$1,Base!$E:$E,"<"&AZ$2,Base!$J:$J,Scorecard!$A7),"0") -> 0 | BA7: =IFERROR(COUNTIFS(Base!$E:$E,">"&BA$1,Base!$G:$G,"<"&BA$2,Base!$J:$J,Scorecard!$A7,Base!$T:$T,"COMPLETED")/COUNTIFS(Base!$E:$E,">"&BA$1,Base!$E:$E,"<"&BA$2,Base!$J:$J,Scorecard!$A7),"0") -> 0 | BB7: =IFERROR(COUNTIFS(Base!$E:$E,">"&BB$1,Base!$G:$G,"<"&BB$2,Base!$J:$J,Scorecard!$A7,Base!$T:$T,"COMPLETED")/COUNTIFS(Base!$E:$E,">"&BB$1,Base!$E:$E,"<"&BB$2,Base!$J:$J,Scorecard!$A7),"0") -> 0 | ... BF7: =IFERROR(COUNTIFS(Base!$E:$E,">"&BF$1,Base!$G:$G,"<"&BF$2,Base!$J:$J,Scorecard!$A7,Base!$T:$T,"COMPLETED")/COUNTIFS(Base!$E:$E,">"&BF$1,Base!$E:$E,"<"&BF$2,Base!$J:$J,Scorecard!$A7),"0") -> 0 | BG7: =IFERROR(AVERAGEIF(AU7:BF7,">0",AU7:BF7),"-") -> 0.71163245 | BH7: =IF(BG7="-",0,IF(BG7<Goals!$Q$6,Goals!$R$7,IF(BG7<Goals!$Q$5,Goals!$R$6,IF(BG7<Goals!$Q$4,Goals!$R$5,IF(BG7<Goals!$Q$3,Goals!$R$4,IF(BG7<Goals!$Q$2,Goals!$R$3,Goals!$R$2)))))) -> 0.5 | BI7: =COUNTIFS(Strikes!$A:$A,Scorecard!$A7,Strikes!$C:$C,">"&Scorecard!BI$1,Strikes!$C:$C,"<"&Scorecard!BI$2) -> 0 | BJ7: =COUNTIFS(Strikes!$A:$A,Scorecard!$A7,Strikes!$C:$C,">"&Scorecard!BJ$1,Strikes!$C:$C,"<"&Scorecard!BJ$2) -> 1 | BK7: =COUNTIFS(Strikes!$A:$A,Scorecard!$A7,Strikes!$C:$C,">"&Scorecard!BK$1,Strikes!$C:$C,"<"&Scorecard!BK$2) -> 0 | BL7: =COUNTIFS(Strikes!$A:$A,Scorecard!$A7,Strikes!$C:$C,">"&Scorecard!BL$1,Strikes!$C:$C,"<"&Scorecard!BL$2) -> 0 | BM7: =COUNTIFS(Strikes!$A:$A,Scorecard!$A7,Strikes!$C:$C,">"&Scorecard!BM$1,Strikes!$C:$C,"<"&Scorecard!BM$2) -> 0 | BN7: =COUNTIFS(Strikes!$A:$A,Scorecard!$A7,Strikes!$C:$C,">"&Scorecard!BN$1,Strikes!$C:$C,"<"&Scorecard!BN$2) -> 0 | BO7: =COUNTIFS(Strikes!$A:$A,Scorecard!$A7,Strikes!$C:$C,">"&Scorecard!BO$1,Strikes!$C:$C,"<"&Scorecard!BO$2) -> 0 | BP7: =COUNTIFS(Strikes!$A:$A,Scorecard!$A7,Strikes!$C:$C,">"&Scorecard!BP$1,Strikes!$C:$C,"<"&Scorecard!BP$2) -> 0 | ... BT7: =COUNTIFS(Strikes!$A:$A,Scorecard!$A7,Strikes!$C:$C,">"&Scorecard!BT$1,Strikes!$C:$C,"<"&Scorecard!BT$2) -> 0 | BU7: =IFERROR(AVERAGEIF(BI7:BT7,">0",BI7:BT7),"0") -> 1 | BV7: =IF(BU7="-",0,IF(BU7=Goals!$H$7,Goals!$I$7,IF(BU7=Goals!$H$6,Goals!$I$6,IF(BU7=Goals!$H$5,Goals!$I$5,IF(BU7=Goals!$H$4,Goals!$I$4,IF(BU7=Goals!$H$3,Goals!$I$3,Goals!$I$2)))))) -> 1.2 | BW7: =IFERROR(COUNTIFS('Survey Q1'!$C:$C,Scorecard!$A7,'Survey Q1'!$F:$F,"1")/O7,"0") -> 0.89473684 | BX7: =IFERROR(COUNTIFS('Survey Q2'!$C:$C,Scorecard!$A7,'Survey Q1'!$F:$F,"1")/P7,"0") -> 0 | BY7: =IFERROR(COUNTIFS('Survey Q3'!$C:$C,Scorecard!$A7,'Survey Q1'!$F:$F,"1")/Q7,"0") -> 0 | BZ7: =IFERROR(COUNTIFS('Survey Q4'!$C:$C,Scorecard!$A7,'Survey Q1'!$F:$F,"1")/R7,"0") -> 0 | CA7: =IFERROR(AVERAGEIF(BW7:BZ7,">0",BW7:BZ7),"-") -> 0.89473684 | CB7: =IF(CA7="-",0,IF(CA7<Goals!$T$6,Goals!$U$7,IF(CA7<Goals!$T$5,Goals!$U$6,IF(CA7<Goals!$T$4,Goals!$U$5,IF(CA7<Goals!$T$3,Goals!$U$4,IF(CA7<Goals!$T$2,Goals!$U$3,Goals!$U$2)))))) -> 0.8 | CC7: =Scorecard!AF7*Goals!$C$3+Scorecard!AT7*Goals!$D$3+Scorecard!BH7*Goals!$E$3+Scorecard!CB7*Goals!$B$3+BV7*Goals!$F$3 -> 0.67
A8: joaoclan | B8: =COUNTIFS('Sellers Pro'!$F:$F,Scorecard!$A8,'Sellers Pro'!$Q:$Q,"<"&Scorecard!B$2,'Sellers Pro'!$O:$O,"1") -> 33 | C8: =COUNTIFS('Sellers Pro'!$F:$F,Scorecard!$A8,'Sellers Pro'!$Q:$Q,"<"&Scorecard!C$2,'Sellers Pro'!$O:$O,"1") -> 33 | D8: =COUNTIFS('Sellers Pro'!$F:$F,Scorecard!$A8,'Sellers Pro'!$Q:$Q,"<"&Scorecard!D$2,'Sellers Pro'!$O:$O,"1") -> 33 | E8: =COUNTIFS('Sellers Pro'!$F:$F,Scorecard!$A8,'Sellers Pro'!$Q:$Q,"<"&Scorecard!E$2,'Sellers Pro'!$O:$O,"1") -> 33 | F8: =COUNTIFS('Sellers Pro'!$F:$F,Scorecard!$A8,'Sellers Pro'!$Q:$Q,"<"&Scorecard!F$2,'Sellers Pro'!$O:$O,"1") -> 33 | G8: =COUNTIFS('Sellers Pro'!$F:$F,Scorecard!$A8,'Sellers Pro'!$Q:$Q,"<"&Scorecard!G$2,'Sellers Pro'!$O:$O,"1") -> 33 | H8: =COUNTIFS('Sellers Pro'!$F:$F,Scorecard!$A8,'Sellers Pro'!$Q:$Q,"<"&Scorecard!H$2,'Sellers Pro'!$O:$O,"1") -> 33 | I8: =COUNTIFS('Sellers Pro'!$F:$F,Scorecard!$A8,'Sellers Pro'!$Q:$Q,"<"&Scorecard!I$2,'Sellers Pro'!$O:$O,"1") -> 33 | ... M8: =COUNTIFS('Sellers Pro'!$F:$F,Scorecard!$A8,'Sellers Pro'!$Q:$Q,"<"&Scorecard!M$2,'Sellers Pro'!$O:$O,"1") -> 33 | N8: =IFERROR(AVERAGEIF(B8:M8,">0",B8:M8),"-") -> 33 | O8: =COUNTIFS('Survey Q1'!$G:$G,"="&1,'Survey Q1'!$C:$C,Scorecard!$A8) -> 13 | P8: =COUNTIFS('Survey Q2'!$G:$G,"="&1,'Survey Q1'!$C:$C,Scorecard!$A8) -> 0 | Q8: =COUNTIFS('Survey Q3'!$G:$G,"="&1,'Survey Q1'!$C:$C,Scorecard!$A8) -> 0 | R8: =COUNTIFS('Survey Q4'!$G:$G,"="&1,'Survey Q1'!$C:$C,Scorecard!$A8) -> 0 | S8: =IFERROR(COUNTIFS(Base!$J:$J,Scorecard!$A8,Base!$E:$E,">"&S$1,Base!$E:$E,"<"&S$2,Base!$AH:$AH,"1",Base!$A:$A,"2026")/$N8,"0") -> 0.57575758 | T8: =IFERROR(COUNTIFS(Base!$J:$J,Scorecard!$A8,Base!$E:$E,">"&T$1,Base!$E:$E,"<"&T$2,Base!$AH:$AH,"1",Base!$A:$A,"2026")/$N8,"0") -> 0.78787879 | U8: =IFERROR(COUNTIFS(Base!$J:$J,Scorecard!$A8,Base!$E:$E,">"&U$1,Base!$E:$E,"<"&U$2,Base!$AH:$AH,"1",Base!$A:$A,"2026")/$N8,"0") -> 0.57575758 | V8: =IFERROR(COUNTIFS(Base!$J:$J,Scorecard!$A8,Base!$E:$E,">"&V$1,Base!$E:$E,"<"&V$2,Base!$AH:$AH,"1",Base!$A:$A,"2026")/$N8,"0") -> 0 | W8: =IFERROR(COUNTIFS(Base!$J:$J,Scorecard!$A8,Base!$E:$E,">"&W$1,Base!$E:$E,"<"&W$2,Base!$AH:$AH,"1",Base!$A:$A,"2026")/$N8,"0") -> 0 | X8: =IFERROR(COUNTIFS(Base!$J:$J,Scorecard!$A8,Base!$E:$E,">"&X$1,Base!$E:$E,"<"&X$2,Base!$AH:$AH,"1",Base!$A:$A,"2026")/$N8,"0") -> 0 | Y8: =IFERROR(COUNTIFS(Base!$J:$J,Scorecard!$A8,Base!$E:$E,">"&Y$1,Base!$E:$E,"<"&Y$2,Base!$AH:$AH,"1",Base!$A:$A,"2026")/$N8,"0") -> 0 | Z8: =IFERROR(COUNTIFS(Base!$J:$J,Scorecard!$A8,Base!$E:$E,">"&Z$1,Base!$E:$E,"<"&Z$2,Base!$AH:$AH,"1",Base!$A:$A,"2026")/$N8,"0") -> 0 | ... AD8: =IFERROR(COUNTIFS(Base!$J:$J,Scorecard!$A8,Base!$E:$E,">"&AD$1,Base!$E:$E,"<"&AD$2,Base!$AH:$AH,"1",Base!$A:$A,"2026")/$N8,"0") -> 0 | AE8: =IFERROR(AVERAGEIF(S8:AD8,">0",S8:AD8),"-") -> 0.64646465 | AF8: =IF(AE8="-",0,IF(AE8<Goals!$K$6,Goals!$L$7,IF(AE8<Goals!$K$5,Goals!$L$6,IF(AE8<Goals!$K$4,Goals!$L$5,IF(AE8<Goals!$K$3,Goals!$L$4,IF(AE8<Goals!$K$2,Goals!$L$3,Goals!$L$2)))))) -> 0.5 | AG8: =IFERROR(AVERAGEIFS(Base!$V:$V,Base!$J:$J,Scorecard!$A8,Base!$E:$E,">"&AG$1,Base!$G:$G,"<"&AG$2,Base!$V:$V,"<"&$A$2,Base!$V:$V,">"&0,Base!$A:$A,"2026"),"0") -> 3.325 | AH8: =IFERROR(AVERAGEIFS(Base!$V:$V,Base!$J:$J,Scorecard!$A8,Base!$E:$E,">"&AH$1,Base!$G:$G,"<"&AH$2,Base!$V:$V,"<"&$A$2,Base!$V:$V,">"&0,Base!$A:$A,"2026"),"0") -> 4.1136364 | AI8: =IFERROR(AVERAGEIFS(Base!$V:$V,Base!$J:$J,Scorecard!$A8,Base!$E:$E,">"&AI$1,Base!$G:$G,"<"&AI$2,Base!$V:$V,"<"&$A$2,Base!$V:$V,">"&0,Base!$A:$A,"2026"),"0") -> 3.3428571 | AJ8: =IFERROR(AVERAGEIFS(Base!$V:$V,Base!$J:$J,Scorecard!$A8,Base!$E:$E,">"&AJ$1,Base!$G:$G,"<"&AJ$2,Base!$V:$V,"<"&$A$2,Base!$V:$V,">"&0,Base!$A:$A,"2026"),"0") -> 0 | AK8: =IFERROR(AVERAGEIFS(Base!$V:$V,Base!$J:$J,Scorecard!$A8,Base!$E:$E,">"&AK$1,Base!$G:$G,"<"&AK$2,Base!$V:$V,"<"&$A$2,Base!$V:$V,">"&0,Base!$A:$A,"2026"),"0") -> 0 | AL8: =IFERROR(AVERAGEIFS(Base!$V:$V,Base!$J:$J,Scorecard!$A8,Base!$E:$E,">"&AL$1,Base!$G:$G,"<"&AL$2,Base!$V:$V,"<"&$A$2,Base!$V:$V,">"&0,Base!$A:$A,"2026"),"0") -> 0 | AM8: =IFERROR(AVERAGEIFS(Base!$V:$V,Base!$J:$J,Scorecard!$A8,Base!$E:$E,">"&AM$1,Base!$G:$G,"<"&AM$2,Base!$V:$V,"<"&$A$2,Base!$V:$V,">"&0,Base!$A:$A,"2026"),"0") -> 0 | AN8: =IFERROR(AVERAGEIFS(Base!$V:$V,Base!$J:$J,Scorecard!$A8,Base!$E:$E,">"&AN$1,Base!$G:$G,"<"&AN$2,Base!$V:$V,"<"&$A$2,Base!$V:$V,">"&0,Base!$A:$A,"2026"),"0") -> 0 | ... AR8: =IFERROR(AVERAGEIFS(Base!$V:$V,Base!$J:$J,Scorecard!$A8,Base!$E:$E,">"&AR$1,Base!$G:$G,"<"&AR$2,Base!$V:$V,"<"&$A$2,Base!$V:$V,">"&0,Base!$A:$A,"2026"),"0") -> 0 | AS8: =IFERROR(AVERAGEIF(AG8:AR8,">0",AG8:AR8),"-") -> 3.5938312 | AT8: =IF(AS8="-",0,IF(AS8>Goals!$N$6,Goals!$O$7,IF(AS8>Goals!$N$5,Goals!$O$6,IF(AS8>Goals!$N$4,Goals!$O$5,IF(AS8>Goals!$N$3,Goals!$O$4,IF(AS8>Goals!$N$2,Goals!$O$3,Goals!$O$2)))))) -> 0.8 | AU8: =IFERROR(COUNTIFS(Base!$E:$E,">"&AU$1,Base!$G:$G,"<"&AU$2,Base!$J:$J,Scorecard!$A8,Base!$T:$T,"COMPLETED")/COUNTIFS(Base!$E:$E,">"&AU$1,Base!$E:$E,"<"&AU$2,Base!$J:$J,Scorecard!$A8),"0") -> 0.8245614 | AV8: =IFERROR(COUNTIFS(Base!$E:$E,">"&AV$1,Base!$G:$G,"<"&AV$2,Base!$J:$J,Scorecard!$A8,Base!$T:$T,"COMPLETED")/COUNTIFS(Base!$E:$E,">"&AV$1,Base!$E:$E,"<"&AV$2,Base!$J:$J,Scorecard!$A8),"0") -> 0.89189189 | AW8: =IFERROR(COUNTIFS(Base!$E:$E,">"&AW$1,Base!$G:$G,"<"&AW$2,Base!$J:$J,Scorecard!$A8,Base!$T:$T,"COMPLETED")/COUNTIFS(Base!$E:$E,">"&AW$1,Base!$E:$E,"<"&AW$2,Base!$J:$J,Scorecard!$A8),"0") -> 0.78571429 | AX8: =IFERROR(COUNTIFS(Base!$E:$E,">"&AX$1,Base!$G:$G,"<"&AX$2,Base!$J:$J,Scorecard!$A8,Base!$T:$T,"COMPLETED")/COUNTIFS(Base!$E:$E,">"&AX$1,Base!$E:$E,"<"&AX$2,Base!$J:$J,Scorecard!$A8),"0") -> 0 | AY8: =IFERROR(COUNTIFS(Base!$E:$E,">"&AY$1,Base!$G:$G,"<"&AY$2,Base!$J:$J,Scorecard!$A8,Base!$T:$T,"COMPLETED")/COUNTIFS(Base!$E:$E,">"&AY$1,Base!$E:$E,"<"&AY$2,Base!$J:$J,Scorecard!$A8),"0") -> 0 | AZ8: =IFERROR(COUNTIFS(Base!$E:$E,">"&AZ$1,Base!$G:$G,"<"&AZ$2,Base!$J:$J,Scorecard!$A8,Base!$T:$T,"COMPLETED")/COUNTIFS(Base!$E:$E,">"&AZ$1,Base!$E:$E,"<"&AZ$2,Base!$J:$J,Scorecard!$A8),"0") -> 0 | BA8: =IFERROR(COUNTIFS(Base!$E:$E,">"&BA$1,Base!$G:$G,"<"&BA$2,Base!$J:$J,Scorecard!$A8,Base!$T:$T,"COMPLETED")/COUNTIFS(Base!$E:$E,">"&BA$1,Base!$E:$E,"<"&BA$2,Base!$J:$J,Scorecard!$A8),"0") -> 0 | BB8: =IFERROR(COUNTIFS(Base!$E:$E,">"&BB$1,Base!$G:$G,"<"&BB$2,Base!$J:$J,Scorecard!$A8,Base!$T:$T,"COMPLETED")/COUNTIFS(Base!$E:$E,">"&BB$1,Base!$E:$E,"<"&BB$2,Base!$J:$J,Scorecard!$A8),"0") -> 0 | ... BF8: =IFERROR(COUNTIFS(Base!$E:$E,">"&BF$1,Base!$G:$G,"<"&BF$2,Base!$J:$J,Scorecard!$A8,Base!$T:$T,"COMPLETED")/COUNTIFS(Base!$E:$E,">"&BF$1,Base!$E:$E,"<"&BF$2,Base!$J:$J,Scorecard!$A8),"0") -> 0 | BG8: =IFERROR(AVERAGEIF(AU8:BF8,">0",AU8:BF8),"-") -> 0.83405586 | BH8: =IF(BG8="-",0,IF(BG8<Goals!$Q$6,Goals!$R$7,IF(BG8<Goals!$Q$5,Goals!$R$6,IF(BG8<Goals!$Q$4,Goals!$R$5,IF(BG8<Goals!$Q$3,Goals!$R$4,IF(BG8<Goals!$Q$2,Goals!$R$3,Goals!$R$2)))))) -> 0.6 | BI8: =COUNTIFS(Strikes!$A:$A,Scorecard!$A8,Strikes!$C:$C,">"&Scorecard!BI$1,Strikes!$C:$C,"<"&Scorecard!BI$2) -> 0 | BJ8: =COUNTIFS(Strikes!$A:$A,Scorecard!$A8,Strikes!$C:$C,">"&Scorecard!BJ$1,Strikes!$C:$C,"<"&Scorecard!BJ$2) -> 0 | BK8: =COUNTIFS(Strikes!$A:$A,Scorecard!$A8,Strikes!$C:$C,">"&Scorecard!BK$1,Strikes!$C:$C,"<"&Scorecard!BK$2) -> 0 | BL8: =COUNTIFS(Strikes!$A:$A,Scorecard!$A8,Strikes!$C:$C,">"&Scorecard!BL$1,Strikes!$C:$C,"<"&Scorecard!BL$2) -> 0 | BM8: =COUNTIFS(Strikes!$A:$A,Scorecard!$A8,Strikes!$C:$C,">"&Scorecard!BM$1,Strikes!$C:$C,"<"&Scorecard!BM$2) -> 0 | BN8: =COUNTIFS(Strikes!$A:$A,Scorecard!$A8,Strikes!$C:$C,">"&Scorecard!BN$1,Strikes!$C:$C,"<"&Scorecard!BN$2) -> 0 | BO8: =COUNTIFS(Strikes!$A:$A,Scorecard!$A8,Strikes!$C:$C,">"&Scorecard!BO$1,Strikes!$C:$C,"<"&Scorecard!BO$2) -> 0 | BP8: =COUNTIFS(Strikes!$A:$A,Scorecard!$A8,Strikes!$C:$C,">"&Scorecard!BP$1,Strikes!$C:$C,"<"&Scorecard!BP$2) -> 0 | ... BT8: =COUNTIFS(Strikes!$A:$A,Scorecard!$A8,Strikes!$C:$C,">"&Scorecard!BT$1,Strikes!$C:$C,"<"&Scorecard!BT$2) -> 0 | BU8: =IFERROR(AVERAGEIF(BI8:BT8,">0",BI8:BT8),"0") -> 0 | BV8: =IF(BU8="-",0,IF(BU8=Goals!$H$7,Goals!$I$7,IF(BU8=Goals!$H$6,Goals!$I$6,IF(BU8=Goals!$H$5,Goals!$I$5,IF(BU8=Goals!$H$4,Goals!$I$4,IF(BU8=Goals!$H$3,Goals!$I$3,Goals!$I$2)))))) -> 1.2 | BW8: =IFERROR(COUNTIFS('Survey Q1'!$C:$C,Scorecard!$A8,'Survey Q1'!$F:$F,"1")/O8,"0") -> 0.84615385 | BX8: =IFERROR(COUNTIFS('Survey Q2'!$C:$C,Scorecard!$A8,'Survey Q1'!$F:$F,"1")/P8,"0") -> 0 | BY8: =IFERROR(COUNTIFS('Survey Q3'!$C:$C,Scorecard!$A8,'Survey Q1'!$F:$F,"1")/Q8,"0") -> 0 | BZ8: =IFERROR(COUNTIFS('Survey Q4'!$C:$C,Scorecard!$A8,'Survey Q1'!$F:$F,"1")/R8,"0") -> 0 | CA8: =IFERROR(AVERAGEIF(BW8:BZ8,">0",BW8:BZ8),"-") -> 0.84615385 | CB8: =IF(CA8="-",0,IF(CA8<Goals!$T$6,Goals!$U$7,IF(CA8<Goals!$T$5,Goals!$U$6,IF(CA8<Goals!$T$4,Goals!$U$5,IF(CA8<Goals!$T$3,Goals!$U$4,IF(CA8<Goals!$T$2,Goals!$U$3,Goals!$U$2)))))) -> 0.6 | CC8: =Scorecard!AF8*Goals!$C$3+Scorecard!AT8*Goals!$D$3+Scorecard!BH8*Goals!$E$3+Scorecard!CB8*Goals!$B$3+BV8*Goals!$F$3 -> 0.66
A9: tiaelima | B9: =COUNTIFS('Sellers Pro'!$F:$F,Scorecard!$A9,'Sellers Pro'!$Q:$Q,"<"&Scorecard!B$2,'Sellers Pro'!$O:$O,"1") -> 39 | C9: =COUNTIFS('Sellers Pro'!$F:$F,Scorecard!$A9,'Sellers Pro'!$Q:$Q,"<"&Scorecard!C$2,'Sellers Pro'!$O:$O,"1") -> 40 | D9: =COUNTIFS('Sellers Pro'!$F:$F,Scorecard!$A9,'Sellers Pro'!$Q:$Q,"<"&Scorecard!D$2,'Sellers Pro'!$O:$O,"1") -> 41 | E9: =COUNTIFS('Sellers Pro'!$F:$F,Scorecard!$A9,'Sellers Pro'!$Q:$Q,"<"&Scorecard!E$2,'Sellers Pro'!$O:$O,"1") -> 41 | F9: =COUNTIFS('Sellers Pro'!$F:$F,Scorecard!$A9,'Sellers Pro'!$Q:$Q,"<"&Scorecard!F$2,'Sellers Pro'!$O:$O,"1") -> 41 | G9: =COUNTIFS('Sellers Pro'!$F:$F,Scorecard!$A9,'Sellers Pro'!$Q:$Q,"<"&Scorecard!G$2,'Sellers Pro'!$O:$O,"1") -> 41 | H9: =COUNTIFS('Sellers Pro'!$F:$F,Scorecard!$A9,'Sellers Pro'!$Q:$Q,"<"&Scorecard!H$2,'Sellers Pro'!$O:$O,"1") -> 41 | I9: =COUNTIFS('Sellers Pro'!$F:$F,Scorecard!$A9,'Sellers Pro'!$Q:$Q,"<"&Scorecard!I$2,'Sellers Pro'!$O:$O,"1") -> 41 | ... M9: =COUNTIFS('Sellers Pro'!$F:$F,Scorecard!$A9,'Sellers Pro'!$Q:$Q,"<"&Scorecard!M$2,'Sellers Pro'!$O:$O,"1") -> 41 | N9: =IFERROR(AVERAGEIF(B9:M9,">0",B9:M9),"-") -> 40.75 | O9: =COUNTIFS('Survey Q1'!$G:$G,"="&1,'Survey Q1'!$C:$C,Scorecard!$A9) -> 15 | P9: =COUNTIFS('Survey Q2'!$G:$G,"="&1,'Survey Q1'!$C:$C,Scorecard!$A9) -> 0 | Q9: =COUNTIFS('Survey Q3'!$G:$G,"="&1,'Survey Q1'!$C:$C,Scorecard!$A9) -> 0 | R9: =COUNTIFS('Survey Q4'!$G:$G,"="&1,'Survey Q1'!$C:$C,Scorecard!$A9) -> 0 | S9: =IFERROR(COUNTIFS(Base!$J:$J,Scorecard!$A9,Base!$E:$E,">"&S$1,Base!$E:$E,"<"&S$2,Base!$AH:$AH,"1",Base!$A:$A,"2026")/$N9,"0") -> 0.80981595 | T9: =IFERROR(COUNTIFS(Base!$J:$J,Scorecard!$A9,Base!$E:$E,">"&T$1,Base!$E:$E,"<"&T$2,Base!$AH:$AH,"1",Base!$A:$A,"2026")/$N9,"0") -> 0.66257669 | U9: =IFERROR(COUNTIFS(Base!$J:$J,Scorecard!$A9,Base!$E:$E,">"&U$1,Base!$E:$E,"<"&U$2,Base!$AH:$AH,"1",Base!$A:$A,"2026")/$N9,"0") -> 0.90797546 | V9: =IFERROR(COUNTIFS(Base!$J:$J,Scorecard!$A9,Base!$E:$E,">"&V$1,Base!$E:$E,"<"&V$2,Base!$AH:$AH,"1",Base!$A:$A,"2026")/$N9,"0") -> 0 | W9: =IFERROR(COUNTIFS(Base!$J:$J,Scorecard!$A9,Base!$E:$E,">"&W$1,Base!$E:$E,"<"&W$2,Base!$AH:$AH,"1",Base!$A:$A,"2026")/$N9,"0") -> 0 | X9: =IFERROR(COUNTIFS(Base!$J:$J,Scorecard!$A9,Base!$E:$E,">"&X$1,Base!$E:$E,"<"&X$2,Base!$AH:$AH,"1",Base!$A:$A,"2026")/$N9,"0") -> 0 | Y9: =IFERROR(COUNTIFS(Base!$J:$J,Scorecard!$A9,Base!$E:$E,">"&Y$1,Base!$E:$E,"<"&Y$2,Base!$AH:$AH,"1",Base!$A:$A,"2026")/$N9,"0") -> 0 | Z9: =IFERROR(COUNTIFS(Base!$J:$J,Scorecard!$A9,Base!$E:$E,">"&Z$1,Base!$E:$E,"<"&Z$2,Base!$AH:$AH,"1",Base!$A:$A,"2026")/$N9,"0") -> 0 | ... AD9: =IFERROR(COUNTIFS(Base!$J:$J,Scorecard!$A9,Base!$E:$E,">"&AD$1,Base!$E:$E,"<"&AD$2,Base!$AH:$AH,"1",Base!$A:$A,"2026")/$N9,"0") -> 0 | AE9: =IFERROR(AVERAGEIF(S9:AD9,">0",S9:AD9),"-") -> 0.79345603 | AF9: =IF(AE9="-",0,IF(AE9<Goals!$K$6,Goals!$L$7,IF(AE9<Goals!$K$5,Goals!$L$6,IF(AE9<Goals!$K$4,Goals!$L$5,IF(AE9<Goals!$K$3,Goals!$L$4,IF(AE9<Goals!$K$2,Goals!$L$3,Goals!$L$2)))))) -> 0.8 | AG9: =IFERROR(AVERAGEIFS(Base!$V:$V,Base!$J:$J,Scorecard!$A9,Base!$E:$E,">"&AG$1,Base!$G:$G,"<"&AG$2,Base!$V:$V,"<"&$A$2,Base!$V:$V,">"&0,Base!$A:$A,"2026"),"0") -> 2.304 | AH9: =IFERROR(AVERAGEIFS(Base!$V:$V,Base!$J:$J,Scorecard!$A9,Base!$E:$E,">"&AH$1,Base!$G:$G,"<"&AH$2,Base!$V:$V,"<"&$A$2,Base!$V:$V,">"&0,Base!$A:$A,"2026"),"0") -> 3.443299 | AI9: =IFERROR(AVERAGEIFS(Base!$V:$V,Base!$J:$J,Scorecard!$A9,Base!$E:$E,">"&AI$1,Base!$G:$G,"<"&AI$2,Base!$V:$V,"<"&$A$2,Base!$V:$V,">"&0,Base!$A:$A,"2026"),"0") -> 2.36 | AJ9: =IFERROR(AVERAGEIFS(Base!$V:$V,Base!$J:$J,Scorecard!$A9,Base!$E:$E,">"&AJ$1,Base!$G:$G,"<"&AJ$2,Base!$V:$V,"<"&$A$2,Base!$V:$V,">"&0,Base!$A:$A,"2026"),"0") -> 0 | AK9: =IFERROR(AVERAGEIFS(Base!$V:$V,Base!$J:$J,Scorecard!$A9,Base!$E:$E,">"&AK$1,Base!$G:$G,"<"&AK$2,Base!$V:$V,"<"&$A$2,Base!$V:$V,">"&0,Base!$A:$A,"2026"),"0") -> 0 | AL9: =IFERROR(AVERAGEIFS(Base!$V:$V,Base!$J:$J,Scorecard!$A9,Base!$E:$E,">"&AL$1,Base!$G:$G,"<"&AL$2,Base!$V:$V,"<"&$A$2,Base!$V:$V,">"&0,Base!$A:$A,"2026"),"0") -> 0 | AM9: =IFERROR(AVERAGEIFS(Base!$V:$V,Base!$J:$J,Scorecard!$A9,Base!$E:$E,">"&AM$1,Base!$G:$G,"<"&AM$2,Base!$V:$V,"<"&$A$2,Base!$V:$V,">"&0,Base!$A:$A,"2026"),"0") -> 0 | AN9: =IFERROR(AVERAGEIFS(Base!$V:$V,Base!$J:$J,Scorecard!$A9,Base!$E:$E,">"&AN$1,Base!$G:$G,"<"&AN$2,Base!$V:$V,"<"&$A$2,Base!$V:$V,">"&0,Base!$A:$A,"2026"),"0") -> 0 | ... AR9: =IFERROR(AVERAGEIFS(Base!$V:$V,Base!$J:$J,Scorecard!$A9,Base!$E:$E,">"&AR$1,Base!$G:$G,"<"&AR$2,Base!$V:$V,"<"&$A$2,Base!$V:$V,">"&0,Base!$A:$A,"2026"),"0") -> 0 | AS9: =IFERROR(AVERAGEIF(AG9:AR9,">0",AG9:AR9),"-") -> 2.702433 | AT9: =IF(AS9="-",0,IF(AS9>Goals!$N$6,Goals!$O$7,IF(AS9>Goals!$N$5,Goals!$O$6,IF(AS9>Goals!$N$4,Goals!$O$5,IF(AS9>Goals!$N$3,Goals!$O$4,IF(AS9>Goals!$N$2,Goals!$O$3,Goals!$O$2)))))) -> 1 | AU9: =IFERROR(COUNTIFS(Base!$E:$E,">"&AU$1,Base!$G:$G,"<"&AU$2,Base!$J:$J,Scorecard!$A9,Base!$T:$T,"COMPLETED")/COUNTIFS(Base!$E:$E,">"&AU$1,Base!$E:$E,"<"&AU$2,Base!$J:$J,Scorecard!$A9),"0") -> 0.85572139 | AV9: =IFERROR(COUNTIFS(Base!$E:$E,">"&AV$1,Base!$G:$G,"<"&AV$2,Base!$J:$J,Scorecard!$A9,Base!$T:$T,"COMPLETED")/COUNTIFS(Base!$E:$E,">"&AV$1,Base!$E:$E,"<"&AV$2,Base!$J:$J,Scorecard!$A9),"0") -> 0.87096774 | AW9: =IFERROR(COUNTIFS(Base!$E:$E,">"&AW$1,Base!$G:$G,"<"&AW$2,Base!$J:$J,Scorecard!$A9,Base!$T:$T,"COMPLETED")/COUNTIFS(Base!$E:$E,">"&AW$1,Base!$E:$E,"<"&AW$2,Base!$J:$J,Scorecard!$A9),"0") -> 0.8 | AX9: =IFERROR(COUNTIFS(Base!$E:$E,">"&AX$1,Base!$G:$G,"<"&AX$2,Base!$J:$J,Scorecard!$A9,Base!$T:$T,"COMPLETED")/COUNTIFS(Base!$E:$E,">"&AX$1,Base!$E:$E,"<"&AX$2,Base!$J:$J,Scorecard!$A9),"0") -> 0 | AY9: =IFERROR(COUNTIFS(Base!$E:$E,">"&AY$1,Base!$G:$G,"<"&AY$2,Base!$J:$J,Scorecard!$A9,Base!$T:$T,"COMPLETED")/COUNTIFS(Base!$E:$E,">"&AY$1,Base!$E:$E,"<"&AY$2,Base!$J:$J,Scorecard!$A9),"0") -> 0 | AZ9: =IFERROR(COUNTIFS(Base!$E:$E,">"&AZ$1,Base!$G:$G,"<"&AZ$2,Base!$J:$J,Scorecard!$A9,Base!$T:$T,"COMPLETED")/COUNTIFS(Base!$E:$E,">"&AZ$1,Base!$E:$E,"<"&AZ$2,Base!$J:$J,Scorecard!$A9),"0") -> 0 | BA9: =IFERROR(COUNTIFS(Base!$E:$E,">"&BA$1,Base!$G:$G,"<"&BA$2,Base!$J:$J,Scorecard!$A9,Base!$T:$T,"COMPLETED")/COUNTIFS(Base!$E:$E,">"&BA$1,Base!$E:$E,"<"&BA$2,Base!$J:$J,Scorecard!$A9),"0") -> 0 | BB9: =IFERROR(COUNTIFS(Base!$E:$E,">"&BB$1,Base!$G:$G,"<"&BB$2,Base!$J:$J,Scorecard!$A9,Base!$T:$T,"COMPLETED")/COUNTIFS(Base!$E:$E,">"&BB$1,Base!$E:$E,"<"&BB$2,Base!$J:$J,Scorecard!$A9),"0") -> 0 | ... BF9: =IFERROR(COUNTIFS(Base!$E:$E,">"&BF$1,Base!$G:$G,"<"&BF$2,Base!$J:$J,Scorecard!$A9,Base!$T:$T,"COMPLETED")/COUNTIFS(Base!$E:$E,">"&BF$1,Base!$E:$E,"<"&BF$2,Base!$J:$J,Scorecard!$A9),"0") -> 0 | BG9: =IFERROR(AVERAGEIF(AU9:BF9,">0",AU9:BF9),"-") -> 0.84222971 | BH9: =IF(BG9="-",0,IF(BG9<Goals!$Q$6,Goals!$R$7,IF(BG9<Goals!$Q$5,Goals!$R$6,IF(BG9<Goals!$Q$4,Goals!$R$5,IF(BG9<Goals!$Q$3,Goals!$R$4,IF(BG9<Goals!$Q$2,Goals!$R$3,Goals!$R$2)))))) -> 0.6 | BI9: =COUNTIFS(Strikes!$A:$A,Scorecard!$A9,Strikes!$C:$C,">"&Scorecard!BI$1,Strikes!$C:$C,"<"&Scorecard!BI$2) -> 0 | BJ9: =COUNTIFS(Strikes!$A:$A,Scorecard!$A9,Strikes!$C:$C,">"&Scorecard!BJ$1,Strikes!$C:$C,"<"&Scorecard!BJ$2) -> 0 | BK9: =COUNTIFS(Strikes!$A:$A,Scorecard!$A9,Strikes!$C:$C,">"&Scorecard!BK$1,Strikes!$C:$C,"<"&Scorecard!BK$2) -> 0 | BL9: =COUNTIFS(Strikes!$A:$A,Scorecard!$A9,Strikes!$C:$C,">"&Scorecard!BL$1,Strikes!$C:$C,"<"&Scorecard!BL$2) -> 0 | BM9: =COUNTIFS(Strikes!$A:$A,Scorecard!$A9,Strikes!$C:$C,">"&Scorecard!BM$1,Strikes!$C:$C,"<"&Scorecard!BM$2) -> 0 | BN9: =COUNTIFS(Strikes!$A:$A,Scorecard!$A9,Strikes!$C:$C,">"&Scorecard!BN$1,Strikes!$C:$C,"<"&Scorecard!BN$2) -> 0 | BO9: =COUNTIFS(Strikes!$A:$A,Scorecard!$A9,Strikes!$C:$C,">"&Scorecard!BO$1,Strikes!$C:$C,"<"&Scorecard!BO$2) -> 0 | BP9: =COUNTIFS(Strikes!$A:$A,Scorecard!$A9,Strikes!$C:$C,">"&Scorecard!BP$1,Strikes!$C:$C,"<"&Scorecard!BP$2) -> 0 | ... BT9: =COUNTIFS(Strikes!$A:$A,Scorecard!$A9,Strikes!$C:$C,">"&Scorecard!BT$1,Strikes!$C:$C,"<"&Scorecard!BT$2) -> 0 | BU9: =IFERROR(AVERAGEIF(BI9:BT9,">0",BI9:BT9),"0") -> 0 | BV9: =IF(BU9="-",0,IF(BU9=Goals!$H$7,Goals!$I$7,IF(BU9=Goals!$H$6,Goals!$I$6,IF(BU9=Goals!$H$5,Goals!$I$5,IF(BU9=Goals!$H$4,Goals!$I$4,IF(BU9=Goals!$H$3,Goals!$I$3,Goals!$I$2)))))) -> 1.2 | BW9: =IFERROR(COUNTIFS('Survey Q1'!$C:$C,Scorecard!$A9,'Survey Q1'!$F:$F,"1")/O9,"0") -> 0.86666667 | BX9: =IFERROR(COUNTIFS('Survey Q2'!$C:$C,Scorecard!$A9,'Survey Q1'!$F:$F,"1")/P9,"0") -> 0 | BY9: =IFERROR(COUNTIFS('Survey Q3'!$C:$C,Scorecard!$A9,'Survey Q1'!$F:$F,"1")/Q9,"0") -> 0 | BZ9: =IFERROR(COUNTIFS('Survey Q4'!$C:$C,Scorecard!$A9,'Survey Q1'!$F:$F,"1")/R9,"0") -> 0 | CA9: =IFERROR(AVERAGEIF(BW9:BZ9,">0",BW9:BZ9),"-") -> 0.86666667 | CB9: =IF(CA9="-",0,IF(CA9<Goals!$T$6,Goals!$U$7,IF(CA9<Goals!$T$5,Goals!$U$6,IF(CA9<Goals!$T$4,Goals!$U$5,IF(CA9<Goals!$T$3,Goals!$U$4,IF(CA9<Goals!$T$2,Goals!$U$3,Goals!$U$2)))))) -> 0.8 | CC9: =Scorecard!AF9*Goals!$C$3+Scorecard!AT9*Goals!$D$3+Scorecard!BH9*Goals!$E$3+Scorecard!CB9*Goals!$B$3+BV9*Goals!$F$3 -> 0.81
A10: wallmach | B10: =COUNTIFS('Sellers Pro'!$F:$F,Scorecard!$A10,'Sellers Pro'!$Q:$Q,"<"&Scorecard!B$2,'Sellers Pro'!$O:$O,"1") -> 33 | C10: =COUNTIFS('Sellers Pro'!$F:$F,Scorecard!$A10,'Sellers Pro'!$Q:$Q,"<"&Scorecard!C$2,'Sellers Pro'!$O:$O,"1") -> 33 | D10: =COUNTIFS('Sellers Pro'!$F:$F,Scorecard!$A10,'Sellers Pro'!$Q:$Q,"<"&Scorecard!D$2,'Sellers Pro'!$O:$O,"1") -> 40 | E10: =COUNTIFS('Sellers Pro'!$F:$F,Scorecard!$A10,'Sellers Pro'!$Q:$Q,"<"&Scorecard!E$2,'Sellers Pro'!$O:$O,"1") -> 40 | F10: =COUNTIFS('Sellers Pro'!$F:$F,Scorecard!$A10,'Sellers Pro'!$Q:$Q,"<"&Scorecard!F$2,'Sellers Pro'!$O:$O,"1") -> 40 | G10: =COUNTIFS('Sellers Pro'!$F:$F,Scorecard!$A10,'Sellers Pro'!$Q:$Q,"<"&Scorecard!G$2,'Sellers Pro'!$O:$O,"1") -> 40 | H10: =COUNTIFS('Sellers Pro'!$F:$F,Scorecard!$A10,'Sellers Pro'!$Q:$Q,"<"&Scorecard!H$2,'Sellers Pro'!$O:$O,"1") -> 40 | I10: =COUNTIFS('Sellers Pro'!$F:$F,Scorecard!$A10,'Sellers Pro'!$Q:$Q,"<"&Scorecard!I$2,'Sellers Pro'!$O:$O,"1") -> 40 | ... M10: =COUNTIFS('Sellers Pro'!$F:$F,Scorecard!$A10,'Sellers Pro'!$Q:$Q,"<"&Scorecard!M$2,'Sellers Pro'!$O:$O,"1") -> 40 | N10: =IFERROR(AVERAGEIF(B10:M10,">0",B10:M10),"-") -> 38.833333 | O10: =COUNTIFS('Survey Q1'!$G:$G,"="&1,'Survey Q1'!$C:$C,Scorecard!$A10) -> 0 | P10: =COUNTIFS('Survey Q2'!$G:$G,"="&1,'Survey Q1'!$C:$C,Scorecard!$A10) -> 0 | Q10: =COUNTIFS('Survey Q3'!$G:$G,"="&1,'Survey Q1'!$C:$C,Scorecard!$A10) -> 0 | R10: =COUNTIFS('Survey Q4'!$G:$G,"="&1,'Survey Q1'!$C:$C,Scorecard!$A10) -> 0 | S10: =IFERROR(COUNTIFS(Base!$J:$J,Scorecard!$A10,Base!$E:$E,">"&S$1,Base!$E:$E,"<"&S$2,Base!$AH:$AH,"1",Base!$A:$A,"2026")/$N10,"0") -> 0 | T10: =IFERROR(COUNTIFS(Base!$J:$J,Scorecard!$A10,Base!$E:$E,">"&T$1,Base!$E:$E,"<"&T$2,Base!$AH:$AH,"1",Base!$A:$A,"2026")/$N10,"0") -> 0 | U10: =IFERROR(COUNTIFS(Base!$J:$J,Scorecard!$A10,Base!$E:$E,">"&U$1,Base!$E:$E,"<"&U$2,Base!$AH:$AH,"1",Base!$A:$A,"2026")/$N10,"0") -> 0 | V10: =IFERROR(COUNTIFS(Base!$J:$J,Scorecard!$A10,Base!$E:$E,">"&V$1,Base!$E:$E,"<"&V$2,Base!$AH:$AH,"1",Base!$A:$A,"2026")/$N10,"0") -> 0 | W10: =IFERROR(COUNTIFS(Base!$J:$J,Scorecard!$A10,Base!$E:$E,">"&W$1,Base!$E:$E,"<"&W$2,Base!$AH:$AH,"1",Base!$A:$A,"2026")/$N10,"0") -> 0 | X10: =IFERROR(COUNTIFS(Base!$J:$J,Scorecard!$A10,Base!$E:$E,">"&X$1,Base!$E:$E,"<"&X$2,Base!$AH:$AH,"1",Base!$A:$A,"2026")/$N10,"0") -> 0 | Y10: =IFERROR(COUNTIFS(Base!$J:$J,Scorecard!$A10,Base!$E:$E,">"&Y$1,Base!$E:$E,"<"&Y$2,Base!$AH:$AH,"1",Base!$A:$A,"2026")/$N10,"0") -> 0 | Z10: =IFERROR(COUNTIFS(Base!$J:$J,Scorecard!$A10,Base!$E:$E,">"&Z$1,Base!$E:$E,"<"&Z$2,Base!$AH:$AH,"1",Base!$A:$A,"2026")/$N10,"0") -> 0 | ... AD10: =IFERROR(COUNTIFS(Base!$J:$J,Scorecard!$A10,Base!$E:$E,">"&AD$1,Base!$E:$E,"<"&AD$2,Base!$AH:$AH,"1",Base!$A:$A,"2026")/$N10,"0") -> 0 | AE10: =IFERROR(AVERAGEIF(S10:AD10,">0",S10:AD10),"-") -> - | AF10: =IF(AE10="-",0,IF(AE10<Goals!$K$6,Goals!$L$7,IF(AE10<Goals!$K$5,Goals!$L$6,IF(AE10<Goals!$K$4,Goals!$L$5,IF(AE10<Goals!$K$3,Goals!$L$4,IF(AE10<Goals!$K$2,Goals!$L$3,Goals!$L$2)))))) -> 0 | AG10: =IFERROR(AVERAGEIFS(Base!$V:$V,Base!$J:$J,Scorecard!$A10,Base!$E:$E,">"&AG$1,Base!$G:$G,"<"&AG$2,Base!$V:$V,"<"&$A$2,Base!$V:$V,">"&0,Base!$A:$A,"2026"),"0") -> 0 | AH10: =IFERROR(AVERAGEIFS(Base!$V:$V,Base!$J:$J,Scorecard!$A10,Base!$E:$E,">"&AH$1,Base!$G:$G,"<"&AH$2,Base!$V:$V,"<"&$A$2,Base!$V:$V,">"&0,Base!$A:$A,"2026"),"0") -> 0 | AI10: =IFERROR(AVERAGEIFS(Base!$V:$V,Base!$J:$J,Scorecard!$A10,Base!$E:$E,">"&AI$1,Base!$G:$G,"<"&AI$2,Base!$V:$V,"<"&$A$2,Base!$V:$V,">"&0,Base!$A:$A,"2026"),"0") -> 0 | AJ10: =IFERROR(AVERAGEIFS(Base!$V:$V,Base!$J:$J,Scorecard!$A10,Base!$E:$E,">"&AJ$1,Base!$G:$G,"<"&AJ$2,Base!$V:$V,"<"&$A$2,Base!$V:$V,">"&0,Base!$A:$A,"2026"),"0") -> 0 | AK10: =IFERROR(AVERAGEIFS(Base!$V:$V,Base!$J:$J,Scorecard!$A10,Base!$E:$E,">"&AK$1,Base!$G:$G,"<"&AK$2,Base!$V:$V,"<"&$A$2,Base!$V:$V,">"&0,Base!$A:$A,"2026"),"0") -> 0 | AL10: =IFERROR(AVERAGEIFS(Base!$V:$V,Base!$J:$J,Scorecard!$A10,Base!$E:$E,">"&AL$1,Base!$G:$G,"<"&AL$2,Base!$V:$V,"<"&$A$2,Base!$V:$V,">"&0,Base!$A:$A,"2026"),"0") -> 0 | AM10: =IFERROR(AVERAGEIFS(Base!$V:$V,Base!$J:$J,Scorecard!$A10,Base!$E:$E,">"&AM$1,Base!$G:$G,"<"&AM$2,Base!$V:$V,"<"&$A$2,Base!$V:$V,">"&0,Base!$A:$A,"2026"),"0") -> 0 | AN10: =IFERROR(AVERAGEIFS(Base!$V:$V,Base!$J:$J,Scorecard!$A10,Base!$E:$E,">"&AN$1,Base!$G:$G,"<"&AN$2,Base!$V:$V,"<"&$A$2,Base!$V:$V,">"&0,Base!$A:$A,"2026"),"0") -> 0 | ... AR10: =IFERROR(AVERAGEIFS(Base!$V:$V,Base!$J:$J,Scorecard!$A10,Base!$E:$E,">"&AR$1,Base!$G:$G,"<"&AR$2,Base!$V:$V,"<"&$A$2,Base!$V:$V,">"&0,Base!$A:$A,"2026"),"0") -> 0 | AS10: =IFERROR(AVERAGEIF(AG10:AR10,">0",AG10:AR10),"-") -> - | AT10: =IF(AS10="-",0,IF(AS10>Goals!$N$6,Goals!$O$7,IF(AS10>Goals!$N$5,Goals!$O$6,IF(AS10>Goals!$N$4,Goals!$O$5,IF(AS10>Goals!$N$3,Goals!$O$4,IF(AS10>Goals!$N$2,Goals!$O$3,Goals!$O$2)))))) -> 0 | AU10: =IFERROR(COUNTIFS(Base!$E:$E,">"&AU$1,Base!$G:$G,"<"&AU$2,Base!$J:$J,Scorecard!$A10,Base!$T:$T,"COMPLETED")/COUNTIFS(Base!$E:$E,">"&AU$1,Base!$E:$E,"<"&AU$2,Base!$J:$J,Scorecard!$A10),"0") -> 0 | AV10: =IFERROR(COUNTIFS(Base!$E:$E,">"&AV$1,Base!$G:$G,"<"&AV$2,Base!$J:$J,Scorecard!$A10,Base!$T:$T,"COMPLETED")/COUNTIFS(Base!$E:$E,">"&AV$1,Base!$E:$E,"<"&AV$2,Base!$J:$J,Scorecard!$A10),"0") -> 0 | AW10: =IFERROR(COUNTIFS(Base!$E:$E,">"&AW$1,Base!$G:$G,"<"&AW$2,Base!$J:$J,Scorecard!$A10,Base!$T:$T,"COMPLETED")/COUNTIFS(Base!$E:$E,">"&AW$1,Base!$E:$E,"<"&AW$2,Base!$J:$J,Scorecard!$A10),"0") -> 0 | AX10: =IFERROR(COUNTIFS(Base!$E:$E,">"&AX$1,Base!$G:$G,"<"&AX$2,Base!$J:$J,Scorecard!$A10,Base!$T:$T,"COMPLETED")/COUNTIFS(Base!$E:$E,">"&AX$1,Base!$E:$E,"<"&AX$2,Base!$J:$J,Scorecard!$A10),"0") -> 0 | AY10: =IFERROR(COUNTIFS(Base!$E:$E,">"&AY$1,Base!$G:$G,"<"&AY$2,Base!$J:$J,Scorecard!$A10,Base!$T:$T,"COMPLETED")/COUNTIFS(Base!$E:$E,">"&AY$1,Base!$E:$E,"<"&AY$2,Base!$J:$J,Scorecard!$A10),"0") -> 0 | AZ10: =IFERROR(COUNTIFS(Base!$E:$E,">"&AZ$1,Base!$G:$G,"<"&AZ$2,Base!$J:$J,Scorecard!$A10,Base!$T:$T,"COMPLETED")/COUNTIFS(Base!$E:$E,">"&AZ$1,Base!$E:$E,"<"&AZ$2,Base!$J:$J,Scorecard!$A10),"0") -> 0 | BA10: =IFERROR(COUNTIFS(Base!$E:$E,">"&BA$1,Base!$G:$G,"<"&BA$2,Base!$J:$J,Scorecard!$A10,Base!$T:$T,"COMPLETED")/COUNTIFS(Base!$E:$E,">"&BA$1,Base!$E:$E,"<"&BA$2,Base!$J:$J,Scorecard!$A10),"0") -> 0 | BB10: =IFERROR(COUNTIFS(Base!$E:$E,">"&BB$1,Base!$G:$G,"<"&BB$2,Base!$J:$J,Scorecard!$A10,Base!$T:$T,"COMPLETED")/COUNTIFS(Base!$E:$E,">"&BB$1,Base!$E:$E,"<"&BB$2,Base!$J:$J,Scorecard!$A10),"0") -> 0 | ... BF10: =IFERROR(COUNTIFS(Base!$E:$E,">"&BF$1,Base!$G:$G,"<"&BF$2,Base!$J:$J,Scorecard!$A10,Base!$T:$T,"COMPLETED")/COUNTIFS(Base!$E:$E,">"&BF$1,Base!$E:$E,"<"&BF$2,Base!$J:$J,Scorecard!$A10),"0") -> 0 | BG10: =IFERROR(AVERAGEIF(AU10:BF10,">0",AU10:BF10),"-") -> - | BH10: =IF(BG10="-",0,IF(BG10<Goals!$Q$6,Goals!$R$7,IF(BG10<Goals!$Q$5,Goals!$R$6,IF(BG10<Goals!$Q$4,Goals!$R$5,IF(BG10<Goals!$Q$3,Goals!$R$4,IF(BG10<Goals!$Q$2,Goals!$R$3,Goals!$R$2)))))) -> 0 | BI10: =COUNTIFS(Strikes!$A:$A,Scorecard!$A10,Strikes!$C:$C,">"&Scorecard!BI$1,Strikes!$C:$C,"<"&Scorecard!BI$2) -> 0 | BJ10: =COUNTIFS(Strikes!$A:$A,Scorecard!$A10,Strikes!$C:$C,">"&Scorecard!BJ$1,Strikes!$C:$C,"<"&Scorecard!BJ$2) -> 0 | BK10: =COUNTIFS(Strikes!$A:$A,Scorecard!$A10,Strikes!$C:$C,">"&Scorecard!BK$1,Strikes!$C:$C,"<"&Scorecard!BK$2) -> 0 | BL10: =COUNTIFS(Strikes!$A:$A,Scorecard!$A10,Strikes!$C:$C,">"&Scorecard!BL$1,Strikes!$C:$C,"<"&Scorecard!BL$2) -> 0 | BM10: =COUNTIFS(Strikes!$A:$A,Scorecard!$A10,Strikes!$C:$C,">"&Scorecard!BM$1,Strikes!$C:$C,"<"&Scorecard!BM$2) -> 0 | BN10: =COUNTIFS(Strikes!$A:$A,Scorecard!$A10,Strikes!$C:$C,">"&Scorecard!BN$1,Strikes!$C:$C,"<"&Scorecard!BN$2) -> 0 | BO10: =COUNTIFS(Strikes!$A:$A,Scorecard!$A10,Strikes!$C:$C,">"&Scorecard!BO$1,Strikes!$C:$C,"<"&Scorecard!BO$2) -> 0 | BP10: =COUNTIFS(Strikes!$A:$A,Scorecard!$A10,Strikes!$C:$C,">"&Scorecard!BP$1,Strikes!$C:$C,"<"&Scorecard!BP$2) -> 0 | ... BT10: =COUNTIFS(Strikes!$A:$A,Scorecard!$A10,Strikes!$C:$C,">"&Scorecard!BT$1,Strikes!$C:$C,"<"&Scorecard!BT$2) -> 0 | BU10: =IFERROR(AVERAGEIF(BI10:BT10,">0",BI10:BT10),"0") -> 0 | BV10: =IF(BU10="-",0,IF(BU10=Goals!$H$7,Goals!$I$7,IF(BU10=Goals!$H$6,Goals!$I$6,IF(BU10=Goals!$H$5,Goals!$I$5,IF(BU10=Goals!$H$4,Goals!$I$4,IF(BU10=Goals!$H$3,Goals!$I$3,Goals!$I$2)))))) -> 1.2 | BW10: =IFERROR(COUNTIFS('Survey Q1'!$C:$C,Scorecard!$A10,'Survey Q1'!$F:$F,"1")/O10,"0") -> 0 | BX10: =IFERROR(COUNTIFS('Survey Q2'!$C:$C,Scorecard!$A10,'Survey Q1'!$F:$F,"1")/P10,"0") -> 0 | BY10: =IFERROR(COUNTIFS('Survey Q3'!$C:$C,Scorecard!$A10,'Survey Q1'!$F:$F,"1")/Q10,"0") -> 0 | BZ10: =IFERROR(COUNTIFS('Survey Q4'!$C:$C,Scorecard!$A10,'Survey Q1'!$F:$F,"1")/R10,"0") -> 0 | CA10: =IFERROR(AVERAGEIF(BW10:BZ10,">0",BW10:BZ10),"-") -> - | CB10: =IF(CA10="-",0,IF(CA10<Goals!$T$6,Goals!$U$7,IF(CA10<Goals!$T$5,Goals!$U$6,IF(CA10<Goals!$T$4,Goals!$U$5,IF(CA10<Goals!$T$3,Goals!$U$4,IF(CA10<Goals!$T$2,Goals!$U$3,Goals!$U$2)))))) -> 0 | CC10: =Scorecard!AF10*Goals!$C$3+Scorecard!AT10*Goals!$D$3+Scorecard!BH10*Goals!$E$3+Scorecard!CB10*Goals!$B$3+BV10*Goals!$F$3 -> 0.06

Sheet Goals
B1: SP Satisfaction (20%) | C1: Growth Levers (80%) | H1: Strikes SOPs | I1: Score | K1: Adoption | L1: Score | N1: TTR (dias) | O1: Score | Q1: % Issue Solved | R1: Score | T1: Seller Satisfaction | U1: Score | V1: Legenda | W1: Score
B2: Survey | C2: Adoption | D2: TTR | E2: Issue % | F2: SOP Strikes | H2: 0 | I2: 1.2 | K2: 0.9 | L2: 1.2 | N2: 1 | O2: 1.2 | Q2: 0.98 | R2: 1.2 | T2: 0.95 | U2: 1.2 | V2: Muito Satisfeito | W2: 1
B3: 0.2 | C3: 0.2 | D3: 0.25 | E3: 0.3 | F3: 0.05 | H3: 2 | I3: 1 | K3: 0.8 | L3: 1 | N3: 3 | O3: 1 | Q3: 0.95 | R3: 1 | T3: 0.9 | U3: 1 | V3: Satisfeto
H4: 4 | I4: 0.8 | K4: 0.7 | L4: 0.8 | N4: 4 | O4: 0.8 | Q4: 0.85 | R4: 0.8 | T4: 0.85 | U4: 0.8 | V4: Nem satisfeito, nem insatisfeito | W4: 0
H5: 6 | I5: 0.6 | K5: 0.7 | L5: 0.6 | N5: 5 | O5: 0.6 | Q5: 0.75 | R5: 0.6 | T5: 0.8 | U5: 0.6 | V5: Insatisfeito
H6: 7 | I6: 0.4 | K6: 0.5 | L6: 0.5 | N6: 6 | O6: 0.5 | Q6: 0.65 | R6: 0.5 | T6: 0.75 | U6: 0.5 | V6: Muito insatisfeito
H7: 8 | I7: 0 | K7: <50% | L7: 0 | N7: 7 | O7: 0 | Q7: <65% | R7: 0 | T7: <75% | U7: 0
H9: SOP Description
H10: Exemplo 1 Descrição: Unidades não recebidas no CD 1/jan: Issue recebido 2/jan: Ticket aberto para o time de FBA --> Link 7/jan: Ticket fechado sem resolução. Thread criada no e-mail pelo Vini 10/jan: Resolução concluída Exemplo 2 Descrição: ASIN bloqueado por HAZMAT 10/jan: Issue recebido 11/jan: Solicitação ao seller das fotos do produto 16/jan: Issue concluído como PSA. Sem retorno do vendedor.
H11: SOP Message
H12: Olá, [ESPAÇO PARA O COLABORADOR ADICIONAR A MENSAGEM PERSONALIZADA] Além disso, segue atualização sobre seus casos em aberto conosco: CASOS EM ACOMPANHAMENTO: 1. KYC Descrição: Problemas de permissão de usuário, não consegue atribuir as permissões ou realizar a verificação de... Status: Em Andamento Última atualização: [colaborador deve adicionar a última atualização do problema] Qualquer dúvida sobre os outros casos, fique à vontade para perguntar! Atenciosamente, [Nome do Colaborador]

Sheet Goal Description
A1: Type | B1: Goal Summary | C1: Timeframe | D1: Weight | E1: Capped | F1: Formula | G1: Definition | H1: Data Source
A2: OMSX Score | B2: 90% OM satisfaction | C2: Quarterly | D2: 0.2 | E2: Yes, 120% | F2: 90% OM satisfaction of SPs that answered survey | G2: Count of SPs that answered with somewhat or extremely satisfied (MC) count in SPX Survey. Eligible 3rd month of program. | H2: Qualtrics
A3: Adoption | B3: 80% of seller adoption | C3: Monthly | D3: 0.2 | E3: Yes, 120% | F3: 80% of seller who are using the program monthly | G3: OMs must have an average of 80% of adoption monthly. This includes proactive tasks | H3: Monthly datanet
A4: TTR (dias) | B4: 3 days | C4: Monthly | D4: 0.25 | E4: Yes, 120% | F4: Average of 3 days in solving tickets | G4: OMs must have an average of 3 days of solved tickets. This formula uses tickets closed in the month related to the metric. Also outliers formulas are being used: Interquartil method and issues solved in more than 0 days are outliers. Proactive tasks included | H4: Monthly datanet
A5: % Issue Solved | B5: 95% issues solved | C5: Monthly | D5: 0.3 | E5: Yes, 120% | F5: Average of 95% of tickets solved monthly | G5: OMs must have an average of 95% of issues solved monthly. This includes proactive tasks. Only tasks resolved in the same month as the creation | H5: Monthly datanet
A6: SOPs followed | B6: SOP followed 100% of the time | C6: Monthly | D6: 0.05 | E6: Yes, 120% | F6: Use the SOPs (issue description and issues status to sellers). | G6: Use the SOPs (issue description and issues status to sellers) everytime. If SOP not used, a strike will be posted in the tracker quip. PM will look weekly 3 sellers per OM and will check wheter there is a strike. At least one message using SOP per day | H6: Quip

Sheet Strikes
A1: Alias | B1: Seller | C1: Data
A2: tiaelima | B2: Webfones | C2: 45810
A3: fpereluc | B3: Avant SP | C3: 45810
A4: qmanuelv | B4: CenterSport | C4: 45810
A5: qmanuelv | B5: FRIGELAR | C5: 45810
A6: gomrodrd | B6: Nespresso | C6: 46080

Sheet Survey Q1
A2: Parent CID | B2: Group | C2: OM | D2: IR Eligible | E2: IR User | F2: Nota Satisfaction | G2: Respondeu | H2: Submission ID | I2: Submitted On | J2: Internal Tags | K2: 1) Digite o nome da sua conta na Amazon. | L2: 2) Digite o seu código de vendedor da Amazon. (Encontre seu código de vendedor [aqui](https://sellercentral.amazon.com.br/sw/AccountInfo/MerchantToken/step/MerchantToken?ref_=macs_aimertok_cont_acinfohm)). | M2: 3) Qual seu nome completo? | N2: 4) Qual seu e-mail? | O2: 5) A sua conta na Amazon é majoritariamente: | P2: 1) Nos últimos 3 meses, quão satisfeito você esteve em vender na Amazon.com.br? | Q2: 2) Nos últimos três meses, quão satisfeito você esteve com o programa de Consultoria Estratégica - SAS? | R2: 3) Em que medida está de acordo com a seguinte afirmação: participar do programa de Consultoria Estratégica (SAS) me ajuda a crescer o meu negócio. | S2: 4) Em que medida está de acordo com a seguinte afirmação: o programa de Consultoria Estratégica (SAS) tem um bom custo benefício. | T2: 5) Quão importante os serviços abaixo oferecidos pelo programa de Consultoria Estratégica (SAS) são para você como vendedor? | U2: 6) Você tem alguma sugestão de como o programa SAS pode melhorar os nossos serviços (seleção, ads, marca, conversão, logística, promoções, resolução de problemas)? | V2: 1) Quem foi o consultor que te atendeu a maior parte do tempo nos últimos 3 meses? | W2: 2) Nos últimos três meses, quão satisfeito você esteve com o seu consultor de marketplace? | X2: 3) Baseado nos últimos três meses de serviço, o quanto você concorda ou não com as afirmações abaixo a respeito do seu consultor de marketplace? | Y2: 4) Você tem alguma sugestão de como o seu consultor pode melhorar o seu atendimento (comunicação, expertise, agilidade, plano de negócios, recomendações, suporte com a conta)? | Z2: 1) Você utiliza a página exclusiva de [Serviços Premium](http://sellercentral.amazon.com.br/gc/sas/servicos-premium)? | AA2: 2) Quão satisfeito você está com o serviço prestado? | AB2: 3) Você tem alguma sugestão de como podemos melhorar sua experiência (adicionar novas tarefas, melhorar o serviço, etc)? | AC2: 1) Você faz parte do programa da Consultoria Estratégica Amazon Select? | AD2: 2) Quão satisfeito você está com o suporte para resolução de problemas operacionais oferecido pelo [Suporte Premium](http://sellercentral.amazon.com.br/gc/sas/suporte-premium)? | AE2: 3) Tem algum feedback adicional a respeito do suporte com a resolução de problemas que você gostaria de compartilhar? | AF2: 1) Você possui um consultor específico para Amazon Ads? | AG2: 2) Quão satisfeito você está com o seu consultor de Amazon Ads? | AH2: 3) Você tem alguma sugestão de como o especialista em Ads que atende sua conta pode melhorar o seu atendimento? | AI2: 1) Por favor, classifique em ordem de importância os módulos do nosso serviço em SAS, sendo 1 o mais importante e 7 o menos importante | AJ2: 2) Quais relatórios você gostaria que a gente implementasse? Coloque em ordem de prioridade. | AK2: QuÃ£o importante os serviÃ§os abaixo oferecidos pelo programa de gerenciamento pago (SAS) sÃ£o para vocÃª como vendedor? - Gerenciamento e suporte de catÃ¡logo | AL2: QuÃ£o importante os serviÃ§os abaixo oferecidos pelo programa de gerenciamento pago (SAS) sÃ£o para vocÃª como vendedor? - Suporte com gerenciamento de inventÃ¡rio | AM2: QuÃ£o importante os serviÃ§os abaixo oferecidos pelo programa de gerenciamento pago (SAS) sÃ£o para vocÃª como vendedor? - Suporte com estratÃ©gia para novos produtos | AN2: VocÃª tem alguma sugestÃ£o de como o programa SAS pode melhorar os nossos serviÃ§os (seleÃ§Ã£o, ads, marca, conversÃ£o, logÃ­stica, promoÃ§Ãµes, resoluÃ§Ã£o de problemas)? | AO2: Quem foi o consultor que te atendeu a maior parte do tempo no perÃ­odo de Julho a Setembro de 2025? | AP2: Nos Ãºltimos trÃªs meses, quÃ£o satisfeito vocÃª esteve com o seu consultor de marketplace? | AQ2: Baseado nos Ãºltimos trÃªs meses de serviÃ§o, o quanto vocÃª concorda ou nÃ£o com as afirmaÃ§Ãµes abaixo a respeito do seu consultor de marketplace? - Meu consultor entende do meu negÃ³cio | AR2: Baseado nos Ãºltimos trÃªs meses de serviÃ§o, o quanto vocÃª concorda ou nÃ£o com as afirmaÃ§Ãµes abaixo a respeito do seu consultor de marketplace? - Meu consultor entende as necessidades do meu negÃ³cio com o programa SAS | AS2: Baseado nos Ãºltimos trÃªs meses de serviÃ§o, o quanto vocÃª concorda ou nÃ£o com as afirmaÃ§Ãµes abaixo a respeito do seu consultor de marketplace? - Meu consultor entende sobre a minha categoria de venda | AT2: Baseado nos Ãºltimos trÃªs meses de serviÃ§o, o quanto vocÃª concorda ou nÃ£o com as afirmaÃ§Ãµes abaixo a respeito do seu consultor de marketplace? - Meu consultor fornece recomendaÃ§Ãµes estratÃ©gicas | AU2: Baseado nos Ãºltimos trÃªs meses de serviÃ§o, o quanto vocÃª concorda ou nÃ£o com as afirmaÃ§Ãµes abaixo a respeito do seu consultor de marketplace? - Meu consultor tem conhecimento dos recursos do Seller Central | AV2: Baseado nos Ãºltimos trÃªs meses de serviÃ§o, o quanto vocÃª concorda ou nÃ£o com as afirmaÃ§Ãµes abaixo a respeito do seu consultor de marketplace? - Meu consultor Ã© responsivo via email | AW2: Baseado nos Ãºltimos trÃªs meses de serviÃ§o, o quanto vocÃª concorda ou nÃ£o com as afirmaÃ§Ãµes abaixo a respeito do seu consultor de marketplace? - Meu consultor se comunica por escrito de forma clara | AX2: VocÃª tem alguma sugestÃ£o de como o seu consultor pode melhorar o seu atendimento (comunicaÃ§Ã£o, expertise, agilidade, plano de negÃ³cios, recomendaÃ§Ãµes, suporte com a conta)? | AY2: VocÃª utiliza a pÃ¡gina exclusiva de ServiÃ§os Premium? | AZ2: QuÃ£o satisfeito vocÃª estÃ¡ com o serviÃ§o prestado? | BA2: VocÃª tem alguma sugestÃ£o de como podemos melhorar sua experiÃªncia (adicionar novas tarefas, melhorar o serviÃ§o, etc)? | BB2: VocÃª possui um gerente de contas operacional, responsÃ¡vel apenas pelo suporte com resoluÃ§Ã£o de problemas operacionais? | BC2: QuÃ£o satisfeito vocÃª estÃ¡ com o suporte para resoluÃ§Ã£o de problemas operacionais? | BD2: Tem algum feedback adicional a respeito do suporte com a resoluÃ§Ã£o de problemas que vocÃª gostaria de compartilhar? | BE2: VocÃª possui um consultor especÃ­fico para Amazon Ads? | BF2: QuÃ£o satisfeito vocÃª estÃ¡ com o seu consultor de Amazon Ads? | BG2: VocÃª tem alguma sugestÃ£o de como o especialista em Ads que atende sua conta pode melhorar o seu atendimento? | BH2: Por favor, classifique em ordem de importÃ¢ncia os mÃ³dulos do nosso serviÃ§o em SAS, sendo 1 o mais importante e 7 o menos importante - SeleÃ§Ã£o (recomendaÃ§Ã£o de produtos, oportunidades) | BI2: Por favor, classifique em ordem de importÃ¢ncia os mÃ³dulos do nosso serviÃ§o em SAS, sendo 1 o mais importante e 7 o menos importante - Advertising (anÃºncios patrocinados) | BJ2: Por favor, classifique em ordem de importÃ¢ncia os mÃ³dulos do nosso serviÃ§o em SAS, sendo 1 o mais importante e 7 o menos importante - Marca (registro, proteÃ§Ã£o, conteÃºdo A+, loja oficial) | BK2: Por favor, classifique em ordem de importÃ¢ncia os mÃ³dulos do nosso serviÃ§o em SAS, sendo 1 o mais importante e 7 o menos importante - ConversÃ£o (qualidade do catÃ¡logo, preÃ§os, listatem) | BL2: Por favor, classifique em ordem de importÃ¢ncia os mÃ³dulos do nosso serviÃ§o em SAS, sendo 1 o mais importante e 7 o menos importante - PromoÃ§Ãµes (ofertas, cupons, eventos) | BM2: Por favor, classifique em ordem de importÃ¢ncia os mÃ³dulos do nosso serviÃ§o em SAS, sendo 1 o mais importante e 7 o menos importante - Ajuda na resoluÃ§Ã£o de problemas operacionais | BN2: Por favor, classifique em ordem de importÃ¢ncia os mÃ³dulos do nosso serviÃ§o em SAS, sendo 1 o mais importante e 7 o menos importante - LogÃ­stica (FBA, FBAOS, DBA, logÃ­stica prÃ³pria) | BO2: Quais relatÃ³rios vocÃª gostaria que a gente implementasse? Coloque em ordem de prioridade. | BP2: Q_DataPolicyViolations
A3: 687037975702 | B3: FITHOUSE | C3: gomrodrd | D3: =IF(C3="","0","1") -> 1 | E3: =IFERROR(IF(VLOOKUP(A3,Base!AA:AA,1,0)>0,"1","0"),"0") -> 1 | F3: =IF(OR(C3="",E3="0"),"-",IF(BC3="","-",IF(OR(BC3="Muito satisfeito",BC3="Satisfeito"),"1","0"))) -> 1 | G3: =IF(BC3="","0","1") -> 1 | H3: SurveySubmission-37hkcO3uSX4euzPL7aJBK5aytTz | I3: 2026-01-02 14:06:08.156+00 | K3: FITHOUSE | L3: A9XAMWBG754P1 | M3: Kaylane Fiuza | N3: kaylane.lxdistribuidora@gmail.com | O3: Ambos | P3: Satisfeito | Q3: Muito satisfeito | R3: Concordo plenamente | S3: Concordo plenamente | T3: Recomendações Estratégicas -- Importante Assistência com Resolução de Problemas -- Muito importante Estratégia com Promoções -- Importante Gerenciamento e suporte de catálogo -- Muito importante Suporte com gerenciamento de inventário -- Importante Suporte com estratégia para novos produtos -- Importante | V3: Naiane | W3: Satisfeito | X3: Meu consultor entende do meu negócio -- Concordo plenamente Meu consultor entende as necessidades do meu negócio com o programa SAS -- Concordo plenamente Meu consultor entende sobre a minha categoria de venda -- Concordo plenamente Meu consultor fornece recomendações estratégicas -- Concordo plenamente Meu consultor tem conhecimento dos recursos do Seller Central -- Concordo plenamente Meu consultor é responsivo via email -- Concordo plenamente Meu consultor se comunica por escrito de forma clara -- Concordo plenamente | Z3: Yes | AA3: 5 | AC3: Yes | AD3: 4 | AF3: Yes | AG3: 3 | AI3: ["Promoções (ofertas, cupons, eventos)","Seleção (recomendação de produtos, oportunidades)","Marca (registro, proteção, conteúdo A+, loja oficial)","Ajuda na resolução de problemas operacionais","Advertising (anúncios patrocinados)","Conversão (qualidade do catálogo, preços, listatem)","Logística (FBA, FBA-Onsite, DBA, logística própria)"] | AK3: Importante | AL3: Muito importante | AM3: Muito importante | AO3: Ana Bon | AP3: Muito satisfeito | AQ3: Concordo plenamente | AR3: Concordo plenamente | AS3: Concordo plenamente | AT3: Concordo plenamente | AU3: Concordo plenamente | AV3: Concordo plenamente | AW3: Concordo plenamente | AY3: Sim | AZ3: Satisfeito | BB3: Sim | BC3: Satisfeito | BE3: NÃ£o | BH3: 5 | BI3: 3 | BJ3: 4 | BK3: 2 | BL3: 1 | BM3: 7 | BN3: 6 | BP3: Email Address
A4: 314278248802 | B4: SITECOURO50 | C4: joaoclan | D4: =IF(C4="","0","1") -> 1 | E4: =IFERROR(IF(VLOOKUP(A4,Base!AA:AA,1,0)>0,"1","0"),"0") -> 1 | F4: =IF(OR(C4="",E4="0"),"-",IF(BC4="","-",IF(OR(BC4="Muito satisfeito",BC4="Satisfeito"),"1","0"))) -> 1 | G4: =IF(BC4="","0","1") -> 1 | H4: SurveySubmission-37q9LcGebe8QFc7H2Gw7dnXtI9a | I4: 2026-01-05 13:27:59.956+00 | K4: Couro50 Oficial | L4: A3O6P6WAZO95DT | M4: Lucas Rodirgues Valladão | N4: lucas.valladao@mariartcouros.com.br | O4: Dono de marca | P4: Muito satisfeito | Q4: Muito satisfeito | R4: Concordo plenamente | S4: Concordo parcialmente | T4: Recomendações Estratégicas -- Muito importante Assistência com Resolução de Problemas -- Muito importante Estratégia com Promoções -- Muito importante Gerenciamento e suporte de catálogo -- Importante Suporte com gerenciamento de inventário -- Importante Suporte com estratégia para novos produtos -- Importante | V4: Sarah Meyer | W4: Muito satisfeito | X4: Meu consultor entende do meu negócio -- Concordo plenamente Meu consultor entende as necessidades do meu negócio com o programa SAS -- Concordo plenamente Meu consultor entende sobre a minha categoria de venda -- Concordo plenamente Meu consultor fornece recomendações estratégicas -- Concordo plenamente Meu consultor tem conhecimento dos recursos do Seller Central -- Concordo plenamente Meu consultor é responsivo via email -- Concordo plenamente Meu consultor se comunica por escrito de forma clara -- Concordo plenamente | Z4: No | AC4: No | AF4: Yes | AG4: 5 | AI4: ["Promoções (ofertas, cupons, eventos)","Conversão (qualidade do catálogo, preços, listatem)","Logística (FBA, FBA-Onsite, DBA, logística própria)","Ajuda na resolução de problemas operacionais","Advertising (anúncios patrocinados)","Marca (registro, proteção, conteúdo A+, loja oficial)","Seleção (recomendação de produtos, oportunidades)"] | AK4: Importante | AL4: Importante | AM4: Importante | AO4: Igor Dias | AP4: Muito satisfeito | AQ4: Concordo plenamente | AR4: Concordo plenamente | AS4: Concordo plenamente | AT4: Concordo plenamente | AU4: Concordo plenamente | AV4: Concordo plenamente | AW4: Concordo plenamente | AY4: NÃ£o | BB4: Sim | BC4: Muito satisfeito | BE4: Sim | BF4: Muito satisfeito | BH4: 1 | BI4: 2 | BJ4: 3 | BK4: 4 | BL4: 5 | BM4: 6 | BN4: 7 | BP4: Email Address
A5: 320035971002 | B5: B2 Online Oficial | C5: qmanuelv | D5: =IF(C5="","0","1") -> 1 | E5: =IFERROR(IF(VLOOKUP(A5,Base!AA:AA,1,0)>0,"1","0"),"0") -> 1 | F5: =IF(OR(C5="",E5="0"),"-",IF(BC5="","-",IF(OR(BC5="Muito satisfeito",BC5="Satisfeito"),"1","0"))) -> - | G5: =IF(BC5="","0","1") -> 0 | H5: SurveySubmission-37qEtfHaYmh5C609QJ7x8r00eex | I5: 2026-01-05 14:13:36.986+00 | K5: B2 Online | L5: A2HKNDWRM4L5KF | M5: Philipe Bicalho | N5: philipe.bicalho@b2online.com.br | O5: Revendedor | P5: Muito satisfeito | Q5: Muito satisfeito | R5: Concordo plenamente | S5: Concordo plenamente | T5: Recomendações Estratégicas -- Muito importante Assistência com Resolução de Problemas -- Muito importante Estratégia com Promoções -- Muito importante Gerenciamento e suporte de catálogo -- Muito importante Suporte com gerenciamento de inventário -- Muito importante Suporte com estratégia para novos produtos -- Muito importante | U5: Me atende perfeitamente. | V5: Ana Bon | W5: Muito satisfeito | X5: Meu consultor entende do meu negócio -- Concordo plenamente Meu consultor entende as necessidades do meu negócio com o programa SAS -- Concordo plenamente Meu consultor entende sobre a minha categoria de venda -- Concordo plenamente Meu consultor fornece recomendações estratégicas -- Concordo plenamente Meu consultor tem conhecimento dos recursos do Seller Central -- Concordo plenamente Meu consultor é responsivo via email -- Concordo plenamente Meu consultor se comunica por escrito de forma clara -- Concordo plenamente | Y5: Nenhuma sugestão. Consultora me atende satisfatoriamente. | Z5: Yes | AA5: 5 | AC5: Yes | AD5: 5 | AF5: No | AI5: ["Promoções (ofertas, cupons, eventos)","Seleção (recomendação de produtos, oportunidades)","Advertising (anúncios patrocinados)","Conversão (qualidade do catálogo, preços, listatem)","Marca (registro, proteção, conteúdo A+, loja oficial)","Ajuda na resolução de problemas operacionais","Logística (FBA, FBA-Onsite, DBA, logística própria)"] | AK5: Importante | AL5: Importante | AM5: ServiÃ§o nÃ£o Ã© oferecido | AO5: Tatiane de Assis | AP5: Satisfeito | AQ5: Concordo plenamente | AR5: Concordo plenamente | AS5: Concordo plenamente | AT5: Concordo plenamente | AU5: Concordo plenamente | AV5: Concordo plenamente | AW5: Concordo plenamente | AX5: Nos Ãºltimos meses tenho sentido uma demora nos retornos de nossas demanda via Whats App pela consultora, em comparaÃ§Ã£o a perÃ­odos anteriores. Acredito que seja devido a demandas internas na Amazon. Nada que tenha comprometido nossa performance ou atendimento, mas Ã© um ponto de atenÃ§Ã£o visando retomada do padrÃ£o de atendimento anterior. | AY5: NÃ£o | BB5: NÃ£o | BE5: Sim | BF5: Satisfeito | BH5: 7 | BI5: 3 | BJ5: 4 | BK5: 5 | BL5: 1 | BM5: 6 | BN5: 2 | BP5: Email Address
A6: 607776398302 | B6: Gato Panda | C6: joaoclan | D6: =IF(C6="","0","1") -> 1 | E6: =IFERROR(IF(VLOOKUP(A6,Base!AA:AA,1,0)>0,"1","0"),"0") -> 0 | F6: =IF(OR(C6="",E6="0"),"-",IF(BC6="","-",IF(OR(BC6="Muito satisfeito",BC6="Satisfeito"),"1","0"))) -> - | G6: =IF(BC6="","0","1") -> 0 | H6: SurveySubmission-37qKyk1OfqAAPArPrV20OJNG4VB | I6: 2026-01-05 15:03:37.045+00 | K6: GATO PANDA | L6: A3L1BX2GG542PS | M6: Sammy Dayan | N6: vendas@gatopanda.com.br | O6: Ambos | P6: Muito satisfeito | Q6: Muito satisfeito | R6: Concordo plenamente | S6: Concordo plenamente | T6: Recomendações Estratégicas -- Muito importante Assistência com Resolução de Problemas -- Muito importante Estratégia com Promoções -- Muito importante Gerenciamento e suporte de catálogo -- Muito importante Suporte com gerenciamento de inventário -- Muito importante Suporte com estratégia para novos produtos -- Muito importante | V6: Tatiane | W6: Muito satisfeito | X6: Meu consultor entende do meu negócio -- Concordo plenamente Meu consultor entende as necessidades do meu negócio com o programa SAS -- Concordo plenamente Meu consultor entende sobre a minha categoria de venda -- Concordo plenamente Meu consultor fornece recomendações estratégicas -- Concordo plenamente Meu consultor tem conhecimento dos recursos do Seller Central -- Concordo plenamente Meu consultor é responsivo via email -- Concordo plenamente Meu consultor se comunica por escrito de forma clara -- Concordo plenamente | Z6: Yes | AA6: 5 | AC6: Yes | AD6: 5 | AF6: No | AI6: ["Promoções (ofertas, cupons, eventos)","Ajuda na resolução de problemas operacionais","Logística (FBA, FBA-Onsite, DBA, logística própria)","Seleção (recomendação de produtos, oportunidades)","Advertising (anúncios patrocinados)","Conversão (qualidade do catálogo, preços, listatem)","Marca (registro, proteção, conteúdo A+, loja oficial)"] | AK6: Muito importante | AL6: Muito importante | AM6: Muito importante | AO6: Ana Bon | AP6: Satisfeito | AQ6: Concordo plenamente | AR6: Concordo plenamente | AS6: Concordo plenamente | AT6: Concordo plenamente | AU6: Concordo plenamente | AV6: Concordo plenamente | AW6: Concordo plenamente | AX6: ComunicaÃ§Ã£o da Ana Ã© Ã³tima e ela sempre procura ajudar nos nossos problemas | AY6: Sim | AZ6: Satisfeito | BB6: NÃ£o | BE6: Sim | BF6: Nem satisfeito, nem insatisfeito | BH6: 1 | BI6: 6 | BJ6: 5 | BK6: 4 | BL6: 3 | BM6: 2 | BN6: 7 | BO6: RelatÃ³rio que consiga identificar imagens incorretas no anÃºncio para ser ajustado. | BP6: Email Address
A7: 601998582602 | B7: Usee Brasil | C7: qmanuelv | D7: =IF(C7="","0","1") -> 1 | E7: =IFERROR(IF(VLOOKUP(A7,Base!AA:AA,1,0)>0,"1","0"),"0") -> 1 | F7: =IF(OR(C7="",E7="0"),"-",IF(BC7="","-",IF(OR(BC7="Muito satisfeito",BC7="Satisfeito"),"1","0"))) -> - | G7: =IF(BC7="","0","1") -> 0 | H7: SurveySubmission-37qYoTrURIg53PrPiP22su5J326 | I7: 2026-01-05 16:57:22.115+00 | K7: Usee Brasil | L7: A1S66RXUCVO3OW | M7: Humberto Machado Kiche | N7: humberto.machado@useebrasil.com.br | O7: Ambos | P7: Satisfeito | Q7: Muito satisfeito | R7: Concordo plenamente | S7: Concordo plenamente | T7: Recomendações Estratégicas -- Muito importante Assistência com Resolução de Problemas -- Muito importante Estratégia com Promoções -- Muito importante Gerenciamento e suporte de catálogo -- Muito importante Suporte com gerenciamento de inventário -- Muito importante Suporte com estratégia para novos produtos -- Importante | V7: Karime | W7: Muito satisfeito | X7: Meu consultor entende do meu negócio -- Concordo plenamente Meu consultor entende as necessidades do meu negócio com o programa SAS -- Concordo plenamente Meu consultor entende sobre a minha categoria de venda -- Concordo plenamente Meu consultor fornece recomendações estratégicas -- Concordo plenamente Meu consultor tem conhecimento dos recursos do Seller Central -- Concordo plenamente Meu consultor é responsivo via email -- Concordo plenamente Meu consultor se comunica por escrito de forma clara -- Concordo plenamente | Z7: Yes | AA7: 5 | AC7: Yes | AD7: 5 | AF7: No | AI7: ["Ajuda na resolução de problemas operacionais","Promoções (ofertas, cupons, eventos)","Conversão (qualidade do catálogo, preços, listatem)","Marca (registro, proteção, conteúdo A+, loja oficial)","Logística (FBA, FBA-Onsite, DBA, logística própria)","Advertising (anúncios patrocinados)","Seleção (recomendação de produtos, oportunidades)"] | AK7: Muito importante | AL7: Muito importante | AM7: Muito importante | AO7: Rafaela Saad | AP7: Muito satisfeito | AQ7: Concordo plenamente | AR7: Concordo plenamente | AS7: Concordo plenamente | AT7: Concordo plenamente | AU7: Concordo plenamente | AV7: Concordo plenamente | AW7: Concordo plenamente | AY7: Sim | AZ7: Muito satisfeito | BB7: NÃ£o | BE7: Sim | BF7: Satisfeito | BH7: 3 | BI7: 4 | BJ7: 6 | BK7: 5 | BL7: 1 | BM7: 2 | BN7: 7 | BP7: Email Address
A8: 487573149502 | B8: Dellas Fit | D8: =IF(C8="","0","1") -> 0 | E8: =IFERROR(IF(VLOOKUP(A8,Base!AA:AA,1,0)>0,"1","0"),"0") -> 0 | F8: =IF(OR(C8="",E8="0"),"-",IF(BC8="","-",IF(OR(BC8="Muito satisfeito",BC8="Satisfeito"),"1","0"))) -> - | G8: =IF(BC8="","0","1") -> 1 | H8: SurveySubmission-37qZwtLnlFWtoA7eQeEOtRmmScm | I8: 2026-01-05 17:06:43.273+00 | K8: Dellas Fit | L8: A2U3V3MF9GB7LK | M8: Jéssica Cristina Azalim | N8: jessica.azalim@helpvend.com.br | O8: Dono de marca | P8: Muito satisfeito | Q8: Muito satisfeito | R8: Concordo plenamente | S8: Concordo plenamente | T8: Recomendações Estratégicas -- Muito importante Assistência com Resolução de Problemas -- Muito importante Estratégia com Promoções -- Muito importante Gerenciamento e suporte de catálogo -- Muito importante Suporte com gerenciamento de inventário -- Muito importante Suporte com estratégia para novos produtos -- Muito importante | V8: Karime | W8: Muito satisfeito | X8: Meu consultor entende do meu negócio -- Concordo plenamente Meu consultor entende as necessidades do meu negócio com o programa SAS -- Concordo plenamente Meu consultor entende sobre a minha categoria de venda -- Concordo plenamente Meu consultor fornece recomendações estratégicas -- Concordo plenamente Meu consultor tem conhecimento dos recursos do Seller Central -- Concordo plenamente Meu consultor é responsivo via email -- Concordo plenamente Meu consultor se comunica por escrito de forma clara -- Concordo plenamente | Z8: No | AC8: No | AF8: No | AI8: ["Promoções (ofertas, cupons, eventos)","Ajuda na resolução de problemas operacionais","Logística (FBA, FBA-Onsite, DBA, logística própria)","Conversão (qualidade do catálogo, preços, listatem)","Marca (registro, proteção, conteúdo A+, loja oficial)","Advertising (anúncios patrocinados)","Seleção (recomendação de produtos, oportunidades)"] | AK8: Importante | AL8: Importante | AM8: Sem importÃ¢ncia | AN8: Acredito que o programa podia ser um pouco mais focado, com menos sellers na carteira de cada gerente, isso ajudaria a ter uma analise mais profunda dentro da categoria de atuaÃ§Ã£o, trazendo dados dos concorrentes, trazendo diferenciais que realmente tragam mais visibilidade e trafego para nossos produtos | AO8: Naiane | AP8: Muito satisfeito | AQ8: Concordo parcialmente | AR8: Concordo plenamente | AS8: Concordo plenamente | AT8: Concordo plenamente | AU8: Concordo parcialmente | AV8: Concordo plenamente | AW8: Concordo plenamente | AY8: Sim | AZ8: Satisfeito | BA8: Muitas vezes temos algum "erro" ao enviar alguma planilha, seria interessante que devolutiva trouxesse exatamente o que deu errado para que fosse corrigido, mas acaba que ficamos na tentativa e erro... | BB8: Sim | BC8: Muito satisfeito | BE8: Sim | BF8: Satisfeito | BG8: Ads Ã© por grande parte terrivel, existe uma dificuldade operacial de trazer resultados com um custo baixo para o cliente | BH8: 7 | BI8: 3 | BJ8: 6 | BK8: 4 | BL8: 1 | BM8: 2 | BN8: 5 | BO8: Seria interessante um relatÃ³rio que trouxesse o trafego do meu produto, quais Palavras chaves levaram para esse trefego e quanto eu estou % competitivo em questao de trafego em relaÃ§ao aos meus concorrentes | BP8: Email Address
A9: 481703768002 | B9: Docelar Enxovais | C9: joaoclan | D9: =IF(C9="","0","1") -> 1 | E9: =IFERROR(IF(VLOOKUP(A9,Base!AA:AA,1,0)>0,"1","0"),"0") -> 1 | F9: =IF(OR(C9="",E9="0"),"-",IF(BC9="","-",IF(OR(BC9="Muito satisfeito",BC9="Satisfeito"),"1","0"))) -> - | G9: =IF(BC9="","0","1") -> 0 | H9: SurveySubmission-37qeCT72Btq18KqxTbWE1hBeZ4I | I9: 2026-01-05 17:41:40.451+00 | K9: Paulo Cezar Enxovais | L9: ACLCI1HBSPWGD | M9: Paulo | N9: financeiro@paulocezarenxovais.com.br | O9: Ambos | P9: Satisfeito | Q9: Satisfeito | R9: Concordo plenamente | S9: Concordo parcialmente | T9: Recomendações Estratégicas -- Importante Assistência com Resolução de Problemas -- Importante Estratégia com Promoções -- Muito importante Gerenciamento e suporte de catálogo -- Importante Suporte com gerenciamento de inventário -- Importante Suporte com estratégia para novos produtos -- Serviço não é oferecido | V9: Tatiane Assis | W9: Satisfeito | X9: Meu consultor entende do meu negócio -- Concordo plenamente Meu consultor entende as necessidades do meu negócio com o programa SAS -- Concordo plenamente Meu consultor entende sobre a minha categoria de venda -- Concordo plenamente Meu consultor fornece recomendações estratégicas -- Concordo parcialmente Meu consultor tem conhecimento dos recursos do Seller Central -- Concordo plenamente Meu consultor é responsivo via email -- Concordo parcialmente Meu consultor se comunica por escrito de forma clara -- Concordo plenamente | Z9: No | AC9: No | AF9: No | AI9: ["Ajuda na resolução de problemas operacionais","Promoções (ofertas, cupons, eventos)","Logística (FBA, FBA-Onsite, DBA, logística própria)","Conversão (qualidade do catálogo, preços, listatem)","Advertising (anúncios patrocinados)","Marca (registro, proteção, conteúdo A+, loja oficial)","Seleção (recomendação de produtos, oportunidades)"] | AK9: Sem importÃ¢ncia | AL9: Sem importÃ¢ncia | AM9: Muito importante | AO9: Rodrigo Portela | AP9: Muito satisfeito | AQ9: Concordo plenamente | AR9: Concordo plenamente | AS9: Concordo plenamente | AT9: Concordo plenamente | AU9: Concordo plenamente | AV9: Concordo plenamente | AW9: Concordo plenamente | AY9: Sim | AZ9: Nem satisfeito, nem insatisfeito | BB9: NÃ£o | BE9: Sim | BF9: Nem satisfeito, nem insatisfeito | BH9: 7 | BI9: 6 | BJ9: 5 | BK9: 2 | BL9: 3 | BM9: 1 | BN9: 4 | BP9: Email Address
A10: 247227556102 | B10: Casa Dona | C10: qmanuelv | D10: =IF(C10="","0","1") -> 1 | E10: =IFERROR(IF(VLOOKUP(A10,Base!AA:AA,1,0)>0,"1","0"),"0") -> 1 | F10: =IF(OR(C10="",E10="0"),"-",IF(BC10="","-",IF(OR(BC10="Muito satisfeito",BC10="Satisfeito"),"1","0"))) -> 1 | G10: =IF(BC10="","0","1") -> 1 | H10: SurveySubmission-37qiZnHXBDXsol5lc4HdKe80zsw | I10: 2026-01-05 18:17:39.485+00 | K10: Casa Dona | L10: A1MKGFUOFC9AMW | M10: Cristina Thomaz | N10: cristina.thomaz@casadonasa.com.br | O10: Dono de marca | P10: Muito satisfeito | Q10: Muito satisfeito | R10: Concordo plenamente | S10: Concordo plenamente | T10: Recomendações Estratégicas -- Muito importante Assistência com Resolução de Problemas -- Importante Estratégia com Promoções -- Muito importante Gerenciamento e suporte de catálogo -- Muito importante Suporte com gerenciamento de inventário -- Importante Suporte com estratégia para novos produtos -- Importante | V10: Ana Bon | W10: Muito satisfeito | X10: Meu consultor entende do meu negócio -- Concordo plenamente Meu consultor entende as necessidades do meu negócio com o programa SAS -- Concordo plenamente Meu consultor entende sobre a minha categoria de venda -- Concordo plenamente Meu consultor fornece recomendações estratégicas -- Concordo plenamente Meu consultor tem conhecimento dos recursos do Seller Central -- Concordo plenamente Meu consultor é responsivo via email -- Concordo plenamente Meu consultor se comunica por escrito de forma clara -- Concordo plenamente | Z10: Yes | AA10: 5 | AC10: Yes | AD10: 5 | AE10: Azazzu está a frente do nosso ads hj e está sendo muito positivo, estamos satisfeitos. | AF10: Yes | AG10: 5 | AH10: Gabriel e Joice da Azazzu estão a frente do ads e eles são nota 1000 qto ao trabalho num todo. | AI10: ["Conversão (qualidade do catálogo, preços, listatem)","Advertising (anúncios patrocinados)","Promoções (ofertas, cupons, eventos)","Seleção (recomendação de produtos, oportunidades)","Marca (registro, proteção, conteúdo A+, loja oficial)","Ajuda na resolução de problemas operacionais","Logística (FBA, FBA-Onsite, DBA, logística própria)"] | AJ10: Relação de cobrança de tarifas com prazo maior que 30 dias, e relatorio de gasto de ads por item com prazo maior tb e notas dos asins, que validasse o cadastro no todo e não o asin (variação) como é hj. | AK10: Muito importante | AL10: Muito importante | AM10: Muito importante | AN10: PRECISAMOS DE REBATE | AO10: Alexandre Werner | AP10: Muito satisfeito | AQ10: Concordo plenamente | AR10: Concordo plenamente | AS10: Concordo plenamente | AT10: Concordo plenamente | AU10: Concordo plenamente | AV10: Concordo plenamente | AW10: Concordo plenamente | AX10: MAIS REBATE | AY10: Sim | AZ10: Muito satisfeito | BB10: Sim | BC10: Muito satisfeito | BE10: Sim | BF10: Muito satisfeito | BH10: 3 | BI10: 5 | BJ10: 6 | BK10: 7 | BL10: 2 | BM10: 1 | BN10: 4 | BP10: Email Address
A11: 351067276502 | B11: Sanbox Eletro | C11: tiaelima | D11: =IF(C11="","0","1") -> 1 | E11: =IFERROR(IF(VLOOKUP(A11,Base!AA:AA,1,0)>0,"1","0"),"0") -> 1 | F11: =IF(OR(C11="",E11="0"),"-",IF(BC11="","-",IF(OR(BC11="Muito satisfeito",BC11="Satisfeito"),"1","0"))) -> - | G11: =IF(BC11="","0","1") -> 0 | H11: SurveySubmission-37qiaLYsJsDA4dlzNpalAApX8y7 | I11: 2026-01-05 18:17:44.53+00 | K11: Sanbox Eletro | L11: A20JDTYOVRDV8M | M11: Davi Costa | N11: davi.costa@sanbox.com.br | O11: Ambos | P11: Satisfeito | Q11: Satisfeito | R11: Concordo plenamente | S11: Concordo parcialmente | T11: Recomendações Estratégicas -- Muito importante Assistência com Resolução de Problemas -- Muito importante Estratégia com Promoções -- Muito importante Gerenciamento e suporte de catálogo -- Sem importância Suporte com gerenciamento de inventário -- Sem importância Suporte com estratégia para novos produtos -- Sem importância | U11: Promoções deveriam ser negociadas para o dia e não para entrar com rebate um semana depois, perdemos todo feeling da negociação quando entra uma semana depois | V11: Luciana Tavares | W11: Muito satisfeito | X11: Meu consultor entende do meu negócio -- Concordo plenamente Meu consultor entende as necessidades do meu negócio com o programa SAS -- Concordo plenamente Meu consultor entende sobre a minha categoria de venda -- Concordo parcialmente Meu consultor fornece recomendações estratégicas -- Concordo plenamente Meu consultor tem conhecimento dos recursos do Seller Central -- Concordo plenamente Meu consultor é responsivo via email -- Concordo plenamente Meu consultor se comunica por escrito de forma clara -- Concordo plenamente | Y11: Gostamos muito da Luciana, nada a reclamar | Z11: No | AC11: Yes | AD11: 4 | AE11: Estamos com uma conta bloqueada os anuncios e precisava resolver isos | AF11: No | AI11: [] | AK11: Muito importante | AL11: Muito importante | AM11: Muito importante | AN11: PoderÃ­amos ter uma assessoria um pouco mais estratÃ©gia no todo e nÃ£o apenas em promoÃ§Ãµes. Como insights de estratÃ©gia em ADS, uma resoluÃ§Ã£o mais rÃ¡pida e eficaz em nosso catÃ¡logo que deia muito a deseja quando o assunto Ã© ajuste de tÃ­tulos. | AO11: Sarah Meyer | AP11: Satisfeito | AQ11: Concordo plenamente | AR11: Concordo plenamente | AS11: Concordo plenamente | AT11: Concordo parcialmente | AU11: Concordo parcialmente | AV11: Concordo parcialmente | AW11: Concordo parcialmente | AX11: Sarah vem se dedicando a cada dia, tem nos ajudado mas como comentei anteriormente, gostarÃ­amos de receber mais insights do que relatÃ³rios para que assim nossas vendas melhores e mais suporte quanto ao nosso catÃ¡logo para que seja mais assertivo.. | AY11: Sim | AZ11: Muito satisfeito | BA11: A priori sem comentÃ¡rios | BB11: NÃ£o | BE11: NÃ£o | BH11: 2 | BI11: 4 | BJ11: 7 | BK11: 1 | BL11: 3 | BM11: 5 | BN11: 6 | BO11: Quanto a relatÃ³rios estamos bem abastecidos semanalmente... | BP11: Email Address
A12: 639370275302 | B12: Mimorada | C12: joaoclan | D12: =IF(C12="","0","1") -> 1 | E12: =IFERROR(IF(VLOOKUP(A12,Base!AA:AA,1,0)>0,"1","0"),"0") -> 1 | F12: =IF(OR(C12="",E12="0"),"-",IF(BC12="","-",IF(OR(BC12="Muito satisfeito",BC12="Satisfeito"),"1","0"))) -> 1 | G12: =IF(BC12="","0","1") -> 1 | H12: SurveySubmission-37qj83fQWouDatQwwyuCTVvEqCy | I12: 2026-01-05 18:22:12.689+00 | K12: Mimorada | L12: A2UW4VQQVFZQ4H | M12: Lara Paim | N12: lara.silva@grupobrinox.com.br | O12: Revendedor | P12: Muito satisfeito | Q12: Muito satisfeito | R12: Concordo plenamente | S12: Concordo parcialmente | T12: Recomendações Estratégicas -- Muito importante Assistência com Resolução de Problemas -- Muito importante Estratégia com Promoções -- Muito importante Gerenciamento e suporte de catálogo -- Importante Suporte com gerenciamento de inventário -- Muito importante Suporte com estratégia para novos produtos -- Importante | U12: Retirar ou flexibilizar a ferramenta de "Preço Externo Competitivo" que afeta muito o funcionamento da conta e as vendas. | V12: Stephanie Shinohara | W12: Muito satisfeito | X12: Meu consultor entende do meu negócio -- Concordo plenamente Meu consultor entende as necessidades do meu negócio com o programa SAS -- Concordo plenamente Meu consultor entende sobre a minha categoria de venda -- Concordo plenamente Meu consultor fornece recomendações estratégicas -- Concordo plenamente Meu consultor tem conhecimento dos recursos do Seller Central -- Concordo plenamente Meu consultor é responsivo via email -- Concordo plenamente Meu consultor se comunica por escrito de forma clara -- Concordo plenamente | Z12: Yes | AA12: 5 | AC12: Yes | AD12: 5 | AF12: No | AI12: ["Ajuda na resolução de problemas operacionais","Promoções (ofertas, cupons, eventos)","Logística (FBA, FBA-Onsite, DBA, logística própria)","Conversão (qualidade do catálogo, preços, listatem)","Marca (registro, proteção, conteúdo A+, loja oficial)","Seleção (recomendação de produtos, oportunidades)","Advertising (anúncios patrocinados)"] | AK12: Muito importante | AL12: Muito importante | AM12: Muito importante | AO12: Thomas Thalenberg | AP12: Muito satisfeito | AQ12: Concordo plenamente | AR12: Concordo plenamente | AS12: Concordo plenamente | AT12: Concordo plenamente | AU12: Concordo plenamente | AV12: Concordo plenamente | AW12: Concordo plenamente | AY12: Sim | AZ12: Satisfeito | BB12: Sim | BC12: Satisfeito | BE12: Sim | BF12: Insatisfeito | BH12: 7 | BI12: 5 | BJ12: 6 | BK12: 1 | BL12: 2 | BM12: 3 | BN12: 4 | BP12: Email Address
A13: 655945459902 | B13: Ecomprei - Devintex | C13: qmanuelv | D13: =IF(C13="","0","1") -> 1 | E13: =IFERROR(IF(VLOOKUP(A13,Base!AA:AA,1,0)>0,"1","0"),"0") -> 1 | F13: =IF(OR(C13="",E13="0"),"-",IF(BC13="","-",IF(OR(BC13="Muito satisfeito",BC13="Satisfeito"),"1","0"))) -> - | G13: =IF(BC13="","0","1") -> 0 | H13: SurveySubmission-37qjoPgwD8F19FpkZunKkzbMZyk | I13: 2026-01-05 18:27:49.322+00 | K13: Ecomprei | L13: A2SVSWCYO9DMJB | M13: David de Santana Lima | N13: david.lima@devintex.com.br | O13: Dono de marca | P13: Satisfeito | Q13: Muito satisfeito | R13: Concordo plenamente | S13: Concordo plenamente | T13: Recomendações Estratégicas -- Muito importante Assistência com Resolução de Problemas -- Importante Estratégia com Promoções -- Muito importante Gerenciamento e suporte de catálogo -- Importante Suporte com gerenciamento de inventário -- Importante Suporte com estratégia para novos produtos -- Importante | U13: Em ADS, acreditamos que a plataforma de vocês é muito difícil o entendimento, com isso, os resultados são baixo | V13: Karime Cabral | W13: Muito satisfeito | X13: Meu consultor entende do meu negócio -- Concordo parcialmente Meu consultor entende as necessidades do meu negócio com o programa SAS -- Concordo parcialmente Meu consultor entende sobre a minha categoria de venda -- Concordo plenamente Meu consultor fornece recomendações estratégicas -- Concordo parcialmente Meu consultor tem conhecimento dos recursos do Seller Central -- Concordo plenamente Meu consultor é responsivo via email -- Concordo plenamente Meu consultor se comunica por escrito de forma clara -- Concordo plenamente | Y13: Apenas melhorar as recomendações das oportunidades dentro da Amazon, Canais para promoção, exemplos: Afiliados. trazer opções que podemos trabalhar com outra estratégia além de preço | Z13: Yes | AA13: 5 | AB13: Não | AC13: Yes | AD13: 5 | AE13: Nossa experiência está sendo ótima | AF13: Yes | AG13: 1 | AH13: Toda estratégia que a consultora nos deu, ficamos com um resultado pior (ROI), nos criando as campanhas com o que já sabemos de Amazon, temos um retorno melhor. | AI13: ["Seleção (recomendação de produtos, oportunidades)","Ajuda na resolução de problemas operacionais","Marca (registro, proteção, conteúdo A+, loja oficial)","Conversão (qualidade do catálogo, preços, listatem)","Logística (FBA, FBA-Onsite, DBA, logística própria)","Advertising (anúncios patrocinados)","Promoções (ofertas, cupons, eventos)"] | AJ13: um relatório geral claro, que venha em Excel, das vendas. hoje temos dificuldades com os relatórios da Amazon, pois vem em TXT, na conversão para Excel da erro | AK13: Muito importante | AL13: Muito importante | AM13: Muito importante | AO13: Rafaela Saad | AP13: Muito satisfeito | AQ13: Concordo plenamente | AR13: Concordo plenamente | AS13: Concordo plenamente | AT13: Concordo plenamente | AU13: Concordo plenamente | AV13: Concordo plenamente | AW13: Concordo plenamente | AY13: Sim | AZ13: Muito satisfeito | BB13: NÃ£o | BE13: NÃ£o | BH13: 5 | BI13: 7 | BJ13: 3 | BK13: 4 | BL13: 2 | BM13: 1 | BN13: 6 | BP13: Email Address
A14: 10369153302 | B14: TNTinfoLoja | C14: tiaelima | D14: =IF(C14="","0","1") -> 1 | E14: =IFERROR(IF(VLOOKUP(A14,Base!AA:AA,1,0)>0,"1","0"),"0") -> 1 | F14: =IF(OR(C14="",E14="0"),"-",IF(BC14="","-",IF(OR(BC14="Muito satisfeito",BC14="Satisfeito"),"1","0"))) -> - | G14: =IF(BC14="","0","1") -> 0 | H14: SurveySubmission-37qk8teI179hUDkTV5sV7vYWRVm | I14: 2026-01-05 18:30:32.401+00 | K14: TNTinfoLoja | L14: AZXF92ML84B44 | M14: Victor Vieira Junqueira | N14: loja05@tntinfo.com.br | O14: Revendedor | P14: Muito satisfeito | Q14: Muito satisfeito | R14: Concordo plenamente | S14: Concordo plenamente | T14: Recomendações Estratégicas -- Muito importante Assistência com Resolução de Problemas -- Muito importante Estratégia com Promoções -- Muito importante Gerenciamento e suporte de catálogo -- Muito importante Suporte com gerenciamento de inventário -- Muito importante Suporte com estratégia para novos produtos -- Muito importante | V14: Alexandre Werner | W14: Muito satisfeito | X14: Meu consultor entende do meu negócio -- Concordo plenamente Meu consultor entende as necessidades do meu negócio com o programa SAS -- Concordo plenamente Meu consultor entende sobre a minha categoria de venda -- Concordo plenamente Meu consultor fornece recomendações estratégicas -- Concordo plenamente Meu consultor tem conhecimento dos recursos do Seller Central -- Concordo plenamente Meu consultor é responsivo via email -- Concordo plenamente Meu consultor se comunica por escrito de forma clara -- Concordo plenamente | Y14: Podria no recomendar mais produtos chave ou lancamentos | Z14: Yes | AA14: 5 | AC14: Yes | AD14: 4 | AE14: Veiculo de comunicacao um pouco confuso. Nao sabemos se mantemos as conversas dentro do chat, por email... poderiam unificar o meio de comunicacao | AF14: Yes | AG14: 4 | AI14: ["Logística (FBA, FBA-Onsite, DBA, logística própria)","Ajuda na resolução de problemas operacionais","Seleção (recomendação de produtos, oportunidades)","Marca (registro, proteção, conteúdo A+, loja oficial)","Promoções (ofertas, cupons, eventos)","Conversão (qualidade do catálogo, preços, listatem)","Advertising (anúncios patrocinados)"] | AK14: Muito importante | AL14: Muito importante | AM14: Muito importante | AN14: No momento nÃ£o | AO14: Thomas Thalenberg | AP14: Muito satisfeito | AQ14: Concordo plenamente | AR14: Concordo plenamente | AS14: Concordo plenamente | AT14: Concordo plenamente | AU14: Concordo plenamente | AV14: Concordo plenamente | AW14: Concordo plenamente | AX14: NÃ£o, estamos muito satisfeitos com ele, ele nos atende muito bem. | AY14: Sim | AZ14: Muito satisfeito | BA14: No momento nÃ£o, o que eu pedia vocÃªs estÃ£o fazendo, que sÃ£o aÃ§Ãµes de reduÃ§Ã£o de comissÃ£o. | BB14: NÃ£o | BE14: Sim | BF14: Nem satisfeito, nem insatisfeito | BG14: No momento nÃ£o, vamos voltar a utilozar o serviÃ§o em breve | BH14: 3 | BI14: 7 | BJ14: 5 | BK14: 4 | BL14: 1 | BM14: 6 | BN14: 2 | BO14: Atualmente, acho que os itens em ruptura do 1P, para a gente aproveitar essas oportunidades | BP14: Email Address
A15: 97596278102 | B15: Trevizo Suplementos. | C15: fpereluc | D15: =IF(C15="","0","1") -> 1 | E15: =IFERROR(IF(VLOOKUP(A15,Base!AA:AA,1,0)>0,"1","0"),"0") -> 1 | F15: =IF(OR(C15="",E15="0"),"-",IF(BC15="","-",IF(OR(BC15="Muito satisfeito",BC15="Satisfeito"),"1","0"))) -> 1 | G15: =IF(BC15="","0","1") -> 1 | H15: SurveySubmission-37ql7WLnrJ0EKqdnu009v7dn0l1 | I15: 2026-01-05 18:38:34.186+00 | K15: Dark Lab Suplementos | L15: A26A8MT1BQFCBQ | M15: Aline Laranjeira | N15: alinelaranjeira@darklabsuplementos.com.br | O15: Dono de marca | P15: Muito satisfeito | Q15: Satisfeito | R15: Concordo plenamente | S15: Concordo parcialmente | T15: Recomendações Estratégicas -- Muito importante Assistência com Resolução de Problemas -- Muito importante Estratégia com Promoções -- Muito importante Gerenciamento e suporte de catálogo -- Importante Suporte com gerenciamento de inventário -- Importante Suporte com estratégia para novos produtos -- Importante | V15: Thomas Thalenberg | W15: Muito satisfeito | X15: Meu consultor entende do meu negócio -- Concordo plenamente Meu consultor entende as necessidades do meu negócio com o programa SAS -- Concordo plenamente Meu consultor entende sobre a minha categoria de venda -- Concordo plenamente Meu consultor fornece recomendações estratégicas -- Concordo parcialmente Meu consultor tem conhecimento dos recursos do Seller Central -- Concordo plenamente Meu consultor é responsivo via email -- Concordo plenamente Meu consultor se comunica por escrito de forma clara -- Concordo plenamente | Z15: Yes | AA15: 4 | AC15: Yes | AD15: 5 | AF15: Yes | AG15: 3 | AI15: ["Promoções (ofertas, cupons, eventos)","Ajuda na resolução de problemas operacionais","Logística (FBA, FBA-Onsite, DBA, logística própria)","Conversão (qualidade do catálogo, preços, listatem)","Advertising (anúncios patrocinados)","Seleção (recomendação de produtos, oportunidades)","Marca (registro, proteção, conteúdo A+, loja oficial)"] | AK15: Muito importante | AL15: ServiÃ§o nÃ£o Ã© oferecido | AM15: ServiÃ§o nÃ£o Ã© oferecido | AN15: O marketplace estÃ¡ muito atras em relaÃ§Ã£o a outros marketplaces. Infelizmente. | AO15: Julia Brito | AP15: Nem satisfeito, nem insatisfeito | AQ15: Discordo | AR15: Concordo parcialmente | AS15: Discordo | AT15: Discordo | AU15: Nem concordo, nem discordo | AV15: Nem concordo, nem discordo | AW15: Concordo parcialmente | AX15: Ajudar a destravar a loja com mais Ãªnfase | AY15: Sim | AZ15: Nem satisfeito, nem insatisfeito | BB15: Sim | BC15: Satisfeito | BE15: NÃ£o | BH15: 5 | BI15: 6 | BJ15: 7 | BK15: 4 | BL15: 1 | BM15: 3 | BN15: 2 | BP15: Email Address
A16: 795323312102 | B16: Krokodilus | C16: qmanuelv | D16: =IF(C16="","0","1") -> 1 | E16: =IFERROR(IF(VLOOKUP(A16,Base!AA:AA,1,0)>0,"1","0"),"0") -> 1 | F16: =IF(OR(C16="",E16="0"),"-",IF(BC16="","-",IF(OR(BC16="Muito satisfeito",BC16="Satisfeito"),"1","0"))) -> - | G16: =IF(BC16="","0","1") -> 0 | H16: SurveySubmission-37qlgfKYoXPxufpu1UGOcs93Mfg | I16: 2026-01-05 18:43:14.534+00 | K16: Krokodilus | L16: A1TL5IEQM3H5EI | M16: Matheus Castanho de Menezes | N16: pointbplus@gmail.com | O16: Ambos | P16: Satisfeito | Q16: Satisfeito | R16: Concordo parcialmente | S16: Concordo plenamente | T16: Recomendações Estratégicas -- Muito importante Assistência com Resolução de Problemas -- Muito importante Estratégia com Promoções -- Muito importante Gerenciamento e suporte de catálogo -- Muito importante Suporte com gerenciamento de inventário -- Muito importante Suporte com estratégia para novos produtos -- Muito importante | V16: Karime | W16: Satisfeito | X16: Meu consultor entende do meu negócio -- Concordo plenamente Meu consultor entende as necessidades do meu negócio com o programa SAS -- Concordo plenamente Meu consultor entende sobre a minha categoria de venda -- Concordo plenamente Meu consultor fornece recomendações estratégicas -- Concordo plenamente Meu consultor tem conhecimento dos recursos do Seller Central -- Concordo plenamente Meu consultor é responsivo via email -- Concordo plenamente Meu consultor se comunica por escrito de forma clara -- Concordo plenamente | Z16: Yes | AA16: 5 | AC16: Yes | AD16: 5 | AF16: Yes | AG16: 5 | AI16: ["Promoções (ofertas, cupons, eventos)","Seleção (recomendação de produtos, oportunidades)","Advertising (anúncios patrocinados)","Marca (registro, proteção, conteúdo A+, loja oficial)","Conversão (qualidade do catálogo, preços, listatem)","Ajuda na resolução de problemas operacionais","Logística (FBA, FBA-Onsite, DBA, logística própria)"] | AK16: Muito importante | AL16: Importante | AM16: Sem importÃ¢ncia | AO16: Julia de Brito | AP16: Muito satisfeito | AQ16: Concordo plenamente | AR16: Concordo parcialmente | AS16: Concordo plenamente | AT16: Concordo parcialmente | AU16: Concordo plenamente | AV16: Concordo plenamente | AW16: Concordo plenamente | AY16: NÃ£o | BB16: NÃ£o | BE16: Sim | BF16: Muito satisfeito | BH16: 5 | BI16: 4 | BJ16: 7 | BK16: 1 | BL16: 6 | BM16: 2 | BN16: 3 | BO16: AnÃ¡lise da concorrÃªncia | BP16: Email Address
A17: 30887912302 | B17: H2O Purificadores | C17: qmanuelv | D17: =IF(C17="","0","1") -> 1 | E17: =IFERROR(IF(VLOOKUP(A17,Base!AA:AA,1,0)>0,"1","0"),"0") -> 1 | F17: =IF(OR(C17="",E17="0"),"-",IF(BC17="","-",IF(OR(BC17="Muito satisfeito",BC17="Satisfeito"),"1","0"))) -> - | G17: =IF(BC17="","0","1") -> 0 | H17: SurveySubmission-37qmEWZp2NGjznF16Iq9mPHQSOU | I17: 2026-01-05 18:47:43.315+00 | K17: H2O Purificadores | L17: A1DQQPB2DSSMG5 | M17: Julia Gabrielly Gones dos Santos | N17: julia.santos@h2opurificadores.com | O17: Dono de marca | P17: Satisfeito | Q17: Muito satisfeito | R17: Concordo plenamente | S17: Concordo plenamente | T17: Recomendações Estratégicas -- Muito importante Assistência com Resolução de Problemas -- Muito importante Estratégia com Promoções -- Muito importante Gerenciamento e suporte de catálogo -- Muito importante Suporte com gerenciamento de inventário -- Muito importante Suporte com estratégia para novos produtos -- Muito importante | U17: Não | V17: Matheus Balbino | W17: Muito satisfeito | X17: Meu consultor entende do meu negócio -- Concordo plenamente Meu consultor entende as necessidades do meu negócio com o programa SAS -- Concordo plenamente Meu consultor entende sobre a minha categoria de venda -- Concordo plenamente Meu consultor fornece recomendações estratégicas -- Concordo plenamente Meu consultor tem conhecimento dos recursos do Seller Central -- Concordo plenamente Meu consultor é responsivo via email -- Concordo plenamente Meu consultor se comunica por escrito de forma clara -- Concordo plenamente | Y17: Não | Z17: No | AC17: Yes | AD17: 5 | AF17: No | AI17: ["Logística (FBA, FBA-Onsite, DBA, logística própria)","Promoções (ofertas, cupons, eventos)","Advertising (anúncios patrocinados)","Seleção (recomendação de produtos, oportunidades)","Conversão (qualidade do catálogo, preços, listatem)","Marca (registro, proteção, conteúdo A+, loja oficial)","Ajuda na resolução de problemas operacionais"] | AJ17: Os relatórios atuais antendem bem | AK17: Muito importante | AL17: Muito importante | AM17: Muito importante | AO17: Thomas Thalenberg | AP17: Muito satisfeito | AQ17: Discordo totalmente | AR17: Discordo totalmente | AS17: Discordo totalmente | AT17: Discordo totalmente | AU17: Discordo totalmente | AV17: Discordo totalmente | AW17: Discordo totalmente | AY17: Sim | AZ17: Satisfeito | BB17: NÃ£o | BE17: Sim | BF17: Muito satisfeito | BH17: 1 | BI17: 5 | BJ17: 6 | BK17: 7 | BL17: 4 | BM17: 2 | BN17: 3 | BP17: Email Address
A18: 755841394202 | B18: Na Web | C18: joaoclan | D18: =IF(C18="","0","1") -> 1 | E18: =IFERROR(IF(VLOOKUP(A18,Base!AA:AA,1,0)>0,"1","0"),"0") -> 1 | F18: =IF(OR(C18="",E18="0"),"-",IF(BC18="","-",IF(OR(BC18="Muito satisfeito",BC18="Satisfeito"),"1","0"))) -> 1 | G18: =IF(BC18="","0","1") -> 1 | H18: SurveySubmission-37qnx7JIFoy8AIeDCh3Ib24HwNg | I18: 2026-01-05 19:01:52.641+00 | K18: Na web | L18: A1WX2OEIGSWUD | M18: Silvana Márlia Damasceno de Souza | N18: analista3@naweb.vc | O18: Dono de marca | P18: Muito satisfeito | Q18: Muito satisfeito | R18: Concordo plenamente | S18: Concordo plenamente | T18: Recomendações Estratégicas -- Muito importante Assistência com Resolução de Problemas -- Muito importante Estratégia com Promoções -- Muito importante Gerenciamento e suporte de catálogo -- Muito importante Suporte com gerenciamento de inventário -- Muito importante Suporte com estratégia para novos produtos -- Muito importante | U18: Maior auxilio com a criação e gestão das campanhas de ADS; Maior clareza a respeito de taxas cobradas de armazenagem; Criação de registro de marca dentro da plataforma. | V18: Stephanie Shinohara | W18: Muito satisfeito | X18: Meu consultor entende do meu negócio -- Concordo plenamente Meu consultor entende as necessidades do meu negócio com o programa SAS -- Concordo plenamente Meu consultor entende sobre a minha categoria de venda -- Concordo plenamente Meu consultor fornece recomendações estratégicas -- Concordo plenamente Meu consultor tem conhecimento dos recursos do Seller Central -- Concordo plenamente Meu consultor é responsivo via email -- Concordo plenamente Meu consultor se comunica por escrito de forma clara -- Concordo plenamente | Y18: Na verdade a plataforma precisa liberar mais bônus como a redução de comissão, taxas mais baratas de frete para poder conseguirmos continuar competindo com os outros marketplaces. | Z18: Yes | AA18: 5 | AB18: Não | AC18: Yes | AD18: 5 | AE18: O suporte por whatsapp seria muito melhor que o ticket, pois muitas vezes precisamos de ajuda para resolver um problema na hora, e abrimos muitos chamados para resolver diferentes problemas. | AF18: Yes | AG18: 3 | AH18: Reuniões quinzenais sobre os resultados e campanhas mais precisas de acordo com o que precisamos vender | AI18: ["Seleção (recomendação de produtos, oportunidades)","Promoções (ofertas, cupons, eventos)","Marca (registro, proteção, conteúdo A+, loja oficial)","Conversão (qualidade do catálogo, preços, listatem)","Advertising (anúncios patrocinados)","Ajuda na resolução de problemas operacionais","Logística (FBA, FBA-Onsite, DBA, logística própria)"] | AJ18: Relatório mais claro sobre os custos de armazenagem dos produtos no FBA Painel em tempo real de quais produtos e quantidades estão sendo vendidos no FBA Painel em tempo real sobre está nossa competitividade em relação a outros canais (com listagem de produtos) | AK18: Importante | AL18: Importante | AM18: Importante | AO18: Julia De Brito | AP18: Muito satisfeito | AQ18: Concordo parcialmente | AR18: Concordo plenamente | AS18: Concordo parcialmente | AT18: Concordo plenamente | AU18: Concordo plenamente | AV18: Concordo plenamente | AW18: Concordo plenamente | AY18: NÃ£o | BB18: Sim | BC18: Satisfeito | BE18: Sim | BF18: Satisfeito | BH18: 1 | BI18: 5 | BJ18: 7 | BK18: 4 | BL18: 6 | BM18: 2 | BN18: 3 | BP18: Email Address
A19: 128837707402 | B19: COLOR SPORTS. | C19: qmanuelv | D19: =IF(C19="","0","1") -> 1 | E19: =IFERROR(IF(VLOOKUP(A19,Base!AA:AA,1,0)>0,"1","0"),"0") -> 1 | F19: =IF(OR(C19="",E19="0"),"-",IF(BC19="","-",IF(OR(BC19="Muito satisfeito",BC19="Satisfeito"),"1","0"))) -> - | G19: =IF(BC19="","0","1") -> 0 | H19: SurveySubmission-37qpgWD8GrAJ33CZx753XizAMpI | I19: 2026-01-05 19:16:06.385+00 | K19: COLOR SPORTS | L19: AJTRHQYPRMPJ3 | M19: Vitor Gonçalves de Oliveira | N19: analistacomercialcs05@gmail.com | O19: Ambos | P19: Satisfeito | Q19: Muito satisfeito | R19: Concordo plenamente | S19: Concordo plenamente | T19: Recomendações Estratégicas -- Muito importante Assistência com Resolução de Problemas -- Muito importante Estratégia com Promoções -- Muito importante Gerenciamento e suporte de catálogo -- Muito importante Suporte com gerenciamento de inventário -- Muito importante Suporte com estratégia para novos produtos -- Muito importante | V19: Karime Cabral | W19: Muito satisfeito | X19: Meu consultor entende do meu negócio -- Concordo plenamente Meu consultor entende as necessidades do meu negócio com o programa SAS -- Concordo plenamente Meu consultor entende sobre a minha categoria de venda -- Concordo plenamente Meu consultor fornece recomendações estratégicas -- Concordo plenamente Meu consultor tem conhecimento dos recursos do Seller Central -- Concordo plenamente Meu consultor é responsivo via email -- Concordo plenamente Meu consultor se comunica por escrito de forma clara -- Concordo plenamente | Z19: Yes | AA19: 4 | AC19: Yes | AD19: 4 | AF19: No | AI19: ["Seleção (recomendação de produtos, oportunidades)","Conversão (qualidade do catálogo, preços, listatem)","Ajuda na resolução de problemas operacionais","Logística (FBA, FBA-Onsite, DBA, logística própria)","Advertising (anúncios patrocinados)","Promoções (ofertas, cupons, eventos)","Marca (registro, proteção, conteúdo A+, loja oficial)"] | AK19: Muito importante | AL19: Muito importante | AM19: Sem importÃ¢ncia | AO19: Rafaela Saad | AP19: Muito satisfeito | AQ19: Concordo plenamente | AR19: Concordo plenamente | AS19: Concordo plenamente | AT19: Concordo plenamente | AU19: Concordo plenamente | AV19: Concordo plenamente | AW19: Concordo plenamente | AY19: Sim | AZ19: Muito satisfeito | BB19: NÃ£o | BE19: NÃ£o | BH19: 7 | BI19: 3 | BJ19: 6 | BK19: 5 | BL19: 1 | BM19: 2 | BN19: 4 | BP19: Email Address
A20: 244366726002 | B20: COMPRAMAIS | C20: joaoclan | D20: =IF(C20="","0","1") -> 1 | E20: =IFERROR(IF(VLOOKUP(A20,Base!AA:AA,1,0)>0,"1","0"),"0") -> 1 | F20: =IF(OR(C20="",E20="0"),"-",IF(BC20="","-",IF(OR(BC20="Muito satisfeito",BC20="Satisfeito"),"1","0"))) -> 1 | G20: =IF(BC20="","0","1") -> 1 | H20: SurveySubmission-37qsfx93SEBP4gFKZAOH1O73Lhk | I20: 2026-01-05 19:40:42.307+00 | K20: Compramais | L20: A2N1DD131JVLCL | M20: Augusto Flávio Júlio Júnior | N20: augusto.junior@compramais.com.br | O20: Ambos | P20: Nem satisfeito, nem insatisfeito | Q20: Satisfeito | R20: Concordo parcialmente | S20: Nem concordo, nem discordo | T20: Recomendações Estratégicas -- Importante Assistência com Resolução de Problemas -- Muito importante Estratégia com Promoções -- Muito importante Gerenciamento e suporte de catálogo -- Importante Suporte com gerenciamento de inventário -- Sem importância Suporte com estratégia para novos produtos -- Serviço não é oferecido | U20: Melhor exposição de produtos (afiliados, redes sociais), retornar com oferta WOW, ajudar a alancar novos produtos e marcas. | V20: Sarah Meyer | W20: Satisfeito | X20: Meu consultor entende do meu negócio -- Nem concordo, nem discordo Meu consultor entende as necessidades do meu negócio com o programa SAS -- Concordo parcialmente Meu consultor entende sobre a minha categoria de venda -- Concordo plenamente Meu consultor fornece recomendações estratégicas -- Concordo plenamente Meu consultor tem conhecimento dos recursos do Seller Central -- Concordo plenamente Meu consultor é responsivo via email -- Concordo plenamente Meu consultor se comunica por escrito de forma clara -- Concordo plenamente | Y20: A Sarah está disposta a auxiliar no que estiver dentro do seu alcance, as ultimas negociações foram mais simples e entraram sem grandes problemas. Foram feitos bons acordos com redução de comissão que ajudaram a performar alguns anúncios. Talvez entender e se aprofundar um pouco mais sobre nossas marcas próprias ajudaria a alavancar nossos produtos na Amazon, | Z20: Yes | AA20: 4 | AB20: Prazo de entrega, qualidade do conteúdo A+ com menos aspecto de IA. | AC20: Yes | AD20: 4 | AE20: Usei poucas vezes, e foi resolvido | AF20: Yes | AG20: 3 | AH20: entender um pouco mais do nosso negócio, a fim de sugerir melhorias sobre nossa estratégia de alavancagem de produtos de marca própria. Algumas campanhas foram criadas com base em anos anteriores que hoje já não fazem mais sentido. | AI20: ["Conversão (qualidade do catálogo, preços, listatem)","Promoções (ofertas, cupons, eventos)","Ajuda na resolução de problemas operacionais","Marca (registro, proteção, conteúdo A+, loja oficial)","Advertising (anúncios patrocinados)","Logística (FBA, FBA-Onsite, DBA, logística própria)","Seleção (recomendação de produtos, oportunidades)"] | AK20: Muito importante | AL20: Muito importante | AM20: Muito importante | AO20: Rodrigo Portela | AP20: Muito satisfeito | AQ20: Concordo plenamente | AR20: Concordo plenamente | AS20: Concordo plenamente | AT20: Concordo plenamente | AU20: Concordo plenamente | AV20: Concordo plenamente | AW20: Concordo plenamente | AY20: Sim | AZ20: Muito satisfeito | BB20: Sim | BC20: Muito satisfeito | BE20: NÃ£o | BH20: 4 | BI20: 6 | BJ20: 5 | BK20: 7 | BL20: 1 | BM20: 2 | BN20: 3 | BP20: Email Address
A21: 685488901302 | B21: Vitrine Direta SP | C21: fpereluc | D21: =IF(C21="","0","1") -> 1 | E21: =IFERROR(IF(VLOOKUP(A21,Base!AA:AA,1,0)>0,"1","0"),"0") -> 1 | F21: =IF(OR(C21="",E21="0"),"-",IF(BC21="","-",IF(OR(BC21="Muito satisfeito",BC21="Satisfeito"),"1","0"))) -> 1 | G21: =IF(BC21="","0","1") -> 1 | H21: SurveySubmission-37qxPIKYCg7nByTHJw1xJDhnyAx | I21: 2026-01-05 20:19:36.843+00 | K21: Baby Stock Oficial | L21: A30M1H78WIEMGL | M21: Pedro Luiz Gelmini Cesar | N21: pedro.cesar@vitrinedireta.com.br | O21: Revendedor | P21: Muito satisfeito | Q21: Muito satisfeito | R21: Concordo plenamente | S21: Concordo plenamente | T21: Recomendações Estratégicas -- Muito importante Assistência com Resolução de Problemas -- Importante Estratégia com Promoções -- Muito importante Gerenciamento e suporte de catálogo -- Importante Suporte com gerenciamento de inventário -- Importante Suporte com estratégia para novos produtos -- Importante | V21: Thomas Thalenberg | W21: Muito satisfeito | X21: Meu consultor entende do meu negócio -- Concordo plenamente Meu consultor entende as necessidades do meu negócio com o programa SAS -- Concordo plenamente Meu consultor entende sobre a minha categoria de venda -- Concordo parcialmente Meu consultor fornece recomendações estratégicas -- Concordo plenamente Meu consultor tem conhecimento dos recursos do Seller Central -- Concordo plenamente Meu consultor é responsivo via email -- Concordo plenamente Meu consultor se comunica por escrito de forma clara -- Concordo plenamente | Z21: No | AC21: Yes | AD21: 4 | AF21: No | AI21: ["Promoções (ofertas, cupons, eventos)","Logística (FBA, FBA-Onsite, DBA, logística própria)","Conversão (qualidade do catálogo, preços, listatem)","Seleção (recomendação de produtos, oportunidades)","Advertising (anúncios patrocinados)","Ajuda na resolução de problemas operacionais","Marca (registro, proteção, conteúdo A+, loja oficial)"] | AK21: Importante | AL21: Importante | AM21: Importante | AN21: NÃ£o tenho sugestÃµes. o programa SAS me atende 100% | AO21: Paula Veneu | AP21: Muito satisfeito | AQ21: Discordo totalmente | AR21: Discordo totalmente | AS21: Discordo totalmente | AT21: Discordo totalmente | AU21: Discordo totalmente | AV21: Discordo totalmente | AW21: Discordo totalmente | AX21: NÃ£o tenho sugestÃ£o | AY21: Sim | AZ21: Muito satisfeito | BA21: NÃ£o tenho sugestÃ£o | BB21: Sim | BC21: Muito satisfeito | BD21: Sem sugestÃ£o | BE21: Sim | BF21: Muito satisfeito | BG21: Sem sugestÃ£o | BH21: 6 | BI21: 2 | BJ21: 5 | BK21: 3 | BL21: 1 | BM21: 7 | BN21: 4 | BO21: Todos os relatÃ³rios que preciso jÃ¡ sÃ£o enviados | BP21: Email Address
A22: 20068852602 | B22: DUFRIO | C22: fpereluc | D22: =IF(C22="","0","1") -> 1 | E22: =IFERROR(IF(VLOOKUP(A22,Base!AA:AA,1,0)>0,"1","0"),"0") -> 1 | F22: =IF(OR(C22="",E22="0"),"-",IF(BC22="","-",IF(OR(BC22="Muito satisfeito",BC22="Satisfeito"),"1","0"))) -> - | G22: =IF(BC22="","0","1") -> 0 | H22: SurveySubmission-37qxXbpkpQ6loEs0BvUThWtetnB | I22: 2026-01-05 20:20:42.172+00 | K22: Igor Dias | L22: A3KMLLJZ1EZHJM | M22: Henrique França | N22: henrique.franca@dufrio.com.br | O22: Ambos | P22: Muito satisfeito | Q22: Muito satisfeito | R22: Concordo plenamente | S22: Concordo plenamente | T22: Recomendações Estratégicas -- Muito importante Assistência com Resolução de Problemas -- Muito importante Estratégia com Promoções -- Muito importante Gerenciamento e suporte de catálogo -- Muito importante Suporte com gerenciamento de inventário -- Muito importante Suporte com estratégia para novos produtos -- Muito importante | V22: Igor Dias / Marcella Pazeto (Gerente) dando total apoio | W22: Muito satisfeito | X22: Meu consultor entende do meu negócio -- Concordo plenamente Meu consultor entende as necessidades do meu negócio com o programa SAS -- Concordo plenamente Meu consultor entende sobre a minha categoria de venda -- Concordo plenamente Meu consultor fornece recomendações estratégicas -- Concordo plenamente Meu consultor tem conhecimento dos recursos do Seller Central -- Concordo plenamente Meu consultor é responsivo via email -- Concordo plenamente Meu consultor se comunica por escrito de forma clara -- Concordo plenamente | Z22: Yes | AA22: 5 | AC22: Yes | AD22: 5 | AF22: Yes | AG22: 5 | AI22: ["Promoções (ofertas, cupons, eventos)","Seleção (recomendação de produtos, oportunidades)","Conversão (qualidade do catálogo, preços, listatem)","Marca (registro, proteção, conteúdo A+, loja oficial)","Advertising (anúncios patrocinados)","Ajuda na resolução de problemas operacionais","Logística (FBA, FBA-Onsite, DBA, logística própria)"] | AK22: Muito importante | AL22: Muito importante | AM22: Muito importante | AO22: Stephanie Shinohara | AP22: Muito satisfeito | AQ22: Discordo totalmente | AR22: Discordo totalmente | AS22: Discordo totalmente | AT22: Discordo totalmente | AU22: Discordo totalmente | AV22: Discordo totalmente | AW22: Discordo totalmente | AX22: Precisa de mais agilidade nas respostas, as vezes demora um pouco. | AY22: Sim | AZ22: Satisfeito | BB22: NÃ£o | BE22: Sim | BF22: Muito satisfeito | BG22: Melhorar na agilidade das respostas. | BH22: 3 | BI22: 4 | BJ22: 7 | BK22: 2 | BL22: 1 | BM22: 6 | BN22: 5 | BP22: Email Address
A23: 549848560202 | B23: FRIOPECAS | C23: qmanuelv | D23: =IF(C23="","0","1") -> 1 | E23: =IFERROR(IF(VLOOKUP(A23,Base!AA:AA,1,0)>0,"1","0"),"0") -> 1 | F23: =IF(OR(C23="",E23="0"),"-",IF(BC23="","-",IF(OR(BC23="Muito satisfeito",BC23="Satisfeito"),"1","0"))) -> - | G23: =IF(BC23="","0","1") -> 0 | H23: SurveySubmission-37qz2MPej6OIh4DYmqQIw8TX8FC | I23: 2026-01-05 20:33:00.195+00 | K23: Friopeças | L23: A12YOU7F0X4ZNC | M23: Bruna Cristina Figueiredo | N23: bruna.figueiredo@friopecas.com.br | O23: Ambos | P23: Muito satisfeito | Q23: Muito satisfeito | R23: Concordo plenamente | S23: Concordo plenamente | T23: Recomendações Estratégicas -- Muito importante Assistência com Resolução de Problemas -- Muito importante Estratégia com Promoções -- Muito importante Gerenciamento e suporte de catálogo -- Muito importante Suporte com gerenciamento de inventário -- Muito importante Suporte com estratégia para novos produtos -- Muito importante | V23: Luan Pereira | W23: Muito satisfeito | X23: Meu consultor entende do meu negócio -- Concordo plenamente Meu consultor entende as necessidades do meu negócio com o programa SAS -- Concordo plenamente Meu consultor entende sobre a minha categoria de venda -- Concordo plenamente Meu consultor fornece recomendações estratégicas -- Concordo plenamente Meu consultor tem conhecimento dos recursos do Seller Central -- Concordo plenamente Meu consultor é responsivo via email -- Concordo plenamente Meu consultor se comunica por escrito de forma clara -- Concordo plenamente | Z23: Yes | AA23: 5 | AC23: Yes | AD23: 5 | AF23: No | AI23: ["Conversão (qualidade do catálogo, preços, listatem)","Seleção (recomendação de produtos, oportunidades)","Ajuda na resolução de problemas operacionais","Promoções (ofertas, cupons, eventos)","Marca (registro, proteção, conteúdo A+, loja oficial)","Logística (FBA, FBA-Onsite, DBA, logística própria)","Advertising (anúncios patrocinados)"] | AJ23: Relatórios mais completos da GARANTIA DE AaZ, com motivos de abertura. | AK23: Muito importante | AL23: Muito importante | AM23: Muito importante | AO23: Luan Pereira e Ana Bon | AP23: Satisfeito | AQ23: Concordo parcialmente | AR23: Concordo parcialmente | AS23: Concordo parcialmente | AT23: Concordo parcialmente | AU23: Concordo parcialmente | AV23: Concordo parcialmente | AW23: Concordo parcialmente | AY23: NÃ£o | BB23: NÃ£o | BE23: NÃ£o | BH23: 1 | BI23: 3 | BJ23: 7 | BK23: 5 | BL23: 2 | BM23: 4 | BN23: 6 | BP23: Email Address
A24: 542325043802 | B24: Moblan Decor | C24: fpereluc | D24: =IF(C24="","0","1") -> 1 | E24: =IFERROR(IF(VLOOKUP(A24,Base!AA:AA,1,0)>0,"1","0"),"0") -> 1 | F24: =IF(OR(C24="",E24="0"),"-",IF(BC24="","-",IF(OR(BC24="Muito satisfeito",BC24="Satisfeito"),"1","0"))) -> - | G24: =IF(BC24="","0","1") -> 0 | H24: SurveySubmission-37qzf28Oznz2qHxq91GIfHIS5my | I24: 2026-01-05 20:38:08.6+00 | K24: MOBLAN DECOR | L24: A22IPO4UUU0YFK | M24: MATHEUS HENRIQUE RODRIGUES | N24: matheus@moblandecor.com.br | O24: Dono de marca | P24: Muito satisfeito | Q24: Muito satisfeito | R24: Concordo plenamente | S24: Concordo plenamente | T24: Recomendações Estratégicas -- Muito importante Assistência com Resolução de Problemas -- Muito importante Estratégia com Promoções -- Muito importante Gerenciamento e suporte de catálogo -- Importante Suporte com gerenciamento de inventário -- Importante Suporte com estratégia para novos produtos -- Sem importância | U24: Não tem nada a melhorar | V24: Igor Dias | W24: Satisfeito | X24: Meu consultor entende do meu negócio -- Concordo plenamente Meu consultor entende as necessidades do meu negócio com o programa SAS -- Concordo plenamente Meu consultor entende sobre a minha categoria de venda -- Concordo plenamente Meu consultor fornece recomendações estratégicas -- Concordo plenamente Meu consultor tem conhecimento dos recursos do Seller Central -- Concordo plenamente Meu consultor é responsivo via email -- Concordo plenamente Meu consultor se comunica por escrito de forma clara -- Concordo plenamente | Y24: Nada a melhorar, Igor é nota 10 | Z24: Yes | AA24: 5 | AB24: Não | AC24: Yes | AD24: 5 | AE24: Não | AF24: Yes | AG24: 5 | AH24: Não, Nayara é nota 10 também!!! | AI24: ["Promoções (ofertas, cupons, eventos)","Advertising (anúncios patrocinados)","Marca (registro, proteção, conteúdo A+, loja oficial)","Ajuda na resolução de problemas operacionais","Conversão (qualidade do catálogo, preços, listatem)","Logística (FBA, FBA-Onsite, DBA, logística própria)","Seleção (recomendação de produtos, oportunidades)"] | AJ24: Sem sugestão | AK24: Muito importante | AL24: Muito importante | AM24: Muito importante | AO24: Rafaela Saad | AP24: Muito satisfeito | AQ24: Concordo plenamente | AR24: Concordo plenamente | AS24: Concordo plenamente | AT24: Concordo plenamente | AU24: Concordo plenamente | AV24: Concordo plenamente | AW24: Concordo plenamente | AY24: Sim | AZ24: Muito satisfeito | BB24: NÃ£o | BE24: NÃ£o | BH24: 4 | BI24: 6 | BJ24: 7 | BK24: 2 | BL24: 5 | BM24: 1 | BN24: 3 | BP24: Email Address
A25: 56744200802 | B25: Suggar Eletrodomesticos | D25: =IF(C25="","0","1") -> 0 | E25: =IFERROR(IF(VLOOKUP(A25,Base!AA:AA,1,0)>0,"1","0"),"0") -> 0 | F25: =IF(OR(C25="",E25="0"),"-",IF(BC25="","-",IF(OR(BC25="Muito satisfeito",BC25="Satisfeito"),"1","0"))) -> - | G25: =IF(BC25="","0","1") -> 0 | H25: SurveySubmission-37smjgVGPD3f2VmxzF28jIFQCgi | I25: 2026-01-06 11:51:29.38+00 | K25: suggar eletrodomésticos | L25: AQ7D2VO18Q2VV | M25: Daniel Lacerda | N25: Daniel.lacerda@suggar.com.br | O25: Dono de marca | P25: Muito satisfeito | Q25: Muito satisfeito | R25: Concordo parcialmente | S25: Concordo plenamente | T25: Recomendações Estratégicas -- Muito importante Assistência com Resolução de Problemas -- Muito importante Estratégia com Promoções -- Muito importante Gerenciamento e suporte de catálogo -- Muito importante Suporte com gerenciamento de inventário -- Muito importante Suporte com estratégia para novos produtos -- Sem importância | V25: Luan Perreira | W25: Muito satisfeito | X25: Meu consultor entende do meu negócio -- Concordo plenamente Meu consultor entende as necessidades do meu negócio com o programa SAS -- Concordo plenamente Meu consultor entende sobre a minha categoria de venda -- Concordo plenamente Meu consultor fornece recomendações estratégicas -- Concordo plenamente Meu consultor tem conhecimento dos recursos do Seller Central -- Concordo plenamente Meu consultor é responsivo via email -- Concordo plenamente Meu consultor se comunica por escrito de forma clara -- Concordo plenamente | Z25: Yes | AA25: 4 | AC25: No | AF25: No | AI25: ["Promoções (ofertas, cupons, eventos)","Advertising (anúncios patrocinados)","Ajuda na resolução de problemas operacionais","Logística (FBA, FBA-Onsite, DBA, logística própria)","Conversão (qualidade do catálogo, preços, listatem)","Marca (registro, proteção, conteúdo A+, loja oficial)","Seleção (recomendação de produtos, oportunidades)"] | AJ25: Relatório de pedidos com redução de comissão | AK25: Importante | AL25: Importante | AM25: Importante | AO25: Bianca Ramalho | AP25: Satisfeito | AQ25: Nem concordo, nem discordo | AR25: Nem concordo, nem discordo | AS25: Nem concordo, nem discordo | AT25: Nem concordo, nem discordo | AU25: Concordo parcialmente | AV25: Nem concordo, nem discordo | AW25: Concordo parcialmente | AY25: NÃ£o | BB25: NÃ£o | BE25: Sim | BF25: Satisfeito | BH25: 6 | BI25: 5 | BJ25: 7 | BK25: 4 | BL25: 2 | BM25: 3 | BN25: 1 | BO25: Funil de ConversÃ£o dos produtos (visualizaÃ§Ã£o, carrinho, conversÃ£o) | BP25: Email Address
A26: 1045128782102 | B26: CAFFEINE ARMY I SUPERCOFFEE I EXPRESS | C26: gomrodrd | D26: =IF(C26="","0","1") -> 1 | E26: =IFERROR(IF(VLOOKUP(A26,Base!AA:AA,1,0)>0,"1","0"),"0") -> 1 | F26: =IF(OR(C26="",E26="0"),"-",IF(BC26="","-",IF(OR(BC26="Muito satisfeito",BC26="Satisfeito"),"1","0"))) -> 1 | G26: =IF(BC26="","0","1") -> 1 | H26: SurveySubmission-37soghbEbrYGiAmQ6WdQOuf0475 | I26: 2026-01-06 12:07:32.698+00 | K26: CAFFEINE ARMY | SUPERCOFFEE | EXPRESS | L26: A3TKQBIQVNI2XO | M26: Gabriel Rodrigues Armentano | N26: gabriel.armentano@caffeinearmy.com.br | O26: Dono de marca | P26: Muito satisfeito | Q26: Muito satisfeito | R26: Concordo plenamente | S26: Concordo plenamente | T26: Recomendações Estratégicas -- Sem importância Assistência com Resolução de Problemas -- Muito importante Estratégia com Promoções -- Muito importante Gerenciamento e suporte de catálogo -- Muito importante Suporte com gerenciamento de inventário -- Sem importância Suporte com estratégia para novos produtos -- Muito importante | V26: Rodrigo Portela | W26: Muito satisfeito | X26: Meu consultor entende do meu negócio -- Concordo plenamente Meu consultor entende as necessidades do meu negócio com o programa SAS -- Concordo plenamente Meu consultor entende sobre a minha categoria de venda -- Concordo plenamente Meu consultor fornece recomendações estratégicas -- Concordo plenamente Meu consultor tem conhecimento dos recursos do Seller Central -- Concordo plenamente Meu consultor é responsivo via email -- Concordo plenamente Meu consultor se comunica por escrito de forma clara -- Concordo plenamente | Z26: Yes | AA26: 5 | AC26: Yes | AD26: 5 | AF26: No | AI26: ["Logística (FBA, FBA-Onsite, DBA, logística própria)","Ajuda na resolução de problemas operacionais","Promoções (ofertas, cupons, eventos)","Marca (registro, proteção, conteúdo A+, loja oficial)","Conversão (qualidade do catálogo, preços, listatem)","Advertising (anúncios patrocinados)","Seleção (recomendação de produtos, oportunidades)"] | AK26: Muito importante | AL26: Muito importante | AM26: Sem importÃ¢ncia | AN26: OlÃ¡, Suporte! O pedido consta como "nÃ£o pode ser entregue", mas nÃ£o temos nenhuma informaÃ§Ã£o sobre o motivo. Como vendedores, ficamos sem detalhes que nos ajudem a entender o que aconteceu. Poderiam, por favor, rever essa questÃ£o | AO26: Joao Claudino N. | AP26: Satisfeito | AQ26: Concordo plenamente | AR26: Concordo plenamente | AS26: Concordo parcialmente | AT26: Concordo plenamente | AU26: Concordo plenamente | AV26: Concordo plenamente | AW26: Concordo plenamente | AY26: Sim | AZ26: Muito satisfeito | BA26: Cliente informou que nÃ£o conseguiu receber o pedido, e no sistema de rastreio consta a mensagem: "Pedido nÃ£o pode ser entregue". Poderiam fornecer mais informaÃ§Ãµes | BB26: Sim | BC26: Satisfeito | BE26: Sim | BF26: Satisfeito | BH26: 5 | BI26: 6 | BJ26: 7 | BK26: 4 | BL26: 1 | BM26: 2 | BN26: 3 | BP26: Email Address
A27: 368561207102 | B27: Farmácia Indiana | C27: gomrodrd | D27: =IF(C27="","0","1") -> 1 | E27: =IFERROR(IF(VLOOKUP(A27,Base!AA:AA,1,0)>0,"1","0"),"0") -> 0 | F27: =IF(OR(C27="",E27="0"),"-",IF(BC27="","-",IF(OR(BC27="Muito satisfeito",BC27="Satisfeito"),"1","0"))) -> - | G27: =IF(BC27="","0","1") -> 1 | H27: SurveySubmission-37t21fkKIxCe9AEJzNj7OCIgadL | I27: 2026-01-06 13:57:12.521+00 | K27: Farmácia Indiana | L27: amzn1.pa.o.A1SZ2P0OJKY6Q0 | M27: Marcela Tribst | N27: marcela.t.silva@farmaciaindiana.com.br | O27: Revendedor | P27: Satisfeito | Q27: Muito satisfeito | R27: Concordo plenamente | S27: Concordo parcialmente | T27: Recomendações Estratégicas -- Muito importante Assistência com Resolução de Problemas -- Muito importante Estratégia com Promoções -- Muito importante Gerenciamento e suporte de catálogo -- Muito importante Suporte com gerenciamento de inventário -- Muito importante Suporte com estratégia para novos produtos -- Muito importante | U27: Sim, gostria de uma pessoa no suporte de ADS pra auxiliar a gestão do investimento. Um suporte mais rápido na questão de catalogo seja menos moroso esse processo de subida de itens novos. Pois estamos tentando abrir uma nova loja DBA mais de 3 meses e te agora por conta de burocracia não conseguimos . | V27: Naiane Rangel | W27: Muito satisfeito | X27: Meu consultor entende do meu negócio -- Concordo plenamente Meu consultor entende as necessidades do meu negócio com o programa SAS -- Concordo plenamente Meu consultor entende sobre a minha categoria de venda -- Concordo plenamente Meu consultor fornece recomendações estratégicas -- Concordo plenamente Meu consultor tem conhecimento dos recursos do Seller Central -- Concordo plenamente Meu consultor é responsivo via email -- Concordo plenamente Meu consultor se comunica por escrito de forma clara -- Concordo plenamente | Y27: Infelizmente ela depende de outro setores pra acelerar nossas necessidades | Z27: Yes | AA27: 3 | AC27: Yes | AD27: 3 | AF27: Yes | AG27: 4 | AH27: Ate dezembro nós tínhamos uma excelente, porem foi nos tirado esse apoio tão importante. Nome dela é LUIZA | AI27: ["Promoções (ofertas, cupons, eventos)","Seleção (recomendação de produtos, oportunidades)","Conversão (qualidade do catálogo, preços, listatem)","Advertising (anúncios patrocinados)","Marca (registro, proteção, conteúdo A+, loja oficial)","Ajuda na resolução de problemas operacionais"] | AK27: Muito importante | AL27: Muito importante | AM27: Muito importante | AN27: NÃ£o tenho | AO27: Tatiane De Assis | AP27: Muito satisfeito | AQ27: Discordo totalmente | AR27: Discordo totalmente | AS27: Discordo totalmente | AT27: Discordo totalmente | AU27: Discordo totalmente | AV27: Discordo totalmente | AW27: Discordo totalmente | AX27: NÃ£o tenho | AY27: Sim | AZ27: Muito satisfeito | BA27: NÃ£o tenho | BB27: Sim | BC27: Muito satisfeito | BD27: NÃ£o tenho | BE27: Sim | BF27: Muito satisfeito | BG27: NÃ£o tenho | BH27: 5 | BI27: 6 | BJ27: 7 | BK27: 1 | BL27: 3 | BM27: 2 | BN27: 4 | BO27: NÃ£o tenho | BP27: Email Address
A28: 188325185102 | B28: Dibs Modas | D28: =IF(C28="","0","1") -> 0 | E28: =IFERROR(IF(VLOOKUP(A28,Base!AA:AA,1,0)>0,"1","0"),"0") -> 0 | F28: =IF(OR(C28="",E28="0"),"-",IF(BC28="","-",IF(OR(BC28="Muito satisfeito",BC28="Satisfeito"),"1","0"))) -> - | G28: =IF(BC28="","0","1") -> 0 | H28: SurveySubmission-37t9ny2etcieS3AzuifdEuyi1fA | I28: 2026-01-06 15:01:10.081+00 | K28: Dibs Modas | L28: A15CBXW66NILHA | M28: Willian Hata | N28: marketplace@dibs.com.br | O28: Revendedor | P28: Muito insatisfeito | Q28: Muito insatisfeito | R28: Concordo plenamente | S28: Concordo plenamente | T28: Recomendações Estratégicas -- Muito importante Assistência com Resolução de Problemas -- Muito importante Estratégia com Promoções -- Muito importante Gerenciamento e suporte de catálogo -- Muito importante Suporte com gerenciamento de inventário -- Muito importante Suporte com estratégia para novos produtos -- Muito importante | V28: Karime Cabral | W28: Muito satisfeito | X28: Meu consultor entende do meu negócio -- Concordo plenamente Meu consultor entende as necessidades do meu negócio com o programa SAS -- Concordo plenamente Meu consultor entende sobre a minha categoria de venda -- Concordo plenamente Meu consultor fornece recomendações estratégicas -- Concordo plenamente Meu consultor tem conhecimento dos recursos do Seller Central -- Concordo plenamente Meu consultor é responsivo via email -- Concordo plenamente Meu consultor se comunica por escrito de forma clara -- Concordo plenamente | Z28: Yes | AA28: 5 | AC28: No | AF28: Yes | AG28: 1 | AH28: Recebemos o benefício de ter uma consultoria externa, com a empresa Azazuu. Começaram fazendo um bom trabalho mas no momento que comentamos que precisávamos investir um pouco mais para prorrogar o nosso benefício de isenções do FBA, a empresa torrou um valor desnecessário, que acabou prejudicando nossa rentabilidade no mês de Novembro/25. | AI28: ["Ajuda na resolução de problemas operacionais","Conversão (qualidade do catálogo, preços, listatem)","Seleção (recomendação de produtos, oportunidades)","Logística (FBA, FBA-Onsite, DBA, logística própria)","Promoções (ofertas, cupons, eventos)","Advertising (anúncios patrocinados)","Marca (registro, proteção, conteúdo A+, loja oficial)"] | AK28: Muito importante | AL28: Muito importante | AM28: Muito importante | AN28: Trazer mais insights para a conta e ajudar mais na resoluÃ§Ã£o de problemas. Hoje, quando acontece alguma coisa, sÃ³ nos pedem pra abrir um ticket e resolver pelo ticket. Ou seja, nÃ£o ajudam em nada na resoluÃ§Ã£o. | AO28: Stephanie Shinohara. | AP28: Muito insatisfeito | AQ28: Nem concordo, nem discordo | AR28: Discordo totalmente | AS28: Nem concordo, nem discordo | AT28: Discordo totalmente | AU28: Concordo parcialmente | AV28: Discordo totalmente | AW28: Nem concordo, nem discordo | AX28: Trazer mais insights estratÃ©gicos, e nÃ£o apenas planilhas com sugestÃ£o de preÃ§os onde na grande maioria das vezes nÃ£o conseguimos seguir. AlÃ©m disso, acho que precisa entender da necessidade de se ter um KA auxiliando. | AY28: NÃ£o | BB28: NÃ£o | BE28: Sim | BF28: Muito insatisfeito | BG28: Ser mais presente e participativo na tomada de decisÃµes. Hoje tenho poucas "provocaÃ§Ãµes" em relaÃ§Ã£o a aÃ§Ãµes e pouquÃ­ssimo insight sobre a conta e o negÃ³cio. | BH28: 1 | BI28: 2 | BJ28: 6 | BK28: 3 | BL28: 5 | BM28: 4 | BN28: 7 | BO28: RelatÃ³rios do que vem dando certo em relaÃ§Ã£o Ã s campanhas e atÃ© mesmo do que nÃ£o deu certo e pode melhorar. | BP28: Email Address
A29: 779493596402 | B29: KarolBeauty | D29: =IF(C29="","0","1") -> 0 | E29: =IFERROR(IF(VLOOKUP(A29,Base!AA:AA,1,0)>0,"1","0"),"0") -> 1 | F29: =IF(OR(C29="",E29="0"),"-",IF(BC29="","-",IF(OR(BC29="Muito satisfeito",BC29="Satisfeito"),"1","0"))) -> - | G29: =IF(BC29="","0","1") -> 0 | H29: SurveySubmission-37tSIpud5UNkaTsMLPhswFd4r4w | I29: 2026-01-06 17:33:16.701+00 | K29: KarolBeauty | L29: A1QR7ZH1CBB1LI | M29: LUCAS CAMARDELLA | N29: lucascamardella@gmail.com | O29: Revendedor | P29: Muito satisfeito | Q29: Muito satisfeito | R29: Concordo plenamente | S29: Concordo parcialmente | T29: Recomendações Estratégicas -- Sem importância Assistência com Resolução de Problemas -- Muito importante Estratégia com Promoções -- Muito importante Gerenciamento e suporte de catálogo -- Sem importância Suporte com gerenciamento de inventário -- Sem importância Suporte com estratégia para novos produtos -- Importante | U29: Maior autonomia ao nosso gerente de contas para resolver problemas internos. | V29: Bianca Ramalho | W29: Muito satisfeito | X29: Meu consultor entende do meu negócio -- Concordo plenamente Meu consultor entende as necessidades do meu negócio com o programa SAS -- Concordo plenamente Meu consultor entende sobre a minha categoria de venda -- Concordo plenamente Meu consultor fornece recomendações estratégicas -- Concordo plenamente Meu consultor tem conhecimento dos recursos do Seller Central -- Concordo plenamente Meu consultor é responsivo via email -- Concordo plenamente Meu consultor se comunica por escrito de forma clara -- Concordo plenamente | Y29: Melhorar a autonomia do consultor para suporte com a conta. | Z29: No | AC29: No | AF29: No | AI29: ["Promoções (ofertas, cupons, eventos)","Ajuda na resolução de problemas operacionais","Logística (FBA, FBA-Onsite, DBA, logística própria)","Seleção (recomendação de produtos, oportunidades)","Conversão (qualidade do catálogo, preços, listatem)","Advertising (anúncios patrocinados)","Marca (registro, proteção, conteúdo A+, loja oficial)"] | AJ29: Oportunidades, | AK29: Importante | AL29: Importante | AM29: ServiÃ§o nÃ£o Ã© oferecido | AO29: Manoela | AP29: Muito satisfeito | AQ29: Concordo parcialmente | AR29: Concordo parcialmente | AS29: Concordo parcialmente | AT29: Concordo parcialmente | AU29: Concordo parcialmente | AV29: Concordo parcialmente | AW29: Concordo parcialmente | AY29: NÃ£o | BB29: NÃ£o | BE29: NÃ£o | BH29: 4 | BI29: 6 | BJ29: 2 | BK29: 3 | BL29: 1 | BM29: 7 | BN29: 5 | BP29: Email Address
A30: 20025747402 | B30: MOBLY | C30: qmanuelv | D30: =IF(C30="","0","1") -> 1 | E30: =IFERROR(IF(VLOOKUP(A30,Base!AA:AA,1,0)>0,"1","0"),"0") -> 1 | F30: =IF(OR(C30="",E30="0"),"-",IF(BC30="","-",IF(OR(BC30="Muito satisfeito",BC30="Satisfeito"),"1","0"))) -> - | G30: =IF(BC30="","0","1") -> 0 | H30: SurveySubmission-37tUEc8JKHipSvZ43i82DUQrUuS | I30: 2026-01-06 17:49:10.508+00 | K30: Mobly | L30: AMS8HP2Q7DKSM | M30: Tatiana Nascimento Portugal | N30: tatiana.portugal@mobly.tech | O30: Ambos | P30: Satisfeito | Q30: Satisfeito | R30: Concordo plenamente | S30: Concordo plenamente | T30: Recomendações Estratégicas -- Muito importante Assistência com Resolução de Problemas -- Muito importante Estratégia com Promoções -- Muito importante Gerenciamento e suporte de catálogo -- Muito importante Suporte com gerenciamento de inventário -- Muito importante Suporte com estratégia para novos produtos -- Muito importante | U30: De modo geral, o suporte do programa SAS tem sido bastante útil e prestativo, especialmente no acompanhamento e na resolução de demandas. Como ponto de melhoria, alguns processos da Amazon ainda são bastante burocráticos, o que pode impactar a agilidade das ações. Entendo que isso esteja mais relacionado às diretrizes internas da empresa do que diretamente ao programa SAS, mas qualquer iniciativa que ajude a simplificar fluxos ou tornar os processos mais ágeis certamente agregaria ainda mais valor ao serviço. | V30: Matheus Balbino | W30: Satisfeito | X30: Meu consultor entende do meu negócio -- Concordo plenamente Meu consultor entende as necessidades do meu negócio com o programa SAS -- Concordo plenamente Meu consultor entende sobre a minha categoria de venda -- Concordo plenamente Meu consultor fornece recomendações estratégicas -- Concordo parcialmente Meu consultor tem conhecimento dos recursos do Seller Central -- Concordo parcialmente Meu consultor é responsivo via email -- Concordo plenamente Meu consultor se comunica por escrito de forma clara -- Concordo plenamente | Y30: De modo geral, estou satisfeito com o atendimento do consultor, especialmente pelo contato mais próximo e pela maior agilidade no suporte, algo que infelizmente não tínhamos com o consultor anterior. Quando ele assumiu nossa conta, estava em início de jornada na empresa, então em alguns momentos não tinha respostas imediatas, mas sempre foi prestativo em verificar as informações e retornar com um posicionamento claro. No geral, o atendimento tem sido positivo e em constante evolução. | Z30: Yes | AA30: 4 | AB30: Ainda não utilizei todos os serviços disponíveis do programa, tendo maior experiência apenas com a parte de cadastro de novos produtos, relacionada ao inventário. O principal ponto de melhoria que observo, e que já mencionei anteriormente, está relacionado a alguns processos bastante burocráticos, que não encontro em outros canais onde atuo. Um exemplo é a necessidade de solicitar determinados documentos para cadastrar produtos de marcas novas que ainda não fazem parte do meu catálogo, o que acaba tornando o processo mais lento e oneroso. Entendo, no entanto, que isso esteja mais ligado às diretrizes internas da própria Amazon e fuja da alçada direta dos analistas. Além disso, em alguns atendimentos, os retornos dos analistas não foram totalmente claros, o que acaba dificultando o entendimento e exige novos questionamentos até que a explicação fique totalmente compreensível. | AC30: Yes | AD30: 4 | AE30: De modo geral, estou satisfeita com o suporte na resolução de problemas e, até o momento, minhas dúvidas têm sido sanadas. O único ponto que ainda permanece pendente, e que tem impactado um pouco o trabalho do meu time de SAC, é a questão relacionada a usuários, em que um dos usuários cadastrados apresenta erro e ainda não houve uma resolução efetiva. | AF30: No | AI30: ["Seleção (recomendação de produtos, oportunidades)","Advertising (anúncios patrocinados)","Marca (registro, proteção, conteúdo A+, loja oficial)","Conversão (qualidade do catálogo, preços, listatem)","Promoções (ofertas, cupons, eventos)","Ajuda na resolução de problemas operacionais","Logística (FBA, FBA-Onsite, DBA, logística própria)"] | AJ30: Relatório de produtos com erro de preço | AK30: Importante | AL30: Importante | AM30: Muito importante | AN30: Como evoluÃ§Ã£o, sugiro realizar um trabalho focado em oportunidades de produtos, nos dando uma visÃ£o de produtos mais buscados e vendidos na Amazon. Com essa informaÃ§Ã£o conseguiremos analisar nosso posicionamento na plataforma e buscar melhores oportunidades comerciais e oferats. | AO30: Naiane | AP30: Muito satisfeito | AQ30: Concordo plenamente | AR30: Concordo plenamente | AS30: Concordo plenamente | AT30: Concordo plenamente | AU30: Concordo plenamente | AV30: Concordo plenamente | AW30: Concordo plenamente | AX30: Mais horas conosco. | AY30: Sim | AZ30: Satisfeito | BB30: NÃ£o | BE30: NÃ£o | BH30: 1 | BI30: 4 | BJ30: 7 | BK30: 2 | BL30: 3 | BM30: 5 | BN30: 6 | BP30: Email Address
A31: 24558652202 | B31: FRIGELAR | C31: qmanuelv | D31: =IF(C31="","0","1") -> 1 | E31: =IFERROR(IF(VLOOKUP(A31,Base!AA:AA,1,0)>0,"1","0"),"0") -> 1 | F31: =IF(OR(C31="",E31="0"),"-",IF(BC31="","-",IF(OR(BC31="Muito satisfeito",BC31="Satisfeito"),"1","0"))) -> - | G31: =IF(BC31="","0","1") -> 0 | H31: SurveySubmission-37tgcG20HVRrWOd7UDlGGppHNt5 | I31: 2026-01-06 19:30:58.468+00 | K31: Frigelar Ltda | L31: 727234475902 | M31: ingrid de paulo wroblewski | N31: ingridwroblewski@frigelar.com.br | O31: Ambos | P31: Muito satisfeito | Q31: Muito satisfeito | R31: Concordo plenamente | S31: Concordo parcialmente | T31: Recomendações Estratégicas -- Muito importante Assistência com Resolução de Problemas -- Muito importante Estratégia com Promoções -- Muito importante Gerenciamento e suporte de catálogo -- Muito importante Suporte com gerenciamento de inventário -- Muito importante Suporte com estratégia para novos produtos -- Muito importante | V31: Luan Pereira | W31: Muito satisfeito | X31: Meu consultor entende do meu negócio -- Concordo plenamente Meu consultor entende as necessidades do meu negócio com o programa SAS -- Concordo plenamente Meu consultor entende sobre a minha categoria de venda -- Concordo plenamente Meu consultor fornece recomendações estratégicas -- Concordo plenamente Meu consultor tem conhecimento dos recursos do Seller Central -- Concordo plenamente Meu consultor é responsivo via email -- Concordo plenamente Meu consultor se comunica por escrito de forma clara -- Concordo plenamente | Z31: Yes | AA31: 5 | AB31: Olá! Seguir com negociações feitas diretamente com o gerente de contas. | AC31: Yes | AD31: 4 | AE31: Que houvesse uma forma dos chamados premium ficarem separados. Ou seja, cada caso ter um número e registro próprio. Pois na hora de buscar o histórico e acompanhar os retornos fica complicado achar na conversa. | AF31: Yes | AG31: 3 | AH31: Retornar aos contatos semanais ou quinzenais para analisarmos dados juntos e melhorarmos os números. Estamos no terceiro consultor de Ads, seria legal podermos manter o mesmo consultor durante longo período. Tivemos o João, depois a Carol e agora estamos com o Murilo. | AI31: ["Promoções (ofertas, cupons, eventos)","Conversão (qualidade do catálogo, preços, listatem)","Seleção (recomendação de produtos, oportunidades)","Ajuda na resolução de problemas operacionais","Advertising (anúncios patrocinados)","Logística (FBA, FBA-Onsite, DBA, logística própria)","Marca (registro, proteção, conteúdo A+, loja oficial)"] | AK31: Importante | AL31: Importante | AM31: Importante | AN31: Treinamento em ADS. Treinamento para que o seller consiga inserir as promoÃ§Ãµes, sem ter que ficar esperando pelo consultor nem para ativar e nem para possÃ­veis correÃ§Ãµes. | AO31: Bianca | AP31: Nem satisfeito, nem insatisfeito | AQ31: Nem concordo, nem discordo | AR31: Nem concordo, nem discordo | AS31: Nem concordo, nem discordo | AT31: Nem concordo, nem discordo | AU31: Nem concordo, nem discordo | AV31: Nem concordo, nem discordo | AW31: Nem concordo, nem discordo | AY31: NÃ£o | BB31: NÃ£o | BE31: NÃ£o | BH31: 4 | BI31: 1 | BJ31: 7 | BK31: 5 | BL31: 2 | BM31: 3 | BN31: 6 | BP31: Email Address
A32: 24674493302 | B32: Brastemp Oficial | C32: joaoclan | D32: =IF(C32="","0","1") -> 1 | E32: =IFERROR(IF(VLOOKUP(A32,Base!AA:AA,1,0)>0,"1","0"),"0") -> 1 | F32: =IF(OR(C32="",E32="0"),"-",IF(BC32="","-",IF(OR(BC32="Muito satisfeito",BC32="Satisfeito"),"1","0"))) -> 1 | G32: =IF(BC32="","0","1") -> 1 | H32: SurveySubmission-37tj7BCmPXqR7XwHAnVTB0bHrJQ | I32: 2026-01-06 19:51:31.699+00 | K32: Brastemp | L32: A2O5FLS3OEYELQ | M32: Luiza Maria Ribeiro Ferreira | N32: luiza_m_ferreira@whirlpool.com | O32: Dono de marca | P32: Satisfeito | Q32: Satisfeito | R32: Concordo plenamente | S32: Concordo plenamente | T32: Recomendações Estratégicas -- Muito importante Assistência com Resolução de Problemas -- Muito importante Estratégia com Promoções -- Muito importante Gerenciamento e suporte de catálogo -- Muito importante Suporte com gerenciamento de inventário -- Muito importante Suporte com estratégia para novos produtos -- Muito importante | V32: Stephanie Shinohara | W32: Muito satisfeito | X32: Meu consultor entende do meu negócio -- Concordo plenamente Meu consultor entende as necessidades do meu negócio com o programa SAS -- Concordo parcialmente Meu consultor entende sobre a minha categoria de venda -- Concordo plenamente Meu consultor fornece recomendações estratégicas -- Concordo plenamente Meu consultor tem conhecimento dos recursos do Seller Central -- Concordo plenamente Meu consultor é responsivo via email -- Concordo parcialmente Meu consultor se comunica por escrito de forma clara -- Concordo plenamente | Y32: Estruturação clara de um plano de negócio para crescimento do canal no ano de 2026. | Z32: Yes | AA32: 5 | AC32: No | AF32: No | AI32: ["Promoções (ofertas, cupons, eventos)","Conversão (qualidade do catálogo, preços, listatem)","Ajuda na resolução de problemas operacionais","Advertising (anúncios patrocinados)","Logística (FBA, FBA-Onsite, DBA, logística própria)","Seleção (recomendação de produtos, oportunidades)","Marca (registro, proteção, conteúdo A+, loja oficial)"] | AK32: Muito importante | AL32: Muito importante | AM32: Muito importante | AO32: Naiane Rangel | AP32: Muito satisfeito | AQ32: Concordo plenamente | AR32: Concordo plenamente | AS32: Concordo plenamente | AT32: Concordo plenamente | AU32: Concordo plenamente | AV32: Concordo plenamente | AW32: Concordo plenamente | AY32: Sim | AZ32: Muito satisfeito | BB32: Sim | BC32: Muito satisfeito | BE32: NÃ£o | BH32: 1 | BI32: 2 | BJ32: 3 | BK32: 4 | BL32: 5 | BM32: 6 | BN32: 7 | BP32: Email Address
A33: 56875076002 | B33: CROCS BRASIL | D33: =IF(C33="","0","1") -> 0 | E33: =IFERROR(IF(VLOOKUP(A33,Base!AA:AA,1,0)>0,"1","0"),"0") -> 0 | F33: =IF(OR(C33="",E33="0"),"-",IF(BC33="","-",IF(OR(BC33="Muito satisfeito",BC33="Satisfeito"),"1","0"))) -> - | G33: =IF(BC33="","0","1") -> 1 | H33: SurveySubmission-37tkOnPrFt37lgJX0UXS4meaSxh | I33: 2026-01-06 20:02:04.887+00 | K33: CROCS BRASIL | L33: 56875076002 | M33: Érika Teixeira | N33: eteixeira@crocs.com | O33: Dono de marca | P33: Nem satisfeito, nem insatisfeito | Q33: Satisfeito | R33: Concordo plenamente | S33: Concordo parcialmente | T33: Recomendações Estratégicas -- Importante Assistência com Resolução de Problemas -- Muito importante Estratégia com Promoções -- Importante Gerenciamento e suporte de catálogo -- Muito importante Suporte com gerenciamento de inventário -- Muito importante Suporte com estratégia para novos produtos -- Importante | U33: O programa faz o que pode para nos ajudar, mas nosso maior problema é com catalogação. Vivemos fazendo várias vezes o mesmo trabalho e nunca acerta. É muito frustante como donos da marca, não conseguirmos ajustar o catálogo sem que um chamado seja aberto. E isso tem impactado MUITO nossas vendas, como é possível perceber na queda que tivemos no segunda semestre de 2025. | V33: Karime | W33: Satisfeito | X33: Meu consultor entende do meu negócio -- Concordo plenamente Meu consultor entende as necessidades do meu negócio com o programa SAS -- Concordo plenamente Meu consultor entende sobre a minha categoria de venda -- Concordo plenamente Meu consultor fornece recomendações estratégicas -- Concordo plenamente Meu consultor tem conhecimento dos recursos do Seller Central -- Concordo plenamente Meu consultor é responsivo via email -- Concordo plenamente Meu consultor se comunica por escrito de forma clara -- Concordo plenamente | Y33: Como respondi anteriormente, sabemos que o consultor faz o que pode para nos ajudar, mas o problema da Amazon é sistêmico. | Z33: No | AC33: No | AF33: No | AI33: ["Ajuda na resolução de problemas operacionais","Seleção (recomendação de produtos, oportunidades)","Conversão (qualidade do catálogo, preços, listatem)","Promoções (ofertas, cupons, eventos)","Logística (FBA, FBA-Onsite, DBA, logística própria)","Marca (registro, proteção, conteúdo A+, loja oficial)","Advertising (anúncios patrocinados)"] | AJ33: Não tenho sugestões no momento. | AK33: Muito importante | AL33: Muito importante | AM33: Muito importante | AN33: O sistema poderia ser menos moroso, para refletir alguns pontos no mesmo momento | AO33: Naiane Rangel | AP33: Muito satisfeito | AQ33: Discordo totalmente | AR33: Discordo totalmente | AS33: Discordo totalmente | AT33: Discordo totalmente | AU33: Discordo | AV33: Discordo | AW33: Discordo | AY33: Sim | AZ33: Satisfeito | BB33: Sim | BC33: Satisfeito | BE33: Sim | BF33: Nem satisfeito, nem insatisfeito | BG33: Poderia ser mais prestativo, estar mais presente, passar as comunicaÃ§Ãµes e estar atento as novidades | BH33: 1 | BI33: 4 | BJ33: 5 | BK33: 3 | BL33: 2 | BM33: 7 | BN33: 6 | BP33: Email Address
A34: 22445894402 | B34: MadeiraMadeira | C34: joaoclan | D34: =IF(C34="","0","1") -> 1 | E34: =IFERROR(IF(VLOOKUP(A34,Base!AA:AA,1,0)>0,"1","0"),"0") -> 1 | F34: =IF(OR(C34="",E34="0"),"-",IF(BC34="","-",IF(OR(BC34="Muito satisfeito",BC34="Satisfeito"),"1","0"))) -> 1 | G34: =IF(BC34="","0","1") -> 1 | H34: SurveySubmission-37vfNsIygKGUpTZsq69GpEka2SM | I34: 2026-01-07 12:20:28.127+00 | K34: MadeiraMadeira | L34: A5JVAXGT9G2CN | M34: Adrielle Clauman | N34: adrielle.clauman@madeiramadeira.com.br | O34: Revendedor | P34: Satisfeito | Q34: Satisfeito | R34: Concordo plenamente | S34: Concordo plenamente | T34: Recomendações Estratégicas -- Muito importante Assistência com Resolução de Problemas -- Muito importante Estratégia com Promoções -- Muito importante Gerenciamento e suporte de catálogo -- Muito importante Suporte com gerenciamento de inventário -- Muito importante Suporte com estratégia para novos produtos -- Muito importante | U34: no momento não | V34: Stephanie Steshino | W34: Muito satisfeito | X34: Meu consultor entende do meu negócio -- Concordo plenamente Meu consultor entende as necessidades do meu negócio com o programa SAS -- Concordo plenamente Meu consultor entende sobre a minha categoria de venda -- Concordo plenamente Meu consultor fornece recomendações estratégicas -- Concordo plenamente Meu consultor tem conhecimento dos recursos do Seller Central -- Concordo plenamente Meu consultor é responsivo via email -- Concordo plenamente Meu consultor se comunica por escrito de forma clara -- Concordo plenamente | Y34: ela me atende super bem! | Z34: Yes | AA34: 5 | AB34: no momento não | AC34: No | AF34: Yes | AG34: 3 | AH34: Não tive muito contato efetivo com a pessoa | AI34: ["Seleção (recomendação de produtos, oportunidades)","Advertising (anúncios patrocinados)","Marca (registro, proteção, conteúdo A+, loja oficial)","Conversão (qualidade do catálogo, preços, listatem)","Promoções (ofertas, cupons, eventos)","Ajuda na resolução de problemas operacionais","Logística (FBA, FBA-Onsite, DBA, logística própria)"] | AK34: Muito importante | AL34: Muito importante | AM34: Muito importante | AO34: Naiane | AP34: Muito satisfeito | AQ34: Discordo totalmente | AR34: Discordo totalmente | AS34: Discordo totalmente | AT34: Discordo totalmente | AU34: Discordo totalmente | AV34: Discordo totalmente | AW34: Discordo totalmente | AY34: Sim | AZ34: Muito satisfeito | BB34: Sim | BC34: Muito satisfeito | BE34: Sim | BF34: Muito satisfeito | BH34: 4 | BI34: 7 | BJ34: 5 | BK34: 6 | BL34: 3 | BM34: 1 | BN34: 2 | BP34: Email Address
A35: 743495001802 | B35: Vidro e Decor SP | D35: =IF(C35="","0","1") -> 0 | E35: =IFERROR(IF(VLOOKUP(A35,Base!AA:AA,1,0)>0,"1","0"),"0") -> 0 | F35: =IF(OR(C35="",E35="0"),"-",IF(BC35="","-",IF(OR(BC35="Muito satisfeito",BC35="Satisfeito"),"1","0"))) -> - | G35: =IF(BC35="","0","1") -> 0 | H35: SurveySubmission-37vfudT1odYbvKDgIIHXrl9UZzQ | I35: 2026-01-07 12:24:48.794+00 | K35: Houme Utilidades | L35: A3HY0P9HQ221PR | M35: Wadi Jabra Neto | N35: wadividro@gmail.com | O35: Dono de marca | P35: Muito satisfeito | Q35: Satisfeito | R35: Concordo parcialmente | S35: Concordo parcialmente | T35: Recomendações Estratégicas -- Serviço não é oferecido Assistência com Resolução de Problemas -- Importante Estratégia com Promoções -- Serviço não é oferecido Gerenciamento e suporte de catálogo -- Serviço não é oferecido Suporte com gerenciamento de inventário -- Serviço não é oferecido Suporte com estratégia para novos produtos -- Serviço não é oferecido | U35: Recomendações Estratégicas : Preciso que informe sempre o que pode ser feito sobre o ASIN até quando podemos chegar na redução da tarifa, para que a gente veja corretamente até quanto poderiamos deixar o valor de venda ok, pois só jogar a planilha e falar coloca o valor que consegue que diminuimos a tarifa é ruim. | V35: Manuela | W35: Nem satisfeito, nem insatisfeito | X35: Meu consultor entende do meu negócio -- Nem concordo, nem discordo Meu consultor entende as necessidades do meu negócio com o programa SAS -- Nem concordo, nem discordo Meu consultor entende sobre a minha categoria de venda -- Nem concordo, nem discordo Meu consultor fornece recomendações estratégicas -- Nem concordo, nem discordo Meu consultor tem conhecimento dos recursos do Seller Central -- Concordo parcialmente Meu consultor é responsivo via email -- Nem concordo, nem discordo Meu consultor se comunica por escrito de forma clara -- Nem concordo, nem discordo | Z35: No | AC35: No | AF35: No | AI35: ["Advertising (anúncios patrocinados)","Logística (FBA, FBA-Onsite, DBA, logística própria)","Ajuda na resolução de problemas operacionais","Promoções (ofertas, cupons, eventos)","Conversão (qualidade do catálogo, preços, listatem)","Marca (registro, proteção, conteúdo A+, loja oficial)","Seleção (recomendação de produtos, oportunidades)"] | AJ35: Primeiro de tudo, DBA > Sempre o Código de rastreio da erro sempre, sem suporte para isso rapido. | AK35: Muito importante | AL35: Muito importante | AM35: Importante | AO35: Naiane Rangel | AP35: Muito satisfeito | AQ35: Concordo plenamente | AR35: Concordo plenamente | AS35: Concordo plenamente | AT35: Concordo plenamente | AU35: Concordo plenamente | AV35: Concordo plenamente | AW35: Concordo plenamente | AX35: A Nai Ã© uma excelente consultora! Muito Ã¡gil, traz colaboraÃ§Ãµes valiosas e possui muito conhecimento da plataforma, alÃ©m de proatividade para nos auxiliar da melhor maneira nas resoluÃ§Ãµes de problemas. AlÃ©m disso, temos consegui aproveitar muito bem os eventos da Amazon devido o apoio e direcionamento que ela nos fornece. | AY35: Sim | AZ35: Satisfeito | BB35: NÃ£o | BE35: Sim | BF35: Muito satisfeito | BH35: 6 | BI35: 5 | BJ35: 3 | BK35: 2 | BL35: 4 | BM35: 1 | BN35: 7 | BO35: EvoluÃ§Ã£o glance views | BP35: Email Address
A36: 89297765302 | B36: MAXX NA SUA CASA | D36: =IF(C36="","0","1") -> 0 | E36: =IFERROR(IF(VLOOKUP(A36,Base!AA:AA,1,0)>0,"1","0"),"0") -> 0 | F36: =IF(OR(C36="",E36="0"),"-",IF(BC36="","-",IF(OR(BC36="Muito satisfeito",BC36="Satisfeito"),"1","0"))) -> - | G36: =IF(BC36="","0","1") -> 0 | H36: SurveySubmission-37vi48HzjYEi3iIBXebv5ctQ2VO | I36: 2026-01-07 12:42:31.697+00 | K36: MAXX MERCADINHO | L36: A1QJQSEM18ARA7 | M36: Giovanne Abilio | N36: Analista12@maxxnasuacasa.com.br | O36: Revendedor | P36: Satisfeito | Q36: Satisfeito | R36: Concordo parcialmente | S36: Concordo plenamente | T36: Recomendações Estratégicas -- Importante Assistência com Resolução de Problemas -- Muito importante Estratégia com Promoções -- Muito importante Gerenciamento e suporte de catálogo -- Importante Suporte com gerenciamento de inventário -- Importante Suporte com estratégia para novos produtos -- Importante | U36: Resolução de problemas no quesito inbound, muitos itens se perdem e prejudicam o vendendo alegando discrepância no envio, enviamos a quantidade correta e alegam não receber. | V36: Bianca Ramalho | W36: Muito satisfeito | X36: Meu consultor entende do meu negócio -- Concordo parcialmente Meu consultor entende as necessidades do meu negócio com o programa SAS -- Concordo plenamente Meu consultor entende sobre a minha categoria de venda -- Concordo plenamente Meu consultor fornece recomendações estratégicas -- Concordo plenamente Meu consultor tem conhecimento dos recursos do Seller Central -- Concordo parcialmente Meu consultor é responsivo via email -- Concordo plenamente Meu consultor se comunica por escrito de forma clara -- Concordo plenamente | Z36: Yes | AA36: 4 | AC36: Yes | AD36: 4 | AF36: Yes | AG36: 4 | AI36: ["Promoções (ofertas, cupons, eventos)","Logística (FBA, FBA-Onsite, DBA, logística própria)","Conversão (qualidade do catálogo, preços, listatem)","Ajuda na resolução de problemas operacionais","Advertising (anúncios patrocinados)","Seleção (recomendação de produtos, oportunidades)","Marca (registro, proteção, conteúdo A+, loja oficial)"] | AJ36: Relatório de vendas via PIX com o valor subsidiado pela Amazon | AK36: Muito importante | AL36: Muito importante | AM36: Muito importante | AN36: Acredito que com processos menos burocrÃ¡ticos e menos sellers na carteira do gerente o serviÃ§o poderia ser bem mais efetivo. | AO36: Naiane Rangel | AP36: Satisfeito | AQ36: Concordo parcialmente | AR36: Concordo plenamente | AS36: Concordo parcialmente | AT36: Concordo plenamente | AU36: Concordo plenamente | AV36: Concordo plenamente | AW36: Concordo plenamente | AX36: Acredito que o principal ponto seria o mesmo mencionado anteriormente, pois isso permitiria um melhor aproveitamento do tempo de ambos. | AY36: Sim | AZ36: Satisfeito | BA36: Os processos deveriam ser mais Ã¡geis e menos burocrÃ¡ticos. AlÃ©m disso particularmente acho que as regras de precificaÃ§Ã£o promocional da Amazon Ã© ruim e prejudicial aos sellers. | BB36: NÃ£o | BE36: NÃ£o | BH36: 4 | BI36: 6 | BJ36: 5 | BK36: 1 | BL36: 2 | BM36: 3 | BN36: 7 | BO36: Dados completos do funil de vendas, exemplo: AdiÃ§Ãµes a carrinho, compras realizadas, compras com pagamento nÃ£o aprovado, compras finalizadas, etc... | BP36: Email Address
A37: 1026263719202 | B37: Dyson Brasil | C37: fpereluc | D37: =IF(C37="","0","1") -> 1 | E37: =IFERROR(IF(VLOOKUP(A37,Base!AA:AA,1,0)>0,"1","0"),"0") -> 1 | F37: =IF(OR(C37="",E37="0"),"-",IF(BC37="","-",IF(OR(BC37="Muito satisfeito",BC37="Satisfeito"),"1","0"))) -> - | G37: =IF(BC37="","0","1") -> 0 | H37: SurveySubmission-37w4x0PXinCi9fAuEgmZrchMcdh | I37: 2026-01-07 15:50:41.853+00 | K37: Dyson | L37: A2N095U3MXUGS0 | M37: Paloma Bianca Araujo Garcia | N37: paloma@amazing-brasil.com | O37: Dono de marca | P37: Muito satisfeito | Q37: Muito satisfeito | R37: Concordo plenamente | S37: Concordo plenamente | T37: Recomendações Estratégicas -- Muito importante Assistência com Resolução de Problemas -- Muito importante Estratégia com Promoções -- Muito importante Gerenciamento e suporte de catálogo -- Muito importante Suporte com gerenciamento de inventário -- Muito importante Suporte com estratégia para novos produtos -- Muito importante | V37: Igor Martins Dias | W37: Muito satisfeito | X37: Meu consultor entende do meu negócio -- Concordo plenamente Meu consultor entende as necessidades do meu negócio com o programa SAS -- Concordo plenamente Meu consultor entende sobre a minha categoria de venda -- Concordo plenamente Meu consultor fornece recomendações estratégicas -- Concordo plenamente Meu consultor tem conhecimento dos recursos do Seller Central -- Concordo plenamente Meu consultor é responsivo via email -- Concordo plenamente Meu consultor se comunica por escrito de forma clara -- Concordo plenamente | Z37: No | AC37: Yes | AD37: 5 | AF37: No | AI37: ["Conversão (qualidade do catálogo, preços, listatem)","Marca (registro, proteção, conteúdo A+, loja oficial)","Advertising (anúncios patrocinados)","Promoções (ofertas, cupons, eventos)","Logística (FBA, FBA-Onsite, DBA, logística própria)","Seleção (recomendação de produtos, oportunidades)","Ajuda na resolução de problemas operacionais"] | AK37: Muito importante | AL37: Muito importante | AM37: Importante | AN37: Do lado de operaÃ§Ãµes sentimos a falta de um atendimento mais dedicado, alocado a uma unica pessoa! | AO37: Igor Dias | AP37: Satisfeito | AQ37: Concordo plenamente | AR37: Concordo plenamente | AS37: Concordo plenamente | AT37: Concordo plenamente | AU37: Concordo parcialmente | AV37: Concordo parcialmente | AW37: Concordo plenamente | AX37: Agilidade no retorno por parte do consultor, necessitamos de um suporte maior na parte de operaÃ§Ãµes como cadastro de novos produtos | AY37: Sim | AZ37: Satisfeito | BA37: uma pessoa para ajudar com problemas operacionais | BB37: NÃ£o | BE37: NÃ£o | BH37: 4 | BI37: 3 | BJ37: 7 | BK37: 5 | BL37: 2 | BM37: 1 | BN37: 6 | BP37: Email Address
A38: 241419664602 | B38: Móveis Carraro | C38: fpereluc | D38: =IF(C38="","0","1") -> 1 | E38: =IFERROR(IF(VLOOKUP(A38,Base!AA:AA,1,0)>0,"1","0"),"0") -> 1 | F38: =IF(OR(C38="",E38="0"),"-",IF(BC38="","-",IF(OR(BC38="Muito satisfeito",BC38="Satisfeito"),"1","0"))) -> 0 | G38: =IF(BC38="","0","1") -> 1 | H38: SurveySubmission-37w8gYGmg3nvQqmaiq7JpQniymc | I38: 2026-01-07 16:21:24.894+00 | K38: Móveis Carraro | L38: AOX5AHS90ZKR2 | M38: Leonardo Villa Baú | N38: leonardo.bau@carraro.com.br | O38: Dono de marca | P38: Muito satisfeito | Q38: Muito satisfeito | R38: Concordo plenamente | S38: Concordo plenamente | T38: Recomendações Estratégicas -- Muito importante Assistência com Resolução de Problemas -- Muito importante Estratégia com Promoções -- Muito importante Gerenciamento e suporte de catálogo -- Muito importante Suporte com gerenciamento de inventário -- Muito importante Suporte com estratégia para novos produtos -- Muito importante | U38: É fundamental que o Ads seja muito mais presente e estratégico dentro do programa. Atualmente, é difícil compreender como vender itens sem volume consistente de cliques, impressões e visibilidade, especialmente em categorias altamente competitivas como móveis. Sem investimento contínuo e direcionamento claro em mídia, o crescimento orgânico se torna limitado e a performance dos produtos fica comprometida. Além disso, é essencial que o programa atue de forma mais ativa na definição de prioridades, estratégias de tráfego e posicionamento, garantindo maior exposição dos produtos e suporte efetivo para ganho de relevância, conversão e escala dentro da Amazon. | V38: Igor Martins Dias | W38: Muito satisfeito | X38: Meu consultor entende do meu negócio -- Concordo plenamente Meu consultor entende as necessidades do meu negócio com o programa SAS -- Concordo plenamente Meu consultor entende sobre a minha categoria de venda -- Concordo plenamente Meu consultor fornece recomendações estratégicas -- Concordo plenamente Meu consultor tem conhecimento dos recursos do Seller Central -- Concordo plenamente Meu consultor é responsivo via email -- Concordo plenamente Meu consultor se comunica por escrito de forma clara -- Concordo plenamente | Y38: Atendimento Excelente! | Z38: Yes | AA38: 5 | AB38: Sugiro a entrega de mais relatórios personalizados por produto e por marca, com foco em performance, visibilidade e oportunidades de melhoria. Relatórios semanais, enviados por e-mail, ajudariam a acompanhar a evolução dos resultados, apoiar decisões mais rápidas e tornar o serviço mais estratégico e próximo da realidade operacional do vendedor. | AC38: Yes | AD38: 5 | AF38: Yes | AG38: 4 | AH38: É importante que o consultor de Ads seja mais presente e proativo, trazendo sugestões práticas e direcionadas por produto, com foco em aumentar visibilidade, cliques e vendas. Um acompanhamento mais próximo, com recomendações específicas e frequentes, contribuiria diretamente para melhores resultados e crescimento da conta. | AI38: ["Promoções (ofertas, cupons, eventos)","Advertising (anúncios patrocinados)","Conversão (qualidade do catálogo, preços, listatem)","Ajuda na resolução de problemas operacionais","Marca (registro, proteção, conteúdo A+, loja oficial)","Seleção (recomendação de produtos, oportunidades)","Logística (FBA, FBA-Onsite, DBA, logística própria)"] | AJ38: Relatório semanal por produto (ASIN) Performance individual de cada item, com leitura clara de visibilidade, conversão e potencial de escala Relatório de funil completo Visão integrada semelhante ao funil usado em mídia externa, facilitando entender onde o produto está travando. Relatório comparativo de concorrência por produto Benchmark de preço, posicionamento, visibilidade e participação. Relatório de oportunidades e ações recomendadas por produto Documento acionável, apontando o que ajustar em Ads, preço, conteúdo ou promoções para vender mais, similar a dashboards usados em agências de performance. Relatório de evolução de marca e share de visibilidade Acompanhamento contínuo de presença da marca dentro da categoria, algo comum em mídia e BI fora da Amazon. Relatório de histórico e tendência (semanal/mensal) Análise de evolução para apoiar decisões estratégicas, prática padrão em outros canais digitais. | AK38: Importante | AL38: Importante | AM38: Importante | AN38: Sendo mais estratÃ©gico, buscando auxiliar numa gestÃ£o que olhe o 360Âº da operaÃ§Ã£o. | AO38: Thomas Thalenberg | AP38: Satisfeito | AQ38: Concordo parcialmente | AR38: Concordo parcialmente | AS38: Concordo plenamente | AT38: Concordo plenamente | AU38: Concordo plenamente | AV38: Concordo plenamente | AW38: Concordo plenamente | AX38: Estar mais prÃ³ximo do dia a dia, para auxiliar em oportunidades. Talvez retomar as agendas mensais que tinhamos presenciais, olhando nÃºmeros e acompanhamento das metas desenhadas | AY38: NÃ£o | BB38: Sim | BC38: Nem satisfeito, nem insatisfeito | BD38: Entendi errado a pergunta anterior. NÃ£o tenho um gerente de contas operacional | BE38: NÃ£o | BH38: 3 | BI38: 6 | BJ38: 7 | BK38: 5 | BL38: 2 | BM38: 1 | BN38: 4 | BO38: RelatÃ³rio de cÃ³digos (Asins e Skus) | BP38: Email Address
A39: 92771955402 | B39: Imagem Hitech | C39: tiaelima | D39: =IF(C39="","0","1") -> 1 | E39: =IFERROR(IF(VLOOKUP(A39,Base!AA:AA,1,0)>0,"1","0"),"0") -> 1 | F39: =IF(OR(C39="",E39="0"),"-",IF(BC39="","-",IF(OR(BC39="Muito satisfeito",BC39="Satisfeito"),"1","0"))) -> - | G39: =IF(BC39="","0","1") -> 0 | H39: SurveySubmission-37wD2DIJrFUpigkXnVdrr0Ca950 | I39: 2026-01-07 16:57:10.637+00 | K39: Imagem Hitech FBA | L39: A3POF6EIWE8R8 | M39: Julio Cesar | N39: imagemhitechfbasp@gmail.com | O39: Ambos | P39: Muito satisfeito | Q39: Muito satisfeito | R39: Concordo plenamente | S39: Concordo plenamente | T39: Recomendações Estratégicas -- Muito importante Assistência com Resolução de Problemas -- Importante Estratégia com Promoções -- Muito importante Gerenciamento e suporte de catálogo -- Muito importante Suporte com gerenciamento de inventário -- Importante Suporte com estratégia para novos produtos -- Muito importante | V39: Rafaela Saad | W39: Muito satisfeito | X39: Meu consultor entende do meu negócio -- Concordo plenamente Meu consultor entende as necessidades do meu negócio com o programa SAS -- Concordo plenamente Meu consultor entende sobre a minha categoria de venda -- Concordo plenamente Meu consultor fornece recomendações estratégicas -- Concordo plenamente Meu consultor tem conhecimento dos recursos do Seller Central -- Concordo plenamente Meu consultor é responsivo via email -- Concordo plenamente Meu consultor se comunica por escrito de forma clara -- Concordo plenamente | Z39: Yes | AA39: 5 | AC39: Yes | AD39: 5 | AF39: Yes | AG39: 5 | AI39: ["Ajuda na resolução de problemas operacionais","Logística (FBA, FBA-Onsite, DBA, logística própria)","Promoções (ofertas, cupons, eventos)","Conversão (qualidade do catálogo, preços, listatem)","Marca (registro, proteção, conteúdo A+, loja oficial)","Advertising (anúncios patrocinados)","Seleção (recomendação de produtos, oportunidades)"] | AK39: Muito importante | AL39: Muito importante | AM39: Muito importante | AN39: no momento nÃ£o. | AO39: Rafaela Saad | AP39: Muito satisfeito | AQ39: Concordo plenamente | AR39: Concordo plenamente | AS39: Concordo plenamente | AT39: Concordo plenamente | AU39: Concordo plenamente | AV39: Concordo plenamente | AW39: Concordo plenamente | AX39: No momento nÃ£o. | AY39: Sim | AZ39: Muito satisfeito | BA39: nÃ£o | BB39: NÃ£o | BE39: NÃ£o | BH39: 2 | BI39: 7 | BJ39: 5 | BK39: 3 | BL39: 1 | BM39: 4 | BN39: 6 | BO39: estou satisfeito como estÃ¡ | BP39: Email Address
A40: 453606604502 | B40: Go Compras | C40: joaoclan | D40: =IF(C40="","0","1") -> 1 | E40: =IFERROR(IF(VLOOKUP(A40,Base!AA:AA,1,0)>0,"1","0"),"0") -> 0 | F40: =IF(OR(C40="",E40="0"),"-",IF(BC40="","-",IF(OR(BC40="Muito satisfeito",BC40="Satisfeito"),"1","0"))) -> - | G40: =IF(BC40="","0","1") -> 1 | H40: SurveySubmission-37wejbrH1t62wGcF8gYrU60wj7s | I40: 2026-01-07 20:44:56.944+00 | K40: GoCompras | L40: A3GD2VAPD5RJ7X | M40: Matheus Jardim | N40: ecommerce@denteck.com.br | O40: Revendedor | P40: Muito satisfeito | Q40: Muito satisfeito | R40: Concordo plenamente | S40: Concordo plenamente | T40: Recomendações Estratégicas -- Muito importante Assistência com Resolução de Problemas -- Muito importante Estratégia com Promoções -- Muito importante Gerenciamento e suporte de catálogo -- Muito importante Suporte com gerenciamento de inventário -- Muito importante Suporte com estratégia para novos produtos -- Muito importante | V40: Tatiane Assis | W40: Muito satisfeito | X40: Meu consultor entende do meu negócio -- Concordo plenamente Meu consultor entende as necessidades do meu negócio com o programa SAS -- Concordo plenamente Meu consultor entende sobre a minha categoria de venda -- Concordo plenamente Meu consultor fornece recomendações estratégicas -- Concordo plenamente Meu consultor tem conhecimento dos recursos do Seller Central -- Concordo plenamente Meu consultor é responsivo via email -- Concordo plenamente Meu consultor se comunica por escrito de forma clara -- Concordo plenamente | Z40: Yes | AA40: 5 | AC40: Yes | AD40: 5 | AF40: Yes | AG40: 5 | AI40: ["Promoções (ofertas, cupons, eventos)","Ajuda na resolução de problemas operacionais","Seleção (recomendação de produtos, oportunidades)","Conversão (qualidade do catálogo, preços, listatem)","Logística (FBA, FBA-Onsite, DBA, logística própria)","Marca (registro, proteção, conteúdo A+, loja oficial)","Advertising (anúncios patrocinados)"] | AK40: Muito importante | AL40: Muito importante | AM40: Muito importante | AO40: Rafaela Saad | AP40: Muito satisfeito | AQ40: Concordo plenamente | AR40: Concordo plenamente | AS40: Concordo plenamente | AT40: Concordo plenamente | AU40: Concordo plenamente | AV40: Concordo plenamente | AW40: Concordo plenamente | AY40: Sim | AZ40: Muito satisfeito | BA40: ServiÃ§o de logistica DBA e atendimento referente as operaÃ§Ãµes de coleta ou envio atÃ© o ponto de coleta, mudam do dia para noite, sem comunicado previo e afeta diretamente na nossa operaÃ§Ã£o de expediÃ§Ã£o. | BB40: Sim | BC40: Insatisfeito | BD40: Tivemos durante duas semanas problemas com a logistica da amazon que nÃ£o passou para retirada e depois de duas semanas sinalizando o problema, percebemos que a operaÃ§Ã£o havia virado sem comunicado previo de coleta para envio no ponto de coleta, nÃ£o tivemos suporte do time para resoluÃ§Ã£o, depois de duas semanas foi solicitado que resumissemos o que haviamos conversado sobre esse tema no grupo, 90% da conversa do grupo dessas duas semanas eram sobre esses problemas logisticos e pontos de coleta que haviam mudado de endereÃ§o. | BE40: Sim | BF40: Satisfeito | BH40: 6 | BI40: 2 | BJ40: 5 | BK40: 3 | BL40: 1 | BM40: 7 | BN40: 4 | BP40: Email Address
A41: 125288528002 | B41: Alô Bebê | C41: gomrodrd | D41: =IF(C41="","0","1") -> 1 | E41: =IFERROR(IF(VLOOKUP(A41,Base!AA:AA,1,0)>0,"1","0"),"0") -> 1 | F41: =IF(OR(C41="",E41="0"),"-",IF(BC41="","-",IF(OR(BC41="Muito satisfeito",BC41="Satisfeito"),"1","0"))) -> 1 | G41: =IF(BC41="","0","1") -> 1 | H41: SurveySubmission-37wfKCQIFcp5fzQKuarwOHnjFZs | I41: 2026-01-07 20:49:47.907+00 | K41: Alô Bebê | L41: A3ABUSG30TDB | M41: Alessandro Verdugal | N41: Alessandro.verdugal@alobebe.com.br | O41: Revendedor | P41: Muito satisfeito | Q41: Muito satisfeito | R41: Concordo plenamente | S41: Concordo plenamente | T41: Recomendações Estratégicas -- Importante Assistência com Resolução de Problemas -- Muito importante Estratégia com Promoções -- Importante Gerenciamento e suporte de catálogo -- Importante Suporte com gerenciamento de inventário -- Importante Suporte com estratégia para novos produtos -- Muito importante | V41: Julia de Brito | W41: Muito satisfeito | X41: Meu consultor entende do meu negócio -- Concordo plenamente Meu consultor entende as necessidades do meu negócio com o programa SAS -- Concordo plenamente Meu consultor entende sobre a minha categoria de venda -- Concordo plenamente Meu consultor fornece recomendações estratégicas -- Concordo plenamente Meu consultor tem conhecimento dos recursos do Seller Central -- Concordo plenamente Meu consultor é responsivo via email -- Concordo plenamente Meu consultor se comunica por escrito de forma clara -- Concordo plenamente | Z41: Yes | AA41: 4 | AC41: Yes | AD41: 4 | AF41: Yes | AG41: 5 | AI41: ["Ajuda na resolução de problemas operacionais","Logística (FBA, FBA-Onsite, DBA, logística própria)","Promoções (ofertas, cupons, eventos)","Conversão (qualidade do catálogo, preços, listatem)","Advertising (anúncios patrocinados)","Seleção (recomendação de produtos, oportunidades)","Marca (registro, proteção, conteúdo A+, loja oficial)"] | AJ41: Relatório de Search Keywords deveria ser mensal. | AK41: Muito importante | AL41: Muito importante | AM41: Muito importante | AN41: Acredito que a Amazon poderia ter mais programas de incetivo como nas outras plataformas, como , dias focados de desconto na categoria de moda, pacotes de rebate, mais eventos importsntes, voltar com oferta uau, double date, para ter mais trafego na plataforma e consequentemente mais vendas | AO41: Sarah Meyer | AP41: Muito satisfeito | AQ41: Concordo plenamente | AR41: Concordo plenamente | AS41: Concordo plenamente | AT41: Concordo plenamente | AU41: Concordo plenamente | AV41: Concordo plenamente | AW41: Concordo plenamente | AX41: Acredito que dentro das oportunidades da conta a sarah vem feito um excelente trabalho. Os problemas que tiveram foram mais relacionados a amazon, as limitaÃ§Ãµes da plataforma, e em todas, a sarah prestou assistÃªncia | AY41: Sim | AZ41: Satisfeito | BA41: NÃ£o exploro tudo ainda, entÃ£o nÃ£o tenho base para sugerir melhorias. | BB41: Sim | BC41: Satisfeito | BE41: Sim | BF41: Insatisfeito | BG41: Praticamente nÃ£o temos contato | BH41: 6 | BI41: 4 | BJ41: 7 | BK41: 3 | BL41: 1 | BM41: 2 | BN41: 5 | BP41: Email Address
A42: 658814193902 | B42: FutFanaticsOficial | C42: qmanuelv | D42: =IF(C42="","0","1") -> 1 | E42: =IFERROR(IF(VLOOKUP(A42,Base!AA:AA,1,0)>0,"1","0"),"0") -> 1 | F42: =IF(OR(C42="",E42="0"),"-",IF(BC42="","-",IF(OR(BC42="Muito satisfeito",BC42="Satisfeito"),"1","0"))) -> - | G42: =IF(BC42="","0","1") -> 0 | H42: SurveySubmission-37yJmdljfqaYBlXJzxOXTMwNS6P | I42: 2026-01-08 10:52:17.344+00 | K42: Futfanatics | L42: A1OBYHY407P1CX | M42: Danieli Aparecida da Silva | N42: danieli.silva@futcorp.com.br | O42: Revendedor | P42: Satisfeito | Q42: Satisfeito | R42: Concordo plenamente | S42: Concordo plenamente | T42: Recomendações Estratégicas -- Muito importante Assistência com Resolução de Problemas -- Muito importante Estratégia com Promoções -- Importante Gerenciamento e suporte de catálogo -- Muito importante Suporte com gerenciamento de inventário -- Muito importante Suporte com estratégia para novos produtos -- Muito importante | V42: Ana Bon | W42: Muito satisfeito | X42: Meu consultor entende do meu negócio -- Concordo plenamente Meu consultor entende as necessidades do meu negócio com o programa SAS -- Concordo plenamente Meu consultor entende sobre a minha categoria de venda -- Concordo plenamente Meu consultor fornece recomendações estratégicas -- Concordo plenamente Meu consultor tem conhecimento dos recursos do Seller Central -- Concordo plenamente Meu consultor é responsivo via email -- Concordo plenamente Meu consultor se comunica por escrito de forma clara -- Concordo plenamente | Z42: Yes | AA42: 5 | AC42: Yes | AD42: 5 | AF42: No | AI42: ["Conversão (qualidade do catálogo, preços, listatem)","Marca (registro, proteção, conteúdo A+, loja oficial)","Ajuda na resolução de problemas operacionais","Logística (FBA, FBA-Onsite, DBA, logística própria)","Promoções (ofertas, cupons, eventos)","Seleção (recomendação de produtos, oportunidades)"] | AK42: Muito importante | AL42: Muito importante | AM42: Muito importante | AN42: NÃ£o estamos tendo nenhum respaldo da equipe perante os vendedores fraudulentos que estÃ£o acessando nossos itens, trabalhamos praticamente com nosso inventario todo no Fba e onsite e simplesmente somos invadidos e nÃ£o temos suporte. | AO42: Julia | AP42: Nem satisfeito, nem insatisfeito | AQ42: Nem concordo, nem discordo | AR42: Nem concordo, nem discordo | AS42: Nem concordo, nem discordo | AT42: Nem concordo, nem discordo | AU42: Nem concordo, nem discordo | AV42: Nem concordo, nem discordo | AW42: Nem concordo, nem discordo | AX42: Alguem esta no lugar errado ou o consultor ou a equipe po trÃ¡s. | AY42: NÃ£o | BB42: NÃ£o | BE42: NÃ£o | BH42: 4 | BI42: 3 | BJ42: 1 | BK42: 5 | BL42: 2 | BM42: 6 | BN42: 7 | BO42: sem necessidade | BP42: Email Address
A43: 25545596202 | B43: Magazine Decor | D43: =IF(C43="","0","1") -> 0 | E43: =IFERROR(IF(VLOOKUP(A43,Base!AA:AA,1,0)>0,"1","0"),"0") -> 0 | F43: =IF(OR(C43="",E43="0"),"-",IF(BC43="","-",IF(OR(BC43="Muito satisfeito",BC43="Satisfeito"),"1","0"))) -> - | G43: =IF(BC43="","0","1") -> 0 | H43: SurveySubmission-37yQAMwHPdGP5mwMgQZr6xTW93K | I43: 2026-01-08 11:44:46.865+00 | K43: Magazine Decor | L43: A23WN10NF6K5HQ | M43: Gabriel Pedó | N43: gabriel@magazinedecor.com.br | O43: Ambos | P43: Muito satisfeito | Q43: Muito satisfeito | R43: Concordo plenamente | S43: Concordo plenamente | T43: Recomendações Estratégicas -- Muito importante Assistência com Resolução de Problemas -- Muito importante Estratégia com Promoções -- Muito importante Gerenciamento e suporte de catálogo -- Importante Suporte com gerenciamento de inventário -- Importante Suporte com estratégia para novos produtos -- Importante | V43: Julia de Brito | W43: Muito satisfeito | X43: Meu consultor entende do meu negócio -- Concordo plenamente Meu consultor entende as necessidades do meu negócio com o programa SAS -- Concordo plenamente Meu consultor entende sobre a minha categoria de venda -- Concordo plenamente Meu consultor fornece recomendações estratégicas -- Concordo plenamente Meu consultor tem conhecimento dos recursos do Seller Central -- Concordo plenamente Meu consultor é responsivo via email -- Concordo plenamente Meu consultor se comunica por escrito de forma clara -- Concordo plenamente | Z43: No | AC43: No | AF43: Yes | AG43: 4 | AI43: ["Ajuda na resolução de problemas operacionais","Promoções (ofertas, cupons, eventos)","Logística (FBA, FBA-Onsite, DBA, logística própria)","Conversão (qualidade do catálogo, preços, listatem)","Marca (registro, proteção, conteúdo A+, loja oficial)","Advertising (anúncios patrocinados)","Seleção (recomendação de produtos, oportunidades)"] | AK43: Importante | AL43: Importante | AM43: Sem importÃ¢ncia | AN43: Mais comissÃµes especiais em mais produto e em perÃ­odos sem eventos | AO43: Manoela Rodrigues | AP43: Satisfeito | AQ43: Concordo parcialmente | AR43: Concordo parcialmente | AS43: Concordo plenamente | AT43: Nem concordo, nem discordo | AU43: Concordo parcialmente | AV43: Nem concordo, nem discordo | AW43: Concordo plenamente | AX43: ComunicaÃ§Ã£o mais Ã¡gil | AY43: Sim | AZ43: Satisfeito | BB43: NÃ£o | BE43: NÃ£o | BH43: 6 | BI43: 5 | BJ43: 4 | BK43: 7 | BL43: 1 | BM43: 2 | BN43: 3 | BO43: RelatÃ³rio de produtos mais vendidos na amazon de alguma categoria especifica solicitada | BP43: Email Address
A44: 72695582302 | B44: XcommBR | C44: fpereluc | D44: =IF(C44="","0","1") -> 1 | E44: =IFERROR(IF(VLOOKUP(A44,Base!AA:AA,1,0)>0,"1","0"),"0") -> 1 | F44: =IF(OR(C44="",E44="0"),"-",IF(BC44="","-",IF(OR(BC44="Muito satisfeito",BC44="Satisfeito"),"1","0"))) -> 1 | G44: =IF(BC44="","0","1") -> 1 | H44: SurveySubmission-37yQTSpEHPDjOdElkDumxLxPBOD | I44: 2026-01-08 11:47:18.692+00 | K44: XcommBR | L44: AVRTQ9CK3FDWE | M44: Maiara Nascimento | N44: maiara@tseller.com.br | O44: Revendedor | P44: Satisfeito | Q44: Satisfeito | R44: Concordo plenamente | S44: Concordo parcialmente | T44: Recomendações Estratégicas -- Importante Assistência com Resolução de Problemas -- Muito importante Estratégia com Promoções -- Muito importante Gerenciamento e suporte de catálogo -- Importante Suporte com gerenciamento de inventário -- Importante Suporte com estratégia para novos produtos -- Importante | U44: O programa SAS pode melhorar sendo mais proativo e personalizado, especialmente em ads e promoções, com recomendações baseadas no desempenho real da conta. Também ajudaria trazer insights práticos para conversão e uma resolução de problemas mais ágil entre as áreas. | V44: Igor Martins Dias | W44: Muito satisfeito | X44: Meu consultor entende do meu negócio -- Concordo plenamente Meu consultor entende as necessidades do meu negócio com o programa SAS -- Concordo plenamente Meu consultor entende sobre a minha categoria de venda -- Concordo plenamente Meu consultor fornece recomendações estratégicas -- Concordo plenamente Meu consultor tem conhecimento dos recursos do Seller Central -- Concordo plenamente Meu consultor é responsivo via email -- Concordo plenamente Meu consultor se comunica por escrito de forma clara -- Concordo plenamente | Y44: O consultor tem boa comunicação, demonstra conhecimento da plataforma e mantém um suporte consistente no dia a dia. | Z44: Yes | AA44: 4 | AB44: A experiência é positiva e o serviço atende bem às necessidades atuais. Como melhoria, seria interessante ampliar as tarefas com foco mais estratégico e trazer sugestões proativas baseadas no desempenho da conta. | AC44: Yes | AD44: 4 | AE44: O suporte é eficiente e resolve as demandas com clareza. Como ponto de melhoria, a agilidade em alguns chamados e uma maior integração entre as áreas poderiam tornar a resolução de problemas ainda mais rápida. | AF44: No | AI44: ["Conversão (qualidade do catálogo, preços, listatem)","Promoções (ofertas, cupons, eventos)","Ajuda na resolução de problemas operacionais","Seleção (recomendação de produtos, oportunidades)","Marca (registro, proteção, conteúdo A+, loja oficial)","Logística (FBA, FBA-Onsite, DBA, logística própria)","Advertising (anúncios patrocinados)"] | AJ44: Relatório de problemas operacionais (status, SLA e recorrência de chamados) Relatório de ruptura e estoque (previsão de ruptura e impacto em faturamento) | AK44: Muito importante | AL44: Muito importante | AM44: Muito importante | AN44: Acredito que ajudando melhor no desempenho das nossas campanhas ADS e reuniÃµes de alinhamento estratÃ©gico com o time de ADS, o time de logÃ­stica tambÃ©m deve continuar acompanhando para nos ajudar com todos os possÃ­veis problemas, mas ter as informaÃ§Ãµes de calendÃ¡rio de entrega para grandes eventos mais antecipado juntamente com as projeÃ§Ãµes para nos auxiliar. | AO44: Stephanie Shinohara, | AP44: Muito satisfeito | AQ44: Concordo plenamente | AR44: Concordo plenamente | AS44: Concordo plenamente | AT44: Concordo plenamente | AU44: Concordo plenamente | AV44: Concordo plenamente | AW44: Concordo plenamente | AX44: NÃ£o, ela jÃ¡ Ã© muito boa no que faz | AY44: Sim | AZ44: Muito satisfeito | BA44: Acredito que uma coisa muito boa para nos mandar seriam as projeÃ§Ãµes de quanto vender em cada campanha | BB44: Sim | BC44: Satisfeito | BD44: O suporte Ã© um pouco demorado na resposta, seria melhor disponibilizar um contato pelo Whatsapp igual temos contato com os gerentes para que estes possam nos ajudar com as demandas urgentes que precisam ser tratadas por suporte | BE44: Sim | BF44: Satisfeito | BG44: ReuniÃ£o de alinhamento de expectativa, e sugestÃµes de campanhas que ainda nÃ£o usamos que fazem sentido para nossa empresa | BH44: 3 | BI44: 5 | BJ44: 7 | BK44: 6 | BL44: 1 | BM44: 4 | BN44: 2 | BO44: NÃ£o pe bem um relatÃ³rio, mas seria excelente um painel onde mostra quais produtos e quantidades estÃ£o sendo vendidas de cada produto. | BP44: Email Address
A45: 1041281178802 | B45: TCLSEMP | C45: tiaelima | D45: =IF(C45="","0","1") -> 1 | E45: =IFERROR(IF(VLOOKUP(A45,Base!AA:AA,1,0)>0,"1","0"),"0") -> 1 | F45: =IF(OR(C45="",E45="0"),"-",IF(BC45="","-",IF(OR(BC45="Muito satisfeito",BC45="Satisfeito"),"1","0"))) -> - | G45: =IF(BC45="","0","1") -> 0 | H45: SurveySubmission-37yXwKTtDgDyqO8juEyGAnc6LPF | I45: 2026-01-08 12:48:41.813+00 | K45: Mega-Mamute. | L45: A36Y0ADH0NS701 | M45: Marcelo Henrique Celeri | N45: marcelo.celeri@megamamute.com.br | O45: Revendedor | P45: Muito satisfeito | Q45: Muito satisfeito | R45: Concordo plenamente | S45: Concordo parcialmente | T45: Recomendações Estratégicas -- Muito importante Assistência com Resolução de Problemas -- Muito importante Estratégia com Promoções -- Muito importante Gerenciamento e suporte de catálogo -- Muito importante Suporte com gerenciamento de inventário -- Muito importante Suporte com estratégia para novos produtos -- Muito importante | V45: Rafaela Saad | W45: Muito satisfeito | X45: Meu consultor entende do meu negócio -- Concordo plenamente Meu consultor entende as necessidades do meu negócio com o programa SAS -- Concordo plenamente Meu consultor entende sobre a minha categoria de venda -- Concordo plenamente Meu consultor fornece recomendações estratégicas -- Concordo plenamente Meu consultor tem conhecimento dos recursos do Seller Central -- Concordo plenamente Meu consultor é responsivo via email -- Concordo plenamente Meu consultor se comunica por escrito de forma clara -- Concordo plenamente | Z45: Yes | AA45: 5 | AC45: Yes | AD45: 5 | AF45: No | AI45: ["Promoções (ofertas, cupons, eventos)","Conversão (qualidade do catálogo, preços, listatem)","Ajuda na resolução de problemas operacionais","Logística (FBA, FBA-Onsite, DBA, logística própria)","Seleção (recomendação de produtos, oportunidades)","Advertising (anúncios patrocinados)","Marca (registro, proteção, conteúdo A+, loja oficial)"] | AK45: Muito importante | AL45: Importante | AM45: Importante | AN45: Contato mais ativo com time de ads. | AO45: Rafaela Saad | AP45: Muito satisfeito | AQ45: Concordo plenamente | AR45: Concordo plenamente | AS45: Concordo plenamente | AT45: Concordo plenamente | AU45: Concordo plenamente | AV45: Concordo plenamente | AW45: Concordo plenamente | AX45: Nada, a Rafa Ã© maravilhosa!! Melhor consultora que ja tivemos! | AY45: NÃ£o | BB45: NÃ£o | BE45: Sim | BF45: Insatisfeito | BG45: Ficamos sem consultor por mais de dois meses, nÃ£o fomos sinalizados da saÃ­da do consultor e a conta ficou "Parada" sem melhorias ou sugestÃµes. O consultor novo comeÃ§o, e estamos no aguardo de novas campanhas. | BH45: 4 | BI45: 6 | BJ45: 7 | BK45: 5 | BL45: 1 | BM45: 3 | BN45: 2 | BP45: Email Address
A46: 277711423902 | B46: Tudo de Bicho | C46: gomrodrd | D46: =IF(C46="","0","1") -> 1 | E46: =IFERROR(IF(VLOOKUP(A46,Base!AA:AA,1,0)>0,"1","0"),"0") -> 1 | F46: =IF(OR(C46="",E46="0"),"-",IF(BC46="","-",IF(OR(BC46="Muito satisfeito",BC46="Satisfeito"),"1","0"))) -> 1 | G46: =IF(BC46="","0","1") -> 1 | H46: SurveySubmission-37yauXmQbdoKpO2pIUCQH016Mw0 | I46: 2026-01-08 13:13:07.887+00 | K46: Tudo de Bicho | L46: A344Y1CIM8RQJV | M46: Jéssica Cristina Sousa das Neves | N46: jessica.cristina@tudodebicho.com.br | O46: Ambos | P46: Muito satisfeito | Q46: Muito satisfeito | R46: Concordo plenamente | S46: Concordo plenamente | T46: Recomendações Estratégicas -- Muito importante Assistência com Resolução de Problemas -- Muito importante Estratégia com Promoções -- Muito importante Gerenciamento e suporte de catálogo -- Importante Suporte com gerenciamento de inventário -- Importante Suporte com estratégia para novos produtos -- Muito importante | V46: Julia De Brito | W46: Muito satisfeito | X46: Meu consultor entende do meu negócio -- Concordo plenamente Meu consultor entende as necessidades do meu negócio com o programa SAS -- Concordo plenamente Meu consultor entende sobre a minha categoria de venda -- Concordo plenamente Meu consultor fornece recomendações estratégicas -- Concordo plenamente Meu consultor tem conhecimento dos recursos do Seller Central -- Concordo plenamente Meu consultor é responsivo via email -- Concordo plenamente Meu consultor se comunica por escrito de forma clara -- Concordo plenamente | Z46: Yes | AA46: 5 | AC46: Yes | AD46: 5 | AF46: Yes | AG46: 5 | AI46: ["Promoções (ofertas, cupons, eventos)","Ajuda na resolução de problemas operacionais","Logística (FBA, FBA-Onsite, DBA, logística própria)","Advertising (anúncios patrocinados)","Conversão (qualidade do catálogo, preços, listatem)","Marca (registro, proteção, conteúdo A+, loja oficial)","Seleção (recomendação de produtos, oportunidades)"] | AK46: Muito importante | AL46: Importante | AM46: Importante | AO46: Manoela | AP46: Satisfeito | AQ46: Concordo parcialmente | AR46: Concordo parcialmente | AS46: Nem concordo, nem discordo | AT46: Concordo parcialmente | AU46: Concordo plenamente | AV46: Concordo plenamente | AW46: Concordo plenamente | AY46: NÃ£o | BB46: Sim | BC46: Satisfeito | BE46: Sim | BF46: Insatisfeito | BG46: Melhorar performance baseado na estrategia comercial. Tenho a sensaÃ§Ã£o que estou investindo Ads, apenas para bater uma meta. | BH46: 6 | BI46: 3 | BJ46: 5 | BK46: 4 | BL46: 1 | BM46: 2 | BN46: 7 | BP46: Email Address
A47: 101837981602 | B47: Nespresso Loja Oficial | C47: gomrodrd | D47: =IF(C47="","0","1") -> 1 | E47: =IFERROR(IF(VLOOKUP(A47,Base!AA:AA,1,0)>0,"1","0"),"0") -> 1 | F47: =IF(OR(C47="",E47="0"),"-",IF(BC47="","-",IF(OR(BC47="Muito satisfeito",BC47="Satisfeito"),"1","0"))) -> 1 | G47: =IF(BC47="","0","1") -> 1 | H47: SurveySubmission-37zM3vQPTdh0huuIaS2OEUBprIj | I47: 2026-01-08 19:40:50.895+00 | K47: Nespresso | L47: A3KW89NPNRUEIV | M47: Gustavo de Oliveira Maia | N47: gustavo.maia@nespresso.com | O47: Dono de marca | P47: Nem satisfeito, nem insatisfeito | Q47: Satisfeito | R47: Concordo parcialmente | S47: Concordo parcialmente | T47: Recomendações Estratégicas -- Sem importância Assistência com Resolução de Problemas -- Importante Estratégia com Promoções -- Importante Gerenciamento e suporte de catálogo -- Importante Suporte com gerenciamento de inventário -- Importante Suporte com estratégia para novos produtos -- Sem importância | U47: Poderiamos ter mais granularidade de dados principalmente olhando a nivel categoria. Sem abrir nome de competidores mas sim da categoria | V47: Bianca Ramalho | W47: Satisfeito | X47: Meu consultor entende do meu negócio -- Concordo parcialmente Meu consultor entende as necessidades do meu negócio com o programa SAS -- Concordo parcialmente Meu consultor entende sobre a minha categoria de venda -- Nem concordo, nem discordo Meu consultor fornece recomendações estratégicas -- Nem concordo, nem discordo Meu consultor tem conhecimento dos recursos do Seller Central -- Concordo parcialmente Meu consultor é responsivo via email -- Concordo parcialmente Meu consultor se comunica por escrito de forma clara -- Concordo parcialmente | Z47: No | AC47: No | AF47: Yes | AG47: 4 | AI47: ["Ajuda na resolução de problemas operacionais","Logística (FBA, FBA-Onsite, DBA, logística própria)","Promoções (ofertas, cupons, eventos)","Conversão (qualidade do catálogo, preços, listatem)","Advertising (anúncios patrocinados)","Marca (registro, proteção, conteúdo A+, loja oficial)","Seleção (recomendação de produtos, oportunidades)"] | AK47: Muito importante | AL47: Muito importante | AM47: Muito importante | AO47: Luciana Tavares | AP47: Muito satisfeito | AQ47: Concordo plenamente | AR47: Concordo plenamente | AS47: Concordo plenamente | AT47: Concordo plenamente | AU47: Concordo plenamente | AV47: Concordo plenamente | AW47: Concordo plenamente | AY47: Sim | AZ47: Muito satisfeito | BB47: Sim | BC47: Satisfeito | BE47: Sim | BF47: Satisfeito | BH47: 1 | BI47: 2 | BJ47: 3 | BK47: 4 | BL47: 5 | BM47: 7 | BN47: 6 | BP47: Email Address
A48: 136831572602 | B48: Casa do Fitness | D48: =IF(C48="","0","1") -> 0 | E48: =IFERROR(IF(VLOOKUP(A48,Base!AA:AA,1,0)>0,"1","0"),"0") -> 0 | F48: =IF(OR(C48="",E48="0"),"-",IF(BC48="","-",IF(OR(BC48="Muito satisfeito",BC48="Satisfeito"),"1","0"))) -> - | G48: =IF(BC48="","0","1") -> 1 | H48: SurveySubmission-37zTrDLgwNEf0J1KDqpAUwC0X2R | I48: 2026-01-08 20:44:56.828+00 | K48: CASA DO FITNESS | L48: AXATAOHVRWTQC | M48: Gabriel Fortes | N48: gabriel.fortes@casadofitness.com.br | O48: Ambos | P48: Nem satisfeito, nem insatisfeito | Q48: Satisfeito | R48: Concordo plenamente | S48: Concordo parcialmente | T48: Recomendações Estratégicas -- Importante Assistência com Resolução de Problemas -- Muito importante Estratégia com Promoções -- Importante Gerenciamento e suporte de catálogo -- Muito importante Suporte com gerenciamento de inventário -- Importante Suporte com estratégia para novos produtos -- Importante | V48: Naiara | W48: Muito satisfeito | X48: Meu consultor entende do meu negócio -- Concordo parcialmente Meu consultor entende as necessidades do meu negócio com o programa SAS -- Concordo parcialmente Meu consultor entende sobre a minha categoria de venda -- Concordo parcialmente Meu consultor fornece recomendações estratégicas -- Concordo parcialmente Meu consultor tem conhecimento dos recursos do Seller Central -- Concordo parcialmente Meu consultor é responsivo via email -- Concordo plenamente Meu consultor se comunica por escrito de forma clara -- Concordo plenamente | Y48: No momento tudo corre bem. A troca de consultor é recente então é totalmente compreensivo a fase de adaptação a um novo negocio. | Z48: Yes | AA48: 4 | AC48: No | AF48: No | AI48: ["Ajuda na resolução de problemas operacionais","Conversão (qualidade do catálogo, preços, listatem)","Promoções (ofertas, cupons, eventos)","Seleção (recomendação de produtos, oportunidades)","Marca (registro, proteção, conteúdo A+, loja oficial)","Advertising (anúncios patrocinados)","Logística (FBA, FBA-Onsite, DBA, logística própria)"] | AK48: Muito importante | AL48: Muito importante | AM48: Muito importante | AO48: Rodrigo | AP48: Muito satisfeito | AQ48: Concordo plenamente | AR48: Concordo plenamente | AS48: Concordo plenamente | AT48: Concordo plenamente | AU48: Concordo plenamente | AV48: Concordo plenamente | AW48: Concordo plenamente | AY48: NÃ£o | BB48: Sim | BC48: Muito satisfeito | BE48: NÃ£o | BH48: 5 | BI48: 6 | BJ48: 7 | BK48: 4 | BL48: 1 | BM48: 3 | BN48: 2 | BP48: Email Address
A49: 191336978502 | B49: ITALLE ORIGINAL COFFEE | C49: gomrodrd | D49: =IF(C49="","0","1") -> 1 | E49: =IFERROR(IF(VLOOKUP(A49,Base!AA:AA,1,0)>0,"1","0"),"0") -> 1 | F49: =IF(OR(C49="",E49="0"),"-",IF(BC49="","-",IF(OR(BC49="Muito satisfeito",BC49="Satisfeito"),"1","0"))) -> 1 | G49: =IF(BC49="","0","1") -> 1 | H49: SurveySubmission-37zi8LMK5iLUQn0khInXtIUQjmZ | I49: 2026-01-08 22:42:19.147+00 | K49: ITALLE ORIGINAL COFFEE | L49: A2U7A6WGAKUET3 | M49: Gustavo Eugenio Nassif | N49: contato@cafeitalle.com.br | O49: Dono de marca | P49: Muito satisfeito | Q49: Muito satisfeito | R49: Concordo plenamente | S49: Concordo plenamente | T49: Recomendações Estratégicas -- Muito importante Assistência com Resolução de Problemas -- Muito importante Estratégia com Promoções -- Muito importante Gerenciamento e suporte de catálogo -- Muito importante Suporte com gerenciamento de inventário -- Muito importante Suporte com estratégia para novos produtos -- Muito importante | V49: Julia de Brito | W49: Muito satisfeito | X49: Meu consultor entende do meu negócio -- Concordo plenamente Meu consultor entende as necessidades do meu negócio com o programa SAS -- Concordo plenamente Meu consultor entende sobre a minha categoria de venda -- Concordo plenamente Meu consultor fornece recomendações estratégicas -- Concordo plenamente Meu consultor tem conhecimento dos recursos do Seller Central -- Concordo plenamente Meu consultor é responsivo via email -- Concordo plenamente Meu consultor se comunica por escrito de forma clara -- Concordo plenamente | Z49: Yes | AA49: 5 | AC49: Yes | AD49: 5 | AF49: Yes | AG49: 5 | AI49: ["Promoções (ofertas, cupons, eventos)","Ajuda na resolução de problemas operacionais","Advertising (anúncios patrocinados)","Logística (FBA, FBA-Onsite, DBA, logística própria)","Conversão (qualidade do catálogo, preços, listatem)","Marca (registro, proteção, conteúdo A+, loja oficial)","Seleção (recomendação de produtos, oportunidades)"] | AK49: Muito importante | AL49: Muito importante | AM49: Muito importante | AN49: Acredito que nÃ£o tenha a ver com o SAS, mas sim a nova politica de suprimir as ofertas que julgam nÃ£o serem as melhores, isso basicamente Ã© a pior politica que pode existir e nenhum canal faz isso. Todos perdemos vendas e mesmo assim a Amazon insiste nessa politica. | AO49: Rodrigo Portela | AP49: Muito satisfeito | AQ49: Concordo plenamente | AR49: Concordo plenamente | AS49: Concordo plenamente | AT49: Concordo plenamente | AU49: Concordo plenamente | AV49: Concordo plenamente | AW49: Concordo plenamente | AX49: Novamente, nÃ£o tem a ver com o consultor e sim com a nova politica de suprimir ofertas, muito ruim para todos e isso precisa ser revista o quanto antes. | AY49: Sim | AZ49: Muito satisfeito | BA49: Ajuda com as ofertas suprimidas, mas de uma forma simples | BB49: Sim | BC49: Muito satisfeito | BD49: SAS operacional tem ajudado muito, entendemos que nem tudo ele pode resolver, mas ele tem feito o possÃ­vel. | BE49: Sim | BF49: Muito satisfeito | BG49: NÃ£o temos tanto contato com ele, pois temos uma agÃªncia que faz essa ponte, mas ainda assim quando foi necessÃ¡rio fomos ajudados. | BH49: 5 | BI49: 4 | BJ49: 6 | BK49: 7 | BL49: 1 | BM49: 3 | BN49: 2 | BO49: De custo de envio e comissÃ£o aplicada em cada produto. | BP49: Email Address
